Workbook

Sheet Instructions
B2: Model Instructions & Color Coding
B4: Purpose of This Model
B5: This discounted cash flow (DCF) model is designed to estimate the intrinsic value of Walton Hi-Tech Industries PLC. It integrates a detailed, driver-based forecast of the company's financial statements to determine a fair value per share, providing a data-driven foundation for investment analysis.
B9: Model Structure
B10: The model is built on a three-statement framework (Income Statement, Balance Sheet, Cash Flow Statement) and follows a logical flow:
B11: 1. Assumptions: All forecasting drivers are input here.
B12: 2. Financial Statements: The model projects future performance based on the drivers.
B13: 3. Valuation: The projected free cash flows are discounted to present value.
B15: Color Coding & Conventions
B16: To ensure clarity and ease of use, please adhere to the following color-coding system:
B18: Color | C18: Meaning
B19: Blue 🔵 | C19: Hard-coded Input / Assumption
B20: Black ⚫ | C20: Formula / Calculation
B21: Green 🟢 | C21: Link to Another Sheet

Sheet Assumptions
B2: Assumptions:
D4: 2026 | E4: 2027 | F4: 2028 | G4: 2029 | H4: 2030 | I4: 2031 | J4: 2032 | K4: 2033 | L4: 2034 | M4: 2035 | O4: Justification for DCF Model
C5: 1. REVENUE DRIVERS
C6: Freezer, Refrigerator & Compressor | D6: 0.03 | E6: 0.03 | F6: 0.03 | G6: 0.03 | H6: 0.03 | I6: 0.025 | J6: 0.025 | K6: 0.025 | L6: 0.02 | M6: 0.02 | O6: Moderate growth as mature market, 65–75% market share, low incremental volume growth & margin pressure due to VAT (7.5%)
C7: Air Conditioner | D7: 0.08 | E7: 0.07 | F7: 0.06 | G7: 0.06 | H7: 0.06 | I7: 0.055 | J7: 0.05 | K7: 0.05 | L7: 0.04 | M7: 0.04 | O7: Moderate but volatile growth as high sensitivity to economic cycles, climate change so long-term positive, VAT on AC
C8: Television | D8: 0.025 | E8: 0.02 | F8: 0.015 | G8: 0.015 | H8: 0.015 | I8: 0.01 | J8: 0.01 | K8: 0.01 | L8: 0.01 | M8: 0.01 | O8: Low growth as TV market shifting to imported premium brands (Samsung, LG), local players losing share & cost pressures from display imports
C9: Electrical Appliances (EAP) | D9: 0.1 | E9: 0.08 | F9: 0.07 | G9: 0.06 | H9: 0.05 | I9: 0.05 | J9: 0.05 | K9: 0.05 | L9: 0.05 | M9: 0.05 | O9: High growth as fast-growing segment & long-term growth still strong (middle-class growth)
C10: Home Appliances (HAP) | D10: 0.1 | E10: 0.09 | F10: 0.08 | G10: 0.07 | H10: 0.06 | I10: 0.05 | J10: 0.04 | K10: 0.04 | L10: 0.04 | M10: 0.04 | O10: Moderate growth as demand driven by middle class expansion
C11: Elevator | D11: 0.15 | E11: 0.14 | F11: 0.12 | G11: 0.1 | H11: 0.09 | I11: 0.08 | J11: 0.07 | K11: 0.06 | L11: 0.05 | M11: 0.04 | O11: Steady growth as long-term opportunity & dependent on construction sector (currently weak)
C12: Cable | D12: 0.12 | E12: 0.1 | F12: 0.08 | G12: 0.07 | H12: 0.06 | I12: 0.05 | J12: 0.05 | K12: 0.05 | L12: 0.05 | M12: 0.05 | O12: Steady growth as new factory integration and domestic substitution for imports
C13: Service Parts | D13: 0.18 | E13: 0.16 | F13: 0.14 | G13: 0.12 | H13: 0.1 | I13: 0.08 | J13: 0.07 | K13: 0.06 | L13: 0.06 | M13: 0.06 | O13: High sustainable growth as product installed base increasing & recurring, stable revenue source
C14: Others (Mold, Die, SBN) | D14: 0.08 | E14: 0.07 | F14: 0.06 | G14: 0.05 | H14: 0.05 | I14: 0.04 | J14: 0.04 | K14: 0.04 | L14: 0.04 | M14: 0.04 | O14: Moderate growth as B2B component sales
C15: WDIL IT Products | D15: 0 | E15: 0.3 | F15: 0.25 | G15: 0.2 | H15: 0.15 | I15: 0.1 | J15: 0.09 | K15: 0.08 | L15: 0.07 | M15: 0.06 | O15: Strong growth as strong IT portfolio, Bangladesh IT demand rising & synergies with Walton distribution
C16: Lithium Battery | E16: 0.25 | F16: 0.2 | G16: 0.15 | H16: 0.12 | I16: 0.1 | J16: 0.1 | K16: 0.08 | L16: 0.08 | M16: 0.08 | O16: High growth and then stabilizes in the long-term
C17: VAT Rate | D17: 0.08 | E17: 0.08 | F17: 0.08 | G17: 0.08 | H17: 0.08 | I17: 0.08 | J17: 0.08 | K17: 0.08 | L17: 0.08 | M17: 0.08 | O17: Kept constant per regulatory baseline
C18: WDIL IT Products Revenue | E18: =1015.91*(1+E15) -> 1320.683 | O18: Post-acquision revenue (Digi-Tech's revenue tk 1015.91 cr during 2024)
C19: Lithium Battery Revenue | D19: =(80000*8000)/10000000 -> 64 | O19: 80,000 units at a industry average price of tk. 8000 (estimated)
C21: 2. PROFITABILITY (% of Sales)
C22: COGS (% of Sales) | D22: 0.64 | E22: 0.64 | F22: 0.63 | G22: 0.63 | H22: 0.63 | I22: 0.62 | J22: 0.62 | K22: 0.6 | L22: 0.6 | M22: 0.6 | O22: Vertical Integration Benefit: Slight improvement from as cost controls and high-margin products (batteries) offset inflation.
C23: SG&A Expenses (% of Sales) | D23: 0.12 | E23: 0.117 | F23: 0.114 | G23: 0.112 | H23: 0.11 | I23: 0.1 | J23: 0.1 | K23: 0.1 | L23: 0.1 | M23: 0.1 | O23: High due to competition but improving gradually from 13.05% (2025) as merger synergies are realized.
C24: Merger integration costs (% sales) | E24: 50 | O24: One-time costs (50 crore) for Digi-Tech merger integration. (estimated 10-year amortization, starts FY 2027)
C25: D&A (% of Opening Assets) | D25: ='Ratio Analysis'!$I$44 -> 0.032232189 | E25: ='Ratio Analysis'!$I$44 -> 0.032232189 | F25: ='Ratio Analysis'!$I$44 -> 0.032232189 | G25: ='Ratio Analysis'!$I$44 -> 0.032232189 | H25: ='Ratio Analysis'!$I$44 -> 0.032232189 | I25: ='Ratio Analysis'!$I$44 -> 0.032232189 | J25: ='Ratio Analysis'!$I$44 -> 0.032232189 | K25: ='Ratio Analysis'!$I$44 -> 0.032232189 | ... M25: ='Ratio Analysis'!$I$44 -> 0.032232189 | O25: Historical Average
C26: Effective Tax Rate* | D26: =D42 -> 0 | E26: =D43 -> 0 | F26: =D44 -> 0 | G26: =D45 -> 0.0675 | H26: =D46 -> 0.0675 | I26: =H26 -> 0.0675 | J26: =D48 -> 0.225 | K26: =J26 -> 0.225 | L26: =K26 -> 0.225 | M26: =L26 -> 0.225 | O26: Graduated schedule based on disclosed changes to hi-tech park and manufacturing taxes.
C28: 4. CAPITAL & FINANCING
C29: CapEx % of Revenue | D29: ='Ratio Analysis'!$I$45 -> 0.078610096 | E29: ='Ratio Analysis'!$I$45 -> 0.078610096 | F29: ='Ratio Analysis'!$I$45 -> 0.078610096 | G29: ='Ratio Analysis'!$I$45 -> 0.078610096 | H29: ='Ratio Analysis'!$I$45 -> 0.078610096 | I29: ='Ratio Analysis'!$I$45 -> 0.078610096 | J29: ='Ratio Analysis'!$I$45 -> 0.078610096 | K29: ='Ratio Analysis'!$I$45 -> 0.078610096 | ... M29: ='Ratio Analysis'!$I$45 -> 0.078610096 | O29: In line with historical spending to support growth. [Regular Capex (% of revenue)]
C31: 5. Lithium Project CAPEX (BDT Crore) | D31: 113.66 | E31: 0 | F31: 0 | G31: 0 | H31: 0 | I31: 0 | J31: 0 | K31: 0 | L31: 0 | M31: 0 | O31: One-time CAPEX (BDT 113.66 Cr) for the battery project. [10-year amortization estimated]
C32: 6. Interest Rate on Debt | D32: =$D$54 -> 0.1192 | E32: =$D$54 -> 0.1192 | F32: =$D$54 -> 0.1192 | G32: =$D$54 -> 0.1192 | H32: =$D$54 -> 0.1192 | I32: =$D$54 -> 0.1192 | J32: =$D$54 -> 0.1192 | K32: =$D$54 -> 0.1192 | ... M32: =$D$54 -> 0.1192 | O32: A pre-tax cost of debt of 11.5% is assumed.
C33: 7. Dividend Payout Ratio | D33: 0.4 | E33: 0.4 | F33: 0.4 | G33: 0.4 | H33: 0.4 | I33: 0.4 | J33: 0.4 | K33: 0.4 | L33: 0.4 | M33: 0.4 | O33: New Policy: Reflects the permanent shift down from historical levels to retain earnings for growth.
C35: 8. Bangladesh 10Y Government Bond | D35: 0.1042 | O35: Bangladesh Bank [as of December 1st 2025]
C36: 9. Country Default Risk | D36: 0.081370487 | O36: NYU Stern Professor Aswath Damodaran, [July, 2025]
C37: 10. Equity Risk Premium (Bangladesh), ERP | D37: 0.1235 | O37: NYU Stern Professor Aswath Damodaran, [July, 2025]
C38: 11. Terminal Growth Rate (g) | D38: 0.04 | O38: A terminal growth rate of 4.0% is assumed. This is a conservative estimate that reflects the company's transition to a mature state by the end of the forecast period. It is below the long-term nominal GDP growth rate of Bangladesh, ensuring the company does not outgrow the economy in perpetuity.
C40: *Tax Rate Assumptions:
C41: Year | D41: Projected Tax Rate | E41: Justification for DCF Model
C42: FY 2026 | D42: 0 | E42: 100% tax exemption on business profits
C43: FY 2027 | D43: 0 | E43: 100% tax exemption on business profits
C44: FY 2028 | D44: 0 | E44: 100% tax exemption on business profits
C45: FY 2029 | D45: 0.0675 | E45: 70% tax exemption [ 22.5% * (1 - 0.70)]
C46: FY 2030 | D46: 0.0675 | E46: 70% tax exemption
C47: FY 2031 | D47: 0.0675 | E47: 70% tax exemption
C48: FY 2032 + (Terminal) | D48: 0.225 | E48: Full statutory rate applies
C50: *Cost of Debt:
C51: Pre-tax Cost of Debt:
C52: Bangladesh 10Y Government Bond | D52: =D35 -> 0.1042
C53: Corporate Credit Spread | D53: 0.015
C54: Total | D54: =SUM(D52:D53) -> 0.1192

Sheet Data
B2: Company Name | C2: Walton Hi-Tech Industries PLC
B3: Ticker: | C3: WALTONHIL
B4: Exchange: | C4: DSE
B5: Industry: | C5: Household Appliances
B6: Sector: | C6: Consumer Durables
B7: Face Value Per Share | C7: 10
B8: Current Share Price BDT | C8: 376.6
B9: Market Cap BDT (mn) | C9: 126057.57
B10: Shares Outstanding | C10: 333221177
B12: Income Statement
B13: Particulars | C13: 2019 | D13: 2020 | E13: 2021 | F13: 2022 | G13: 2023 | H13: 2024 | I13: 2025
B14: Sales revenue, net | C14: 51773237116 | D14: 41079248267 | E14: 69949925813 | F14: 81681681284 | G14: 66374271405 | H14: 75121154616 | I14: 70822475704
B15: Purchase | C15: 25277241920 | D15: 27803538581 | E15: 34270695635 | F15: 54876142790 | G15: 27467893812 | H15: 35248800151 | I15: 40996136389
B16: Cost of goods sold | C16: 30805628408 | D16: 25423508810 | E16: 43515489526 | F16: 55146823463 | G16: 43022875679 | H16: 46473228347 | I16: 45291678432
B17: Gross profit | C17: 20967608708 | D17: 15655739458 | E17: 26434436287 | F17: 26534857821 | G17: 23351395726 | H17: 28647926269 | I17: 25530797272
B18: Operating expenses | C18: 4067567881 | D18: 4652465206 | E18: 7089112340 | F18: 9184521666 | G18: 7782901962 | H18: 9850900444 | I18: 10709513504
B19: Selling & distribution expenses | C19: 3239850530 | D19: 3602364329 | E19: 6004705364 | F19: 7795190297 | G19: 6409291118 | H19: 8293518089 | I19: 9014387103
B20: Administrative expenses | C20: 827617351 | D20: 1050100877 | E20: 1084406976 | F20: 1389331369 | G20: 1373610844 | H20: 1557382355 | I20: 1695126401
B21: Depreciation | C21: 1331810588 | D21: 1541134096 | E21: 1676106067 | F21: 1924661890 | G21: 2141649331 | H21: 2508935876 | I21: 2952947737
B22: Amortization | C22: 18065970 | D22: 16341394 | E22: 11509797 | F22: 3946229 | G22: 5325234 | H22: 7022841 | I22: 7863317
B23: Operating profit | C23: 16900040827 | D23: 11003274252 | E23: 19345323947 | F23: 17350336155 | G23: 15571493764 | H23: 18797025825 | I23: 14821283768
B24: Other income/Miscellaneous income | C24: - | D24: - | E24: 84330796 | F24: 79765294 | G24: - | H24: -
B25: Non-operating income | C25: 98108941 | D25: -13131240 | E25: 511456412 | F25: 270571805 | G25: 201930120 | H25: -94598252 | I25: 266614954
B26: Finance income | C26: - | D26: - | E26: - | F26: - | G26: 32175044 | H26: 171221879 | I26: 290334678
B27: Finance costs | C27: 1493855820 | D27: 2243549865 | E27: 1245679758 | F27: 4738325106 | G27: 7535855991 | H27: 4591235836 | I27: 4484038732
B28: Profit before WPPF & Tax | C28: 15504373948 | D28: 8746593145 | E28: 18695434397 | F28: 12962348148 | G28: 8269742937 | H28: 14282421616 | I28: 10894194667
B29: Contribution to WPPF | C29: 738303521 | D29: 416504436 | E29: 890258781 | F29: 617254674 | G29: 393654464 | H29: 680115315 | I29: 518771175
B30: Profit before taxation | C30: 14766070427 | D30: 8330088710 | E30: 17805175616 | F30: 12345093474 | G30: 7876088473 | H30: 13602306301 | I30: 10375423492
B31: Income tax expense | C31: -1004931824 | D31: -1065594991 | E31: -1413136905 | F31: -178942918 | G31: -46309266 | H31: -37046974 | I31: -9263129
B32: Current Tax | C32: 848151353 | D32: -744892973 | E32: -2154739525 | F32: -65269058 | G32: -47752505 | H32: -57026659 | I32: -10227195
B33: Deferred Tax | C33: 156780471 | D33: -320702019 | E33: 741602620 | F33: -113673860 | G33: 1443239 | H33: 19979685 | I33: 964067
B34: Profit after tax | C34: 13761138603 | D34: 7264493719 | E34: 16392038712 | F34: 12166150557 | G34: 7826780005 | H34: 13565259327 | I34: 10366160364
B35: Earnings Per Share (EPS) | C35: 45.67 | D35: 24.21 | E35: 54.11 | F35: 40.16 | G35: 25.84 | H35: 44.78 | I35: 34.22
B38: Balance Sheet
B39: Particulars | C39: 2019 | D39: 2020 | E39: 2021 | F39: 2022 | G39: 2023 | H39: 2024 | I39: 2025
B40: Property, plant and equipment, net | C40: 57575574816 | D40: 59712087153 | E40: 62295280025 | F40: 65475136944 | G40: 68824874693 | H40: 70863873952 | I40: 77180420324
B41: Intangible assets | C41: 29332786 | D41: 23040791 | E41: 13362588 | F41: 13053850 | G41: 19217454 | H41: 16019226 | I41: 46082639
B42: Right-of-Use (ROU) asset | C42: - | D42: - | E42: - | F42: 207685994 | G42: 213136270 | H42: 201866955 | I42: 211722011
B43: Other Non-current assets | C43: 2131266850 | D43: 3771797260 | E43: 3943802332 | F43: 6446187658 | G43: 7351736250 | H43: 7437964575 | I43: 7247599337
B44: Investments | C44: 494171979 | D44: 594806302 | F44: - | G44: - | H44: -
B45: Total Non-current assets | C45: 60230346423 | D45: 64101851526 | E45: 66252444945 | F45: 72142064446 | G45: 76408964667 | H45: 78519724708 | I45: 84685824311
B46: Inventories | C46: 13530290769 | D46: 21833256222 | E46: 24130561864 | F46: 36197619159 | G46: 25573533341 | H46: 26182663525 | I46: 29648739753
B47: Accounts Receivable | D47: 23432843592 | E47: 32828073635 | F47: 41846214575 | G47: 34608612021 | H47: 37153106717 | I47: 35562922175
B48: Other Receivables | D48: 28119857 | E48: 53861380 | F48: 47964310 | G48: 66336365 | H48: 93522952 | I48: 503317824
B49: Trade and other receivables | C49: 24478836553 | D49: 23863541822 | E49: 32881935015 | F49: 41894178885 | G49: 34674948386 | H49: 37246629669 | I49: 36066239999
B50: Investment | C50: - | D50: - | E50: 1106022865 | F50: 1186987977 | G50: 1033741904 | H50: 778283932 | I50: 365800204
B51: Advances, deposits and prepayments | C51: 3574831967 | D51: 4438454103 | E51: 5008968072 | F51: 5536502855 | G51: 5517637114 | H51: 7671704651 | I51: 1486154474
B52: Short term investments | C52: 582901194 | D52: 616911527 | E52: 1365549229 | F52: 278215010 | G52: 313513014 | H52: 305850540 | I52: 297320659
B53: Cash and cash equivalents | C53: 1029902851 | D53: 1466979290 | E53: 3703825657 | F53: 2321365628 | G53: 2417232161 | H53: 6547326350 | I53: 5065456980
B54: Total Current assets | C54: 43197763333 | D54: 52219142964 | E54: 68196862702 | F54: 87414869514 | G54: 69530605920 | H54: 78732458667 | I54: 72929712069
B55: Total assets | C55: 103428109756 | D55: 116421004490 | E55: 134449307647 | F55: 159556933960 | G55: 145939570587 | H55: 157252183375 | I55: 157615536380
B56: Share Capital | C56: 3000000000 | D56: 3000000000 | E56: 3029283430 | F56: 3029283430 | G56: 3029283430 | H56: 3029283430 | I56: 3029283430
B57: Share Premium | C57: - | D57: - | E57: 931683717 | F57: 931683717 | G57: 931683717 | H57: 931683717 | I57: 931683717
B58: Revaluation Reserve | C58: 31390563206 | D58: 31361505710 | E58: 31332448213 | F58: 31303390716 | G58: 30759669655 | H58: 30730612160 | I58: 33761916711
B59: Retained Earnings | C59: 38507504162 | D59: 44881055377 | E59: 59096490476 | F59: 66119942829 | G59: 69403503630 | H59: 80209560207 | I59: 83370439512
B60: Share Money Deposit | C60: - | D60: 608657805 | E60: - | F60: - | G60: - | H60: -
B61: Equity attributable to owners of the company | C61: 72978067368 | D61: 79952218892 | E61: 94389905836 | F61: 101384300692 | G61: 104124140432 | H61: 114901139514 | I61: 121093323370
B62: Total equity | C62: 72978067368 | D62: 79952218892 | E62: 94389905836 | F62: 101384300692 | G62: 104124140432 | H62: 114901139514 | I62: 121093323370
B63: Long Term Borrowings/Loan | C63: 6194630678 | D63: 3944350940 | E63: 3413927312 | F63: 2584065883 | G63: 5144327566 | H63: 5784668868 | I63: 5625548221
B64: Deferred Tax Liabilities | C64: 789268498 | D64: 1109970514 | E64: 365462144 | F64: 477683129 | G64: 989450580 | H64: 967146295 | I64: 2019404737
B65: Lease Liability | C65: - | D65: - | E65: - | F65: 189487463 | G65: 196120077 | H65: 186957709 | I65: 199469372
B66: UNDP Fund | C66: 95004333 | D66: 185401084 | E66: 77603084 | F66: 57116262 | G66: 74329381 | H66: 74068576 | I66: 78824932
B67: Total Non-current liabilities | C67: 7078903607 | D67: 5238722538 | E67: 3856992540 | F67: 3308352737 | G67: 6404227604 | H67: 7012841448 | I67: 7923247262
B68: Trade and other payables | C68: 876557103 | D68: 2274036392 | E68: 2923322846 | F68: 4581457210 | G68: 3058009690 | H68: 3630113554 | I68: 2403051804
B69: Short term loan | C69: 16370583014 | D69: 22482089404 | E69: 23879414713 | F69: 42659073516 | G69: 24096051506 | H69: 21243601979 | I69: 17883976956
B70: Current Portion of Long Term Borrowings/Loan | C70: 2837393300 | D70: 1913765877 | E70: 2352544083 | F70: 1331294074 | G70: 1695951363 | H70: 2513262116 | I70: 2948217565
B71: Current portion of lease obligation/ Finance | C71: - | D71: - | E71: - | F71: 28394840 | G71: 35666642 | H71: 41207819 | I71: 39624404
B72: Accruals and provisions | C72: 3286605474 | D72: 4559171387 | E72: 7045580130 | F72: 6261220114 | G72: 6521744872 | H72: 7904264162 | I72: 5316613766
B73: Unclaimed Dividend | C73: - | D73: - | E73: 1547499 | F73: 2840777 | G73: 3778478 | H73: 5752783 | I73: 7481253
B74: Total Current liabilities | C74: 23371138891 | D74: 31229063060 | E74: 36202409271 | F74: 54864280531 | G74: 35411202551 | H74: 35338202413 | I74: 28598965748
B75: Total equity and liabilities | C75: 103428109766 | D75: 116421004490 | E75: 134449307647 | F75: 159556933960 | G75: 145938570587 | H75: 157252183375 | I75: 157615536380
B76: Net Asset Value (NAV) | C76: 243.16 | D76: 264.48 | E76: 311.59 | F76: 334.68 | G76: 343.73 | H76: 379.3 | I76: 399.74
B77: Net Asset Value (NAV) including Revaluation Surplus | C77: - | D77: - | E77: 208.16 | F77: 334.68 | G77: 343.73 | H77: 379.3 | I77: 399.74
B78: Net Asset Value (NAV) excluding Revaluation Surplus | C78: - | D78: - | E78: 311.59 | F78: 231.34 | G78: 242.18 | H78: 277.86 | I78: 288.29
B79: Number of Shares Outstanding | C79: 300000000 | D79: 302382789 | E79: 302928343 | F79: 302928343 | G79: 302928343 | H79: 302928343 | I79: 302928343
B80: Dividend Per Share | C80: 3 | D80: 20 | E80: 25 | F80: 25 | G80: 30 | H80: 35 | I80: 17.5
B83: Cashflow Statement (Direct Method - from Annual Reports)
B84: Particulars | C84: 2019 | D84: 2020 | E84: 2021 | F84: 2022 | G84: 2023 | H84: 2024 | I84: 2025
B85: Payroll and Other Income | C85: -3012672489 | D85: -3815799702 | E85: - | F85: - | G85: - | H85: - | I85: -
B86: Cash Received from customers | C86: 36482207357 | D86: 43353007765 | E86: 62583809304 | F86: 75328836761 | G86: 78005422848 | H86: 77419988481 | I86: 78507560112
B87: Cash Receipts from Other Income | C87: 2282441 | D87: 505309 | E87: 20512137 | F87: 133258190 | G87: 122427285 | H87: 44492106 | I87: -300489166
B88: Payment to Suppliers for Goods, Services and Others | C88: -31546920460 | D88: -30595598253 | E88: -42885618075 | F88: -66973469260 | G88: -33633766254 | H88: -47829102523 | I88: -45919169501
B89: Payment to employees | C89: - | D89: - | E89: -5307326990 | F89: -7113919709 | G89: -6426803156 | H89: -7264260790 | I89: -8321592870
B90: Cash generated from operation | C90: =SUM(C85:C89) -> 1924896849 | D90: =SUM(D85:D89) -> 8942115119 | E90: =SUM(E85:E89) -> 14411376376 | F90: =SUM(F85:F89) -> 1374705982 | G90: =SUM(G85:G89) -> 38067280723 | H90: =SUM(H85:H89) -> 22371117274 | I90: =SUM(I85:I89) -> 23966308575
B91: Payment for WPPF | C91: -190620661 | D91: -738303522 | E91: -416504436 | F91: -890258781 | G91: -617254674 | H91: -393654464 | I91: -680115315
B92: Payment against Tax and VAT | C92: -1446237719 | D92: -3160471699 | E92: -4329533333 | F92: -2880161918 | G92: -3569879509 | H92: -4721414355 | I92: -5655694493
B93: A. Net cash from operating activities | C93: =SUM(C90:C92) -> 288038469 | D93: =SUM(D90:D92) -> 5043339898 | E93: =SUM(E90:E92) -> 9665338607 | F93: =SUM(F90:F92) -> -2395714717 | G93: =SUM(G90:G92) -> 33880146540 | H93: =SUM(H90:H92) -> 17256048455 | I93: =SUM(I90:I92) -> 17630498767
B95: Acquisition of property, plant and equipment | C95: -4551090575 | D95: -5508056013 | E95: -4595529874 | F95: -7618780348 | G95: -6424773522 | H95: -4800875705 | I95: -5196559175
B96: Interest income from FDR & IPO | C96: 84925786 | D96: 68477435 | E96: 72690206 | F96: 95872412 | G96: 30659852 | H96: 154894895 | I96: 303774449
B97: Encash in long term/term deposits/ Increase/(Decrease) in Long term and other investment / Long Term Investment (Payment)/ Encasement-Net | C97: 280000000 | D97: - | E97: - | F97: - | G97: - | H97: -
B98: Encash in short term/term deposits | C98: 318816520 | D98: -34010334 | E98: -748637702 | F98: 1087334219 | G98: -35298004 | H98: 7662474 | I98: 8529881
B99: Received from Dividend and Other lnvestment lncome | C99: 34655224 | D99: 17291915 | E99: 129333817 | F99: 111353074 | G99: 50758387 | H99: 34690439 | I99: 57467186
B100: Encashment / (Payment) of Investments in Securities | C100: -30486470 | D100: -265221435 | E100: -271375037 | F100: -151424263 | G100: 135402706 | H100: 18925408 | I100: 433082545
B101: Payment for Intangible Assets | C101: -7554445 | D101: -14637674 | E101: -1831593 | F101: -3637488 | G101: -11498840 | H101: -3824614 | I101: -37926730
B102: Proceeds from sale of property, plant and equipment | C102: - | D102: 4639501 | E102: 117546308 | F102: 7850469 | G102: 18922211 | H102: 4946368 | I102: 586024
B103: B. Net cash from/(used in) investing activities | C103: =SUM(C95:C102) -> -3870733960 | D103: =SUM(D95:D102) -> -5731516605 | E103: =SUM(E95:E102) -> -5297803875 | F103: =SUM(F95:F102) -> -6471431925 | G103: =SUM(G95:G102) -> -6235827210 | H103: =SUM(H95:H102) -> -4583580735 | I103: =SUM(I95:I102) -> -4431045820
B105: Payment for Financial Costs | C105: -1402662630 | D105: -1693864902 | E105: -1476116032 | F105: -4301028940 | G105: -7353240991 | H105: -4373088074 | I105: -4388111473
B106: Share Capital Proceed through IPO | C106: - | D106: - | E106: 29283430 | F106: - | G106: - | H106: -
B107: Share money refund/deposit | C107: - | D107: 609657805 | E107: 322025912 | F107: - | G107: - | H107: -
B108: Dividends paid | C108: - | D108: -900000000 | E108: -2307019361 | F108: -5173208575 | G108: -4572791875 | H108: -2790584847 | I108: -7236663155
...

Sheet Historical FS
B2: Historical Financial Statements - Walton Hi-Tech Industries PLC
B3: Years | C3: 2021 | D3: 2022 | E3: 2023 | F3: 2024 | G3: 2025 | H3: 7-Y Trend | I3: Average
I4: BDT in Crore
A5: # | B5: Income Statement
B6: Net Sales Revenue | C6: =IFERROR(Data!E188/10000000,0) -> 6994.9926 | D6: =IFERROR(Data!F188/10000000,0) -> 8168.1681 | E6: =IFERROR(Data!G188/10000000,0) -> 6637.4271 | F6: =IFERROR(Data!H188/10000000,0) -> 7512.1155 | G6: =IFERROR(Data!I188/10000000,0) -> 7082.2476 | I6: =AVERAGE(C6:G6) -> 7278.9902
B7: COGS | C7: =IFERROR(Data!E16/10000000,0) -> 4351.549 | D7: =IFERROR(Data!F16/10000000,0) -> 5514.6823 | E7: =IFERROR(Data!G16/10000000,0) -> 4302.2876 | F7: =IFERROR(Data!H16/10000000,0) -> 4647.3228 | G7: =IFERROR(Data!I16/10000000,0) -> 4529.1678 | I7: =AVERAGE(C7:G7) -> 4669.0019
B8: Gross Profit | C8: =IFERROR(Data!E17/10000000,0) -> 2643.4436 | D8: =IFERROR(Data!F17/10000000,0) -> 2653.4858 | E8: =IFERROR(Data!G17/10000000,0) -> 2335.1396 | F8: =IFERROR(Data!H17/10000000,0) -> 2864.7926 | G8: =IFERROR(Data!I17/10000000,0) -> 2553.0797 | I8: =AVERAGE(C8:G8) -> 2609.9883
B9: Operating expenses | C9: =C10+C11 -> 708.91123 | D9: =D10+D11 -> 918.45217 | E9: =E10+E11 -> 778.2902 | F9: =F10+F11 -> 985.09004 | G9: =G10+G11 -> 1070.9514 | I9: =AVERAGE(C9:G9) -> 892.339
B10: Selling & distribution expenses | C10: =IFERROR(Data!E19/10000000,0) -> 600.47054 | D10: =IFERROR(Data!F19/10000000,0) -> 779.51903 | E10: =IFERROR(Data!G19/10000000,0) -> 640.92911 | F10: =IFERROR(Data!H19/10000000,0) -> 829.35181 | G10: =IFERROR(Data!I19/10000000,0) -> 901.43871 | I10: =AVERAGE(C10:G10) -> 750.34184
B11: Administrative expenses | C11: =IFERROR(Data!E20/10000000,0) -> 108.4407 | D11: =IFERROR(Data!F20/10000000,0) -> 138.93314 | E11: =IFERROR(Data!G20/10000000,0) -> 137.36108 | F11: =IFERROR(Data!H20/10000000,0) -> 155.73824 | G11: =IFERROR(Data!I20/10000000,0) -> 169.51264 | I11: =AVERAGE(C11:G11) -> 141.99716
B12: EBITDA | C12: =C8-C9+C13 -> 2103.294 | D12: =D8-D9+D13 -> 1927.8944 | E12: =E8-E9+E13 -> 1771.5468 | F12: =F8-F9+F13 -> 2131.2985 | G12: =G8-G9+G13 -> 1778.2095 | I12: =AVERAGE(C12:G12) -> 1942.4486
B13: Depreciation & Amortization | C13: =IFERROR((Data!E21+Data!E22)/10000000,0) -> 168.76159 | D13: =IFERROR((Data!F21+Data!F22)/10000000,0) -> 192.86081 | E13: =IFERROR((Data!G21+Data!G22)/10000000,0) -> 214.69746 | F13: =IFERROR((Data!H21+Data!H22)/10000000,0) -> 251.59587 | G13: =IFERROR((Data!I21+Data!I22)/10000000,0) -> 296.08111 | I13: =AVERAGE(C13:G13) -> 224.79937
B14: EBIT | C14: =C12-C13 -> 1934.5324 | D14: =D12-D13 -> 1735.0336 | E14: =E12-E13 -> 1556.8494 | F14: =F12-F13 -> 1879.7026 | G14: =G12-G13 -> 1482.1284 | I14: =AVERAGE(C14:G14) -> 1717.6493
B15: Other income | C15: =IFERROR(Data!E24/10000000,0) -> 8.4330796 | D15: =IFERROR(Data!F24/10000000,0) -> 7.9765294 | E15: =IFERROR(Data!G24/10000000,0) -> 0 | F15: =IFERROR(Data!H24/10000000,0) -> 0 | G15: =IFERROR(Data!I24/10000000,0) -> 0 | I15: =AVERAGE(C15:G15) -> 3.2819218
B16: Non-operating income | C16: =IFERROR(Data!E25/10000000,0) -> 51.145641 | D16: =IFERROR(Data!F25/10000000,0) -> 27.057181 | E16: =IFERROR(Data!G25/10000000,0) -> 20.193012 | F16: =IFERROR(Data!H25/10000000,0) -> -9.4598252 | G16: =IFERROR(Data!I25/10000000,0) -> 26.661495 | I16: =AVERAGE(C16:G16) -> 23.119501
B17: Finance income | C17: =IFERROR(Data!E26/10000000,0) -> 0 | D17: =IFERROR(Data!F26/10000000,0) -> 0 | E17: =IFERROR(Data!G26/10000000,0) -> 3.2175044 | F17: =IFERROR(Data!H26/10000000,0) -> 17.122188 | G17: =IFERROR(Data!I26/10000000,0) -> 29.033468 | I17: =AVERAGE(C17:G17) -> 9.874632
B18: Finance costs | C18: =IFERROR(Data!E27/10000000,0) -> 124.56798 | D18: =IFERROR(Data!F27/10000000,0) -> 473.83251 | E18: =IFERROR(Data!G27/10000000,0) -> 753.5856 | F18: =IFERROR(Data!H27/10000000,0) -> 459.12358 | G18: =IFERROR(Data!I27/10000000,0) -> 448.40387 | I18: =AVERAGE(C18:G18) -> 451.90271
B19: Profit before WPPF & Tax | C19: =IFERROR(Data!E28/10000000,0) -> 1869.5434 | D19: =IFERROR(Data!F28/10000000,0) -> 1296.2348 | E19: =IFERROR(Data!G28/10000000,0) -> 826.97429 | F19: =IFERROR(Data!H28/10000000,0) -> 1428.2422 | G19: =IFERROR(Data!I28/10000000,0) -> 1089.4195 | I19: =AVERAGE(C19:G19) -> 1302.0828
B20: Contribution to WPPF | C20: =IFERROR(Data!E29/10000000,0) -> 89.025878 | D20: =IFERROR(Data!F29/10000000,0) -> 61.725467 | E20: =IFERROR(Data!G29/10000000,0) -> 39.365446 | F20: =IFERROR(Data!H29/10000000,0) -> 68.011532 | G20: =IFERROR(Data!I29/10000000,0) -> 51.877117 | I20: =AVERAGE(C20:G20) -> 62.001088
B21: Earnings Before Tax | C21: =C19-C20 -> 1780.5176 | D21: =D19-D20 -> 1234.5093 | E21: =E19-E20 -> 787.60885 | F21: =F19-F20 -> 1360.2306 | G21: =G19-G20 -> 1037.5423 | I21: =AVERAGE(C21:G21) -> 1240.0817
B22: Tax | C22: =IFERROR(-Data!E31/10000000,0) -> 141.31369 | D22: =IFERROR(-Data!F31/10000000,0) -> 17.894292 | E22: =IFERROR(-Data!G31/10000000,0) -> 4.6309266 | F22: =IFERROR(-Data!H31/10000000,0) -> 3.7046974 | G22: =IFERROR(-Data!I31/10000000,0) -> 0.9263129 | I22: =AVERAGE(C22:G22) -> 33.693984
B23: Net Profit | C23: =IFERROR(Data!E34/10000000,0) -> 1639.2039 | D23: =IFERROR(Data!F34/10000000,0) -> 1216.6151 | E23: =IFERROR(Data!G34/10000000,0) -> 782.678 | F23: =IFERROR(Data!H34/10000000,0) -> 1356.5259 | G23: =IFERROR(Data!I34/10000000,0) -> 1036.616 | I23: =AVERAGE(C23:G23) -> 1206.3278
B24: Number of Shares Outstanding | C24: =IFERROR(Data!E79/10000000,0) -> 30.292834 | D24: =IFERROR(Data!F79/10000000,0) -> 30.292834 | E24: =IFERROR(Data!G79/10000000,0) -> 30.292834 | F24: =IFERROR(Data!H79/10000000,0) -> 30.292834 | G24: =IFERROR(Data!I79/10000000,0) -> 30.292834 | I24: =AVERAGE(C24:G24) -> 30.292834
B25: Earnings per Share | C25: =C23/C24 -> 54.111935 | D25: =D23/D24 -> 40.16181 | E25: =E23/E24 -> 25.837067 | F25: =F23/F24 -> 44.780423 | G25: =G23/G24 -> 34.219843 | I25: =AVERAGE(C25:G25) -> 39.822216
B26: EPS Growth % | D26: =(D25-C25)/C25 -> -0.25780126 | E26: =(E25-D25)/D25 -> -0.35667572 | F26: =(F25-E25)/E25 -> 0.73318521 | G26: =(G25-F25)/F25 -> -0.23583028 | I26: =AVERAGE(C26:G26) -> -0.029280514
B27: Dividend per Share | C27: =IFERROR(Data!E80,0) -> 25 | D27: =IFERROR(Data!F80,0) -> 25 | E27: =IFERROR(Data!G80,0) -> 30 | F27: =IFERROR(Data!H80,0) -> 35 | G27: =IFERROR(Data!I80,0) -> 17.5 | I27: =AVERAGE(C27:G27) -> 26.5
B28: Dividend payout ratio | C28: =C27/C25 -> 0.46200529 | D28: =D27/D25 -> 0.6224819 | E28: =E27/E25 -> 1.1611225 | F28: =F27/F25 -> 0.78159155 | G28: =G27/G25 -> 0.51139919 | I28: =AVERAGE(C28:G28) -> 0.70772008
B29: Retained Earnings | C29: =IFERROR(IF(C25>C27,1-C28,0),0) -> 0.53799471 | D29: =IFERROR(IF(D25>D27,1-D28,0),0) -> 0.3775181 | E29: =IFERROR(IF(E25>E27,1-E28,0),0) -> 0 | F29: =IFERROR(IF(F25>F27,1-F28,0),0) -> 0.21840845 | G29: =IFERROR(IF(G25>G27,1-G28,0),0) -> 0.48860081 | I29: =AVERAGE(C29:G29) -> 0.32450441
A31: # | B31: Balance Sheet
B32: Current Assets
B33: Cash & Cash Equivalents | C33: =IFERROR(Data!E53/10000000,0) -> 370.38257 | D33: =IFERROR(Data!F53/10000000,0) -> 232.13656 | E33: =IFERROR(Data!G53/10000000,0) -> 241.72322 | F33: =IFERROR(Data!H53/10000000,0) -> 654.73263 | G33: =IFERROR(Data!I53/10000000,0) -> 506.5457 | I33: =AVERAGE(C33:G33) -> 401.10414
B34: Short-term Investments | C34: =IFERROR(Data!E52/10000000,0) -> 136.55492 | D34: =IFERROR(Data!F52/10000000,0) -> 27.821501 | E34: =IFERROR(Data!G52/10000000,0) -> 31.351301 | F34: =IFERROR(Data!H52/10000000,0) -> 30.585054 | G34: =IFERROR(Data!I52/10000000,0) -> 29.732066 | I34: =AVERAGE(C34:G34) -> 51.208969
B35: Trade and Other Receivables | C35: =IFERROR(Data!E49/10000000,0) -> 3288.1935 | D35: =IFERROR(Data!F49/10000000,0) -> 4189.4179 | E35: =IFERROR(Data!G49/10000000,0) -> 3467.4948 | F35: =IFERROR(Data!H49/10000000,0) -> 3724.663 | G35: =IFERROR(Data!I49/10000000,0) -> 3606.624 | I35: =AVERAGE(C35:G35) -> 3655.2786
B36: Inventory | C36: =IFERROR(Data!E46/10000000,0) -> 2413.0562 | D36: =IFERROR(Data!F46/10000000,0) -> 3619.7619 | E36: =IFERROR(Data!G46/10000000,0) -> 2557.3533 | F36: =IFERROR(Data!H46/10000000,0) -> 2618.2664 | G36: =IFERROR(Data!I46/10000000,0) -> 2964.874 | I36: =AVERAGE(C36:G36) -> 2834.6624
B37: Advances, Deposits & Prepayments | C37: =IFERROR(Data!E51/10000000,0) -> 500.89681 | D37: =IFERROR(Data!F51/10000000,0) -> 553.65029 | E37: =IFERROR(Data!G51/10000000,0) -> 551.76371 | F37: =IFERROR(Data!H51/10000000,0) -> 767.17047 | G37: =IFERROR(Data!I51/10000000,0) -> 148.61545 | I37: =AVERAGE(C37:G37) -> 504.41934
B38: Investment in Securities | C38: =IFERROR(Data!E50/10000000,0) -> 110.60229 | D38: =IFERROR(Data!F50/10000000,0) -> 118.6988 | E38: =IFERROR(Data!G50/10000000,0) -> 103.37419 | F38: =IFERROR(Data!H50/10000000,0) -> 77.828393 | G38: =IFERROR(Data!I50/10000000,0) -> 36.58002 | I38: =AVERAGE(C38:G38) -> 89.416738
B39: Total Current Assets | C39: =SUM(C33:C38) -> 6819.6863 | D39: =SUM(D33:D38) -> 8741.487 | E39: =SUM(E33:E38) -> 6953.0606 | F39: =SUM(F33:F38) -> 7873.2459 | G39: =SUM(G33:G38) -> 7292.9712 | I39: =AVERAGE(C39:G39) -> 7536.0902
B40: Non-Current Assets
B41: Property, Plant & Equipment | C41: =IFERROR(Data!E40/10000000,0) -> 6229.528 | D41: =IFERROR(Data!F40/10000000,0) -> 6547.5137 | E41: =IFERROR(Data!G40/10000000,0) -> 6882.4875 | F41: =IFERROR(Data!H40/10000000,0) -> 7086.3874 | G41: =IFERROR(Data!I40/10000000,0) -> 7718.042 | I41: =AVERAGE(C41:G41) -> 6892.7917
B42: Right-of-Use Assets | C42: =IFERROR(Data!E42/10000000,0) -> 0 | D42: =IFERROR(Data!F42/10000000,0) -> 20.768599 | E42: =IFERROR(Data!G42/10000000,0) -> 21.313627 | F42: =IFERROR(Data!H42/10000000,0) -> 20.186695 | G42: =IFERROR(Data!I42/10000000,0) -> 21.172201 | I42: =AVERAGE(C42:G42) -> 16.688225
B43: Intangible Assets | C43: =IFERROR(Data!E41/10000000,0) -> 1.3362588 | D43: =IFERROR(Data!F41/10000000,0) -> 1.305385 | E43: =IFERROR(Data!G41/10000000,0) -> 1.9217454 | F43: =IFERROR(Data!H41/10000000,0) -> 1.6019226 | G43: =IFERROR(Data!I41/10000000,0) -> 4.6082639 | I43: =AVERAGE(C43:G43) -> 2.1547151
B44: Other Non-current Assets | C44: =IFERROR(Data!E43/10000000,0) -> 394.38023 | D44: =IFERROR(Data!F43/10000000,0) -> 644.61877 | E44: =IFERROR(Data!G43/10000000,0) -> 735.17363 | F44: =IFERROR(Data!H43/10000000,0) -> 743.79646 | G44: =IFERROR(Data!I43/10000000,0) -> 724.75993 | I44: =AVERAGE(C44:G44) -> 648.5458
B45: Total Non-current Assets | C45: =SUM(C41:C44) -> 6625.2445 | D45: =SUM(D41:D44) -> 7214.2064 | E45: =SUM(E41:E44) -> 7640.8965 | F45: =SUM(F41:F44) -> 7851.9725 | G45: =SUM(G41:G44) -> 8468.5824 | I45: =AVERAGE(C45:G45) -> 7560.1805
B46: Total Assets | C46: =C39+C45 -> 13444.931 | D46: =D39+D45 -> 15955.693 | E46: =E39+E45 -> 14593.957 | F46: =F39+F45 -> 15725.218 | G46: =G39+G45 -> 15761.554 | I46: =AVERAGE(C46:G46) -> 15096.271
B47: Current Liabilities
B48: Accounts Payable | C48: =IFERROR(Data!E68/10000000,0) -> 292.33228 | D48: =IFERROR(Data!F68/10000000,0) -> 458.14572 | E48: =IFERROR(Data!G68/10000000,0) -> 305.80097 | F48: =IFERROR(Data!H68/10000000,0) -> 363.01136 | G48: =IFERROR(Data!I68/10000000,0) -> 240.30518 | I48: =AVERAGE(C48:G48) -> 331.9191
B49: Accrued Expenses | C49: =IFERROR(Data!E72/10000000,0) -> 704.55801 | D49: =IFERROR(Data!F72/10000000,0) -> 626.12201 | E49: =IFERROR(Data!G72/10000000,0) -> 652.17449 | F49: =IFERROR(Data!H72/10000000,0) -> 790.42642 | G49: =IFERROR(Data!I72/10000000,0) -> 531.66138 | I49: =AVERAGE(C49:G49) -> 660.98846
B50: Short-term Debt | C50: =IFERROR(Data!E69/10000000,0) -> 2387.9415 | D50: =IFERROR(Data!F69/10000000,0) -> 4265.9074 | E50: =IFERROR(Data!G69/10000000,0) -> 2409.6052 | F50: =IFERROR(Data!H69/10000000,0) -> 2124.3602 | G50: =IFERROR(Data!I69/10000000,0) -> 1788.3977 | I50: =AVERAGE(C50:G50) -> 2595.2424
B51: Current Portion of LT Debt | C51: =IFERROR(Data!E70/10000000,0) -> 235.25441 | D51: =IFERROR(Data!F70/10000000,0) -> 133.12941 | E51: =IFERROR(Data!G70/10000000,0) -> 169.59514 | F51: =IFERROR(Data!H70/10000000,0) -> 251.32621 | G51: =IFERROR(Data!I70/10000000,0) -> 294.82176 | I51: =AVERAGE(C51:G51) -> 216.82538
B52: Current Portion of Leases | C52: =IFERROR(Data!E71/10000000,0) -> 0 | D52: =IFERROR(Data!F71/10000000,0) -> 2.839484 | E52: =IFERROR(Data!G71/10000000,0) -> 3.5666642 | F52: =IFERROR(Data!H71/10000000,0) -> 4.1207819 | G52: =IFERROR(Data!I71/10000000,0) -> 3.9624404 | I52: =AVERAGE(C52:G52) -> 2.8978741
B53: Unclaimed Dividend | C53: =IFERROR(Data!E73/10000000,0) -> 0.1547499 | D53: =IFERROR(Data!F73/10000000,0) -> 0.2840777 | E53: =IFERROR(Data!G73/10000000,0) -> 0.3778478 | F53: =IFERROR(Data!H73/10000000,0) -> 0.5752783 | G53: =IFERROR(Data!I73/10000000,0) -> 0.7481253 | I53: =AVERAGE(C53:G53) -> 0.4280158
B54: Total Current Liabilities | C54: =SUM(C48:C53) -> 3620.2409 | D54: =SUM(D48:D53) -> 5486.4281 | E54: =SUM(E48:E53) -> 3541.1203 | F54: =SUM(F48:F53) -> 3533.8202 | G54: =SUM(G48:G53) -> 2859.8966 | I54: =AVERAGE(C54:G54) -> 3808.3012
B55: Non-Current Liabilities
B56: Long-term Debt | C56: =IFERROR(Data!E63/10000000,0) -> 341.39273 | D56: =IFERROR(Data!F63/10000000,0) -> 258.40659 | E56: =IFERROR(Data!G63/10000000,0) -> 514.43276 | F56: =IFERROR(Data!H63/10000000,0) -> 578.46689 | G56: =IFERROR(Data!I63/10000000,0) -> 562.55482 | I56: =AVERAGE(C56:G56) -> 451.05076
B57: Lease Liabilities | C57: =IFERROR(Data!E65/10000000,0) -> 0 | D57: =IFERROR(Data!F65/10000000,0) -> 18.948746 | E57: =IFERROR(Data!G65/10000000,0) -> 19.612008 | F57: =IFERROR(Data!H65/10000000,0) -> 18.695771 | G57: =IFERROR(Data!I65/10000000,0) -> 19.946937 | I57: =AVERAGE(C57:G57) -> 15.440692
B58: Deferred Tax Liabilities | C58: =IFERROR(Data!E64/10000000,0) -> 36.546214 | D58: =IFERROR(Data!F64/10000000,0) -> 47.768313 | E58: =IFERROR(Data!G64/10000000,0) -> 98.945058 | F58: =IFERROR(Data!H64/10000000,0) -> 96.71463 | G58: =IFERROR(Data!I64/10000000,0) -> 201.94047 | I58: =AVERAGE(C58:G58) -> 96.382938
B59: UNDP Fund | C59: =IFERROR(Data!E66/10000000,0) -> 7.7603084 | D59: =IFERROR(Data!F66/10000000,0) -> 5.7116262 | E59: =IFERROR(Data!G66/10000000,0) -> 7.4329381 | F59: =IFERROR(Data!H66/10000000,0) -> 7.4068576 | G59: =IFERROR(Data!I66/10000000,0) -> 7.8824932 | I59: =AVERAGE(C59:G59) -> 7.2388447
B60: Total Non-current Liabilities | C60: =SUM(C56:C59) -> 385.69925 | D60: =SUM(D56:D59) -> 330.83527 | E60: =SUM(E56:E59) -> 640.42276 | F60: =SUM(F56:F59) -> 701.28414 | G60: =SUM(G56:G59) -> 792.32473 | I60: =AVERAGE(C60:G60) -> 570.11323
B61: Total Liabilities | C61: =C54+C60 -> 4005.9402 | D61: =D54+D60 -> 5817.2633 | E61: =E54+E60 -> 4181.543 | F61: =F54+F60 -> 4235.1044 | G61: =G54+G60 -> 3652.2213 | I61: =AVERAGE(C61:G61) -> 4378.4144
B62: Shareholders' Equity
B63: Common Stock | C63: =IFERROR(Data!E56/10000000,0) -> 302.92834 | D63: =IFERROR(Data!F56/10000000,0) -> 302.92834 | E63: =IFERROR(Data!G56/10000000,0) -> 302.92834 | F63: =IFERROR(Data!H56/10000000,0) -> 302.92834 | G63: =IFERROR(Data!I56/10000000,0) -> 302.92834 | I63: =AVERAGE(C63:G63) -> 302.92834
B64: Additional Paid-in Capital | C64: =IFERROR(Data!E57/10000000,0) -> 93.168372 | D64: =IFERROR(Data!F57/10000000,0) -> 93.168372 | E64: =IFERROR(Data!G57/10000000,0) -> 93.168372 | F64: =IFERROR(Data!H57/10000000,0) -> 93.168372 | G64: =IFERROR(Data!I57/10000000,0) -> 93.168372 | I64: =AVERAGE(C64:G64) -> 93.168372
B65: Revaluation Reserve | C65: =IFERROR(Data!E58/10000000,0) -> 3133.2448 | D65: =IFERROR(Data!F58/10000000,0) -> 3130.3391 | E65: =IFERROR(Data!G58/10000000,0) -> 3075.967 | F65: =IFERROR(Data!H58/10000000,0) -> 3073.0612 | G65: =IFERROR(Data!I58/10000000,0) -> 3376.1917 | I65: =AVERAGE(C65:G65) -> 3157.7607
B66: Retained Earnings | C66: =IFERROR(Data!E59/10000000,0) -> 5909.649 | D66: =IFERROR(Data!F59/10000000,0) -> 6611.9943 | E66: =IFERROR(Data!G59/10000000,0) -> 6940.3504 | F66: =IFERROR(Data!H59/10000000,0) -> 8020.956 | G66: =IFERROR(Data!I59/10000000,0) -> 8337.044 | I66: =AVERAGE(C66:G66) -> 7163.9987
B67: Total Equity | C67: =SUM(C63:C66) -> 9438.9906 | D67: =SUM(D63:D66) -> 10138.43 | E67: =SUM(E63:E66) -> 10412.414 | F67: =SUM(F63:F66) -> 11490.114 | G67: =SUM(G63:G66) -> 12109.332 | I67: =AVERAGE(C67:G67) -> 10717.856
B68: Total Liabilities and Equity | C68: =C61+C67 -> 13444.931 | D68: =D61+D67 -> 15955.693 | E68: =E61+E67 -> 14593.957 | F68: =F61+F67 -> 15725.218 | G68: =G61+G67 -> 15761.554 | I68: =AVERAGE(C68:G68) -> 15096.271
B69: Total Debt | C69: =IFERROR(Data!E119/10000000,0) -> 2964.5886 | D69: =IFERROR(Data!F119/10000000,0) -> 4679.2316 | E69: =IFERROR(Data!G119/10000000,0) -> 3116.8117 | F69: =IFERROR(Data!H119/10000000,0) -> 2976.9698 | G69: =IFERROR(Data!I119/10000000,0) -> 2669.6837 | I69: =AVERAGE(C69:G69) -> 3281.4571
A71: # | B71: Cash Flow Statement
B72: Net Income | C72: =IFERROR(Data!C125/10000000,0) -> 1639.2039 | D72: =IFERROR(Data!D125/10000000,0) -> 1216.6151 | E72: =IFERROR(Data!E125/10000000,0) -> 782.678 | F72: =IFERROR(Data!F125/10000000,0) -> 1356.5259 | G72: =IFERROR(Data!G125/10000000,0) -> 1036.616 | I72: =AVERAGE(C72:G72) -> 1206.3278
B73: Depreciation & Amortization | C73: =IFERROR(SUM(Data!C126:C127)/10000000,0) -> 168.76699 | D73: =IFERROR(SUM(Data!D126:D127)/10000000,0) -> 192.86081 | E73: =IFERROR(SUM(Data!E126:E127)/10000000,0) -> 214.69746 | F73: =IFERROR(SUM(Data!F126:F127)/10000000,0) -> 251.59587 | G73: =IFERROR(SUM(Data!G126:G127)/10000000,0) -> 296.08111 | I73: =AVERAGE(C73:G73) -> 224.80045
B74: Loss (Gain) From Sale of Assets | C74: =IFERROR(Data!C128/10000000,0) -> 3.7066843 | D74: =IFERROR(Data!D128/10000000,0) -> 4.0651337 | E74: =IFERROR(Data!E128/10000000,0) -> 4.8641547 | F74: =IFERROR(Data!F128/10000000,0) -> 44.606383 | G74: =IFERROR(Data!G128/10000000,0) -> 4.6711994 | I74: =AVERAGE(C74:G74) -> 12.382711
B75: Asset Writedown & Restructuring Costs | C75: =IFERROR(Data!C129/10000000,0) -> 0 | D75: =IFERROR(Data!D129/10000000,0) -> 0 | E75: =IFERROR(Data!E129/10000000,0) -> 0 | F75: =IFERROR(Data!F129/10000000,0) -> 0 | G75: =IFERROR(Data!G129/10000000,0) -> 12.214957 | I75: =AVERAGE(C75:G75) -> 2.4429914
B76: Loss (Gain) From Sale of Investments | C76: =IFERROR(Data!C130/10000000,0) -> -23.971152 | D76: =IFERROR(Data!D130/10000000,0) -> 7.0459151 | E76: =IFERROR(Data!E130/10000000,0) -> 1.7843367 | F76: =IFERROR(Data!F130/10000000,0) -> 23.653256 | G76: =IFERROR(Data!G130/10000000,0) -> -2.0598817 | I76: =AVERAGE(C76:G76) -> 1.2904948
B77: Other Operating Activities | C77: =IFERROR(Data!C131/10000000,0) -> 41.30508 | D77: =IFERROR(Data!D131/10000000,0) -> 413.73748 | E77: =IFERROR(Data!E131/10000000,0) -> 723.91318 | F77: =IFERROR(Data!F131/10000000,0) -> 409.52959 | G77: =IFERROR(Data!G131/10000000,0) -> 397.35421 | I77: =AVERAGE(C77:G77) -> 397.16791
B78: Change in Accounts Receivable | C78: =IFERROR(Data!C132/10000000,0) -> -939.523 | D78: =IFERROR(Data!D132/10000000,0) -> -901.81409 | E78: =IFERROR(Data!E132/10000000,0) -> 723.76026 | F78: =IFERROR(Data!F132/10000000,0) -> -254.44947 | G78: =IFERROR(Data!G132/10000000,0) -> 159.01845 | I78: =AVERAGE(C78:G78) -> -242.60157
B79: Change in Inventory | C79: =IFERROR(Data!C133/10000000,0) -> -219.73056 | D79: =IFERROR(Data!D133/10000000,0) -> -1206.7057 | E79: =IFERROR(Data!E133/10000000,0) -> 1062.4086 | F79: =IFERROR(Data!F133/10000000,0) -> -60.913018 | G79: =IFERROR(Data!G133/10000000,0) -> -346.60762 | I79: =AVERAGE(C79:G79) -> -154.30967
B80: Change in Accounts Payable | C80: =IFERROR(Data!C134/10000000,0) -> 105.18648 | D80: =IFERROR(Data!D134/10000000,0) -> 165.67774 | E80: =IFERROR(Data!E134/10000000,0) -> -152.34475 | F80: =IFERROR(Data!F134/10000000,0) -> 57.210386 | G80: =IFERROR(Data!G134/10000000,0) -> -122.70617 | I80: =AVERAGE(C80:G80) -> 10.604736
B81: Change in Income Taxes | C81: =IFERROR(Data!C135/10000000,0) -> 0 | D81: =IFERROR(Data!D135/10000000,0) -> 0 | E81: =IFERROR(Data!E135/10000000,0) -> 0 | F81: =IFERROR(Data!F135/10000000,0) -> 0 | G81: =IFERROR(Data!G135/10000000,0) -> -39.698996 | I81: =AVERAGE(C81:G81) -> -7.9397992
B82: Change in Other Net Operating Assets | C82: =IFERROR(Data!C136/10000000,0) -> 191.58948 | D82: =IFERROR(Data!D136/10000000,0) -> -131.05378 | E82: =IFERROR(Data!E136/10000000,0) -> 26.253443 | F82: =IFERROR(Data!F136/10000000,0) -> -102.15409 | G82: =IFERROR(Data!G136/10000000,0) -> 368.16659 | I82: =AVERAGE(C82:G82) -> 70.560329
B83: Net Cash Flow from Operating Activities | C83: =SUM(C72:C82) -> 966.53386 | D83: =SUM(D72:D82) -> -239.57147 | E83: =SUM(E72:E82) -> 3388.0147 | F83: =SUM(F72:F82) -> 1725.6048 | G83: =SUM(G72:G82) -> 1763.0499 | I83: =AVERAGE(C83:G83) -> 1520.7264
B84: Capital Expenditures | C84: =IFERROR(Data!C139/10000000,0) -> -459.55299 | D84: =IFERROR(Data!D139/10000000,0) -> -761.87803 | E84: =IFERROR(Data!E139/10000000,0) -> -642.47735 | F84: =IFERROR(Data!F139/10000000,0) -> -480.08757 | G84: =IFERROR(Data!G139/10000000,0) -> -519.65592 | I84: =AVERAGE(C84:G84) -> -572.73037
B85: Sale of Property, Plant & Equipment | C85: =IFERROR(Data!C140/10000000,0) -> 11.754631 | D85: =IFERROR(Data!D140/10000000,0) -> 0.7850469 | E85: =IFERROR(Data!E140/10000000,0) -> 1.8922211 | F85: =IFERROR(Data!F140/10000000,0) -> 0.4946368 | G85: =IFERROR(Data!G140/10000000,0) -> 0.0586024 | I85: =AVERAGE(C85:G85) -> 2.9970276
B86: Sale (Purchase) of Intangibles | C86: =IFERROR(Data!C141/10000000,0) -> -0.1831593 | D86: =IFERROR(Data!D141/10000000,0) -> -0.3637488 | E86: =IFERROR(Data!E141/10000000,0) -> -1.148884 | F86: =IFERROR(Data!F141/10000000,0) -> -0.3824614 | G86: =IFERROR(Data!G141/10000000,0) -> -3.792673 | I86: =AVERAGE(C86:G86) -> -1.1741853
B87: Investment in Securities | C87: =IFERROR(Data!C142/10000000,0) -> -102.00127 | D87: =IFERROR(Data!D142/10000000,0) -> 93.590996 | E87: =IFERROR(Data!E142/10000000,0) -> 10.01047 | F87: =IFERROR(Data!F142/10000000,0) -> 2.6587882 | G87: =IFERROR(Data!G142/10000000,0) -> 44.161243 | I87: =AVERAGE(C87:G87) -> 9.6840445
B88: Other Investing Activities | C88: =IFERROR(Data!C143/10000000,0) -> 20.202402 | D88: =IFERROR(Data!D143/10000000,0) -> 20.722549 | E88: =IFERROR(Data!E143/10000000,0) -> 8.1418239 | F88: =IFERROR(Data!F143/10000000,0) -> 18.958533 | G88: =IFERROR(Data!G143/10000000,0) -> 36.124163 | I88: =AVERAGE(C88:G88) -> 20.829894
B89: Net Cash Flow from Investing Activities | C89: =SUM(C84:C88) -> -529.78039 | D89: =SUM(D84:D88) -> -647.14319 | E89: =SUM(E84:E88) -> -623.58172 | F89: =SUM(F84:F88) -> -458.35807 | G89: =SUM(G84:G88) -> -443.10458 | I89: =AVERAGE(C89:G89) -> -540.39359
B90: Short Term Loan-Received/(Repaid), Net | C90: =IFERROR(Data!E113/10000000,0) -> 139.27831 | D90: =IFERROR(Data!F113/10000000,0) -> 1877.9659 | E90: =IFERROR(Data!G113/10000000,0) -> -1856.4035 | F90: =IFERROR(Data!H113/10000000,0) -> -285.24495 | G90: =IFERROR(Data!I113/10000000,0) -> -335.9625 | I90: =AVERAGE(C90:G90) -> -92.073361
B91: Long Term Loan-Received/(Repaid), Net | C91: =IFERROR(Data!E109/10000000,0) -> -9.1645422 | D91: =IFERROR(Data!F109/10000000,0) -> -185.11114 | E91: =IFERROR(Data!G109/10000000,0) -> 292.4919 | F91: =IFERROR(Data!H109/10000000,0) -> 145.76521 | G91: =IFERROR(Data!I109/10000000,0) -> 27.58348 | I91: =AVERAGE(C91:G91) -> 54.312979
B92: Lease Payment | C92: =IFERROR(Data!E111/10000000,0) -> 0 | D92: =IFERROR(Data!F111/10000000,0) -> -3.5346059 | E92: =IFERROR(Data!G111/10000000,0) -> -3.0258351 | F92: =IFERROR(Data!H111/10000000,0) -> -3.7516806 | G92: =IFERROR(Data!I111/10000000,0) -> -4.1340652 | I92: =AVERAGE(C92:G92) -> -2.8892374
B93: Issuance of Common Stock | C93: =IFERROR(Data!C152/10000000,0) -> 35.130934 | D93: =IFERROR(Data!D152/10000000,0) -> 0 | E93: =IFERROR(Data!E152/10000000,0) -> 0 | F93: =IFERROR(Data!F152/10000000,0) -> 0 | G93: =IFERROR(Data!G152/10000000,0) -> 0 | I93: =AVERAGE(C93:G93) -> 7.0261868
B94: Common Dividends Paid | C94: =IFERROR(Data!C153/10000000,0) -> -230.70194 | D94: =IFERROR(Data!D153/10000000,0) -> -517.32086 | E94: =IFERROR(Data!E153/10000000,0) -> -457.27919 | F94: =IFERROR(Data!F153/10000000,0) -> -279.05848 | G94: =IFERROR(Data!G153/10000000,0) -> -723.66632 | I94: =AVERAGE(C94:G94) -> -441.60536
B95: Other Financing Activities | C95: =IFERROR(Data!C154/10000000,0) -> -147.6116 | D95: =IFERROR(Data!D154/10000000,0) -> -423.53061 | E95: =IFERROR(Data!E154/10000000,0) -> -730.62961 | F95: =IFERROR(Data!F154/10000000,0) -> -431.94744 | G95: =IFERROR(Data!G154/10000000,0) -> -431.95283 | I95: =AVERAGE(C95:G95) -> -433.13442
B96: Net Cash Flow from Financing Activities | C96: =SUM(C90:C95) -> -213.06884 | D96: =SUM(D90:D95) -> 748.46866 | E96: =SUM(E90:E95) -> -2754.8463 | F96: =SUM(F90:F95) -> -854.23735 | G96: =SUM(G90:G95) -> -1468.1322 | I96: =AVERAGE(C96:G96) -> -908.36321
B97: Net Cash Flow | C97: =IFERROR(Data!C157/10000000,0) -> 223.68464 | D97: =IFERROR(Data!D157/10000000,0) -> -138.246 | E97: =IFERROR(Data!E157/10000000,0) -> 9.5866533 | F97: =IFERROR(Data!F157/10000000,0) -> 413.00942 | G97: =IFERROR(Data!G157/10000000,0) -> -148.18694 | I97: =AVERAGE(C97:G97) -> 71.969554
B98: Cash and cash equivalent at beginning of the year | C98: =IFERROR(Data!D167/10000000,0) -> 146.69793 | D98: =IFERROR(Data!E167/10000000,0) -> 370.38257 | E98: =IFERROR(Data!F167/10000000,0) -> 232.13656 | F98: =IFERROR(Data!G167/10000000,0) -> 241.72322 | G98: =IFERROR(Data!H167/10000000,0) -> 654.73263 | I98: =AVERAGE(C98:G98) -> 329.13458
B99: Cash and cash equivalent at end of the year | C99: =C98+C97 -> 370.38257 | D99: =D98+D97 -> 232.13656 | E99: =E98+E97 -> 241.72322 | F99: =F98+F97 -> 654.73264 | G99: =G98+G97 -> 506.5457 | I99: =AVERAGE(C99:G99) -> 401.10414
B100: Consolidated Net Operating Cash Flow Per Share (NOCFPS) | C100: =IFERROR(Data!E118,0) -> 31.96 | D100: =IFERROR(Data!F118,0) -> -7.91 | E100: =IFERROR(Data!G118,0) -> 111.84 | F100: =IFERROR(Data!H118,0) -> 56.96 | G100: =IFERROR(Data!I118,0) -> 58.2 | I100: =AVERAGE(C100:G100) -> 50.21

Sheet Revenue Forecast
B2: Revenue Forecast
B3: Years | C3: 2021 | D3: 2022 | E3: 2023 | F3: 2024 | G3: 2025 | H3: 2026 | I3: 2027 | J3: 2028 | K3: 2029 | L3: 2030 | M3: 2031 | N3: 2032 | O3: 2033 | P3: 2034 | Q3: 2035
Q4: BDT in Crore
B5: Freezer, Refrigerator & Compressor | C5: =IFERROR(Data!E177/10000000,0) -> 5216.6796 | D5: =IFERROR(Data!F177/10000000,0) -> 5818.2458 | E5: =IFERROR(Data!G177/10000000,0) -> 4454.7964 | F5: =IFERROR(Data!H177/10000000,0) -> 4658.8328 | G5: =IFERROR(Data!I177/10000000,0) -> 4759.5797 | H5: =G5*(1+Assumptions!D6) -> 4902.3671 | I5: =H5*(1+Assumptions!E6) -> 5049.4381 | J5: =I5*(1+Assumptions!F6) -> 5200.9213 | K5: =J5*(1+Assumptions!G6) -> 5356.9489 | L5: =K5*(1+Assumptions!H6) -> 5517.6574 | M5: =L5*(1+Assumptions!I6) -> 5655.5988 | N5: =M5*(1+Assumptions!J6) -> 5796.9888 | O5: =N5*(1+Assumptions!K6) -> 5941.9135 | ... Q5: =P5*(1+Assumptions!M6) -> 6181.9668
B6: Growth % | D6: =D5/C5-1 -> 0.1153159 | E6: =E5/D5-1 -> -0.23434028 | F6: =F5/E5-1 -> 0.045801503 | G6: =G5/F5-1 -> 0.021624936 | H6: =H5/G5-1 -> 0.03 | I6: =I5/H5-1 -> 0.03 | J6: =J5/I5-1 -> 0.03 | K6: =K5/J5-1 -> 0.03 | ... Q6: =Q5/P5-1 -> 0.02
B7: Air Conditioner | C7: =IFERROR(Data!E178/10000000,0) -> 366.38747 | D7: =IFERROR(Data!F178/10000000,0) -> 446.144 | E7: =IFERROR(Data!G178/10000000,0) -> 620.02496 | F7: =IFERROR(Data!H178/10000000,0) -> 965.08733 | G7: =IFERROR(Data!I178/10000000,0) -> 660.40191 | H7: =G7*(1+Assumptions!D7) -> 713.23406 | I7: =H7*(1+Assumptions!E7) -> 763.16044 | J7: =I7*(1+Assumptions!F7) -> 808.95007 | K7: =J7*(1+Assumptions!G7) -> 857.48707 | L7: =K7*(1+Assumptions!H7) -> 908.9363 | M7: =L7*(1+Assumptions!I7) -> 958.9278 | N7: =M7*(1+Assumptions!J7) -> 1006.8742 | O7: =N7*(1+Assumptions!K7) -> 1057.2179 | ... Q7: =P7*(1+Assumptions!M7) -> 1143.4869
B8: Growth % | D8: =D7/C7-1 -> 0.21768358 | E8: =E7/D7-1 -> 0.38974177 | F8: =F7/E7-1 -> 0.5565298 | G8: =G7/F7-1 -> -0.31570762 | H8: =H7/G7-1 -> 0.08 | I8: =I7/H7-1 -> 0.07 | J8: =J7/I7-1 -> 0.06 | K8: =K7/J7-1 -> 0.06 | ... Q8: =Q7/P7-1 -> 0.04
B9: Television | C9: =IFERROR(Data!E179/10000000,0) -> 827.78093 | D9: =IFERROR(Data!F179/10000000,0) -> 922.46286 | E9: =IFERROR(Data!G179/10000000,0) -> 610.69963 | F9: =IFERROR(Data!H179/10000000,0) -> 523.34811 | G9: =IFERROR(Data!I179/10000000,0) -> 411.47071 | H9: =G9*(1+Assumptions!D8) -> 421.75748 | I9: =H9*(1+Assumptions!E8) -> 430.19263 | J9: =I9*(1+Assumptions!F8) -> 436.64552 | K9: =J9*(1+Assumptions!G8) -> 443.1952 | L9: =K9*(1+Assumptions!H8) -> 449.84313 | M9: =L9*(1+Assumptions!I8) -> 454.34156 | N9: =M9*(1+Assumptions!J8) -> 458.88498 | O9: =N9*(1+Assumptions!K8) -> 463.47383 | ... Q9: =P9*(1+Assumptions!M8) -> 472.78965
B10: Growth % | D10: =D9/C9-1 -> 0.11438041 | E10: =E9/D9-1 -> -0.33796833 | F10: =F9/E9-1 -> -0.14303515 | G10: =G9/F9-1 -> -0.21377243 | H10: =H9/G9-1 -> 0.025 | I10: =I9/H9-1 -> 0.02 | J10: =J9/I9-1 -> 0.015 | K10: =K9/J9-1 -> 0.015 | ... Q10: =Q9/P9-1 -> 0.01
B11: Electrical Appliances (EAP) | C11: =IFERROR(Data!E180/10000000,0) -> 465.98171 | D11: =IFERROR(Data!F180/10000000,0) -> 701.83689 | E11: =IFERROR(Data!G180/10000000,0) -> 928.06174 | F11: =IFERROR(Data!H180/10000000,0) -> 1257.9784 | G11: =IFERROR(Data!I180/10000000,0) -> 1016.8628 | H11: =G11*(1+Assumptions!D9) -> 1118.549 | I11: =H11*(1+Assumptions!E9) -> 1208.0329 | J11: =I11*(1+Assumptions!F9) -> 1292.5953 | K11: =J11*(1+Assumptions!G9) -> 1370.151 | L11: =K11*(1+Assumptions!H9) -> 1438.6585 | M11: =L11*(1+Assumptions!I9) -> 1510.5914 | N11: =M11*(1+Assumptions!J9) -> 1586.121 | O11: =N11*(1+Assumptions!K9) -> 1665.4271 | ... Q11: =P11*(1+Assumptions!M9) -> 1836.1333
B12: Growth % | D12: =D11/C11-1 -> 0.50614687 | E12: =E11/D11-1 -> 0.32233251 | F12: =F11/E11-1 -> 0.35548995 | G12: =G11/F11-1 -> -0.19166912 | H12: =H11/G11-1 -> 0.1 | I12: =I11/H11-1 -> 0.08 | J12: =J11/I11-1 -> 0.07 | K12: =K11/J11-1 -> 0.06 | ... Q12: =Q11/P11-1 -> 0.05
B13: Home Appliances (HAP) | C13: =IFERROR(Data!E181/10000000,0) -> 319.6641 | D13: =IFERROR(Data!F181/10000000,0) -> 491.0798 | E13: =IFERROR(Data!G181/10000000,0) -> 351.64985 | F13: =IFERROR(Data!H181/10000000,0) -> 433.55145 | G13: =IFERROR(Data!I181/10000000,0) -> 462.02502 | H13: =G13*(1+Assumptions!D10) -> 508.22752 | I13: =H13*(1+Assumptions!E10) -> 553.968 | J13: =I13*(1+Assumptions!F10) -> 598.28544 | K13: =J13*(1+Assumptions!G10) -> 640.16542 | L13: =K13*(1+Assumptions!H10) -> 678.57534 | M13: =L13*(1+Assumptions!I10) -> 712.50411 | N13: =M13*(1+Assumptions!J10) -> 741.00428 | O13: =N13*(1+Assumptions!K10) -> 770.64445 | ... Q13: =P13*(1+Assumptions!M10) -> 833.52903
B14: Growth % | D14: =D13/C13-1 -> 0.53623697 | E14: =E13/D13-1 -> -0.28392525 | F14: =F13/E13-1 -> 0.23290668 | G14: =G13/F13-1 -> 0.06567518 | H14: =H13/G13-1 -> 0.1 | I14: =I13/H13-1 -> 0.09 | J14: =J13/I13-1 -> 0.08 | K14: =K13/J13-1 -> 0.07 | ... Q14: =Q13/P13-1 -> 0.04
B15: Elevator | D15: =IFERROR(Data!F182/10000000,0) -> 53.907451 | E15: =IFERROR(Data!G182/10000000,0) -> 104.11405 | F15: =IFERROR(Data!H182/10000000,0) -> 108.65919 | G15: =IFERROR(Data!I182/10000000,0) -> 161.07881 | H15: =G15*(1+Assumptions!D11) -> 185.24063 | I15: =H15*(1+Assumptions!E11) -> 211.17432 | J15: =I15*(1+Assumptions!F11) -> 236.51524 | K15: =J15*(1+Assumptions!G11) -> 260.16677 | L15: =K15*(1+Assumptions!H11) -> 283.58177 | M15: =L15*(1+Assumptions!I11) -> 306.26832 | N15: =M15*(1+Assumptions!J11) -> 327.7071 | O15: =N15*(1+Assumptions!K11) -> 347.36952 | ... Q15: =P15*(1+Assumptions!M11) -> 379.32752
B16: Growth % | E16: =E15/D15-1 -> 0.93134807 | F16: =F15/E15-1 -> 0.043655343 | G16: =G15/F15-1 -> 0.4824224 | H16: =H15/G15-1 -> 0.15 | I16: =I15/H15-1 -> 0.14 | J16: =J15/I15-1 -> 0.12 | K16: =K15/J15-1 -> 0.1 | L16: =L15/K15-1 -> 0.09 | ... Q16: =Q15/P15-1 -> 0.04
B17: Cable | G17: =IFERROR(Data!I183/10000000,0) -> 134.16057 | H17: =G17*(1+Assumptions!D12) -> 150.25984 | I17: =H17*(1+Assumptions!E12) -> 165.28582 | J17: =I17*(1+Assumptions!F12) -> 178.50869 | K17: =J17*(1+Assumptions!G12) -> 191.0043 | L17: =K17*(1+Assumptions!H12) -> 202.46456 | M17: =L17*(1+Assumptions!I12) -> 212.58778 | N17: =M17*(1+Assumptions!J12) -> 223.21717 | O17: =N17*(1+Assumptions!K12) -> 234.37803 | ... Q17: =P17*(1+Assumptions!M12) -> 258.40178
B18: Growth % | H18: =H17/G17-1 -> 0.12 | I18: =I17/H17-1 -> 0.1 | J18: =J17/I17-1 -> 0.08 | K18: =K17/J17-1 -> 0.07 | L18: =L17/K17-1 -> 0.06 | M18: =M17/L17-1 -> 0.05 | N18: =N17/M17-1 -> 0.05 | O18: =O17/N17-1 -> 0.05 | ... Q18: =Q17/P17-1 -> 0.05
B19: Service Parts | E19: =IFERROR(Data!G184/10000000,0) -> 3.6709551 | F19: =IFERROR(Data!H184/10000000,0) -> 27.632899 | G19: =IFERROR(Data!I184/10000000,0) -> 61.913861 | H19: =G19*(1+Assumptions!D13) -> 73.058356 | I19: =H19*(1+Assumptions!E13) -> 84.747693 | J19: =I19*(1+Assumptions!F13) -> 96.612369 | K19: =J19*(1+Assumptions!G13) -> 108.20585 | L19: =K19*(1+Assumptions!H13) -> 119.02644 | M19: =L19*(1+Assumptions!I13) -> 128.54855 | N19: =M19*(1+Assumptions!J13) -> 137.54695 | O19: =N19*(1+Assumptions!K13) -> 145.79977 | ... Q19: =P19*(1+Assumptions!M13) -> 163.82062
B20: Growth % | F20: =F19/E19-1 -> 6.5274414 | G20: =G19/F19-1 -> 1.240585 | H20: =H19/G19-1 -> 0.18 | I20: =I19/H19-1 -> 0.16 | J20: =J19/I19-1 -> 0.14 | K20: =K19/J19-1 -> 0.12 | L20: =L19/K19-1 -> 0.1 | M20: =M19/L19-1 -> 0.08 | ... Q20: =Q19/P19-1 -> 0.06
B21: Others (Mold, Die, SBN) | E21: =IFERROR(Data!G185/10000000,0) -> 3.76444 | F21: =IFERROR(Data!H185/10000000,0) -> 21.35821 | G21: =IFERROR(Data!I185/10000000,0) -> 24.244176 | H21: =G21*(1+Assumptions!D14) -> 26.18371 | I21: =H21*(1+Assumptions!E14) -> 28.01657 | J21: =I21*(1+Assumptions!F14) -> 29.697564 | K21: =J21*(1+Assumptions!G14) -> 31.182442 | L21: =K21*(1+Assumptions!H14) -> 32.741565 | M21: =L21*(1+Assumptions!I14) -> 34.051227 | N21: =M21*(1+Assumptions!J14) -> 35.413276 | O21: =N21*(1+Assumptions!K14) -> 36.829807 | ... Q21: =P21*(1+Assumptions!M14) -> 39.83512
B22: Growth % | F22: =F21/E21-1 -> 4.6736752 | G22: =G21/F21-1 -> 0.13512211 | H22: =H21/G21-1 -> 0.08 | I22: =I21/H21-1 -> 0.07 | J22: =J21/I21-1 -> 0.06 | K22: =K21/J21-1 -> 0.05 | L22: =L21/K21-1 -> 0.05 | M22: =M21/L21-1 -> 0.04 | ... Q22: =Q21/P21-1 -> 0.04
B23: WDIL IT Products | I23: =Assumptions!E18 -> 1320.683 | J23: =I23*(1+Assumptions!F15) -> 1650.8537 | K23: =J23*(1+Assumptions!G15) -> 1981.0245 | L23: =K23*(1+Assumptions!H15) -> 2278.1782 | M23: =L23*(1+Assumptions!I15) -> 2505.996 | N23: =M23*(1+Assumptions!J15) -> 2731.5356 | O23: =N23*(1+Assumptions!K15) -> 2950.0585 | P23: =O23*(1+Assumptions!L15) -> 3156.5626 | Q23: =P23*(1+Assumptions!M15) -> 3345.9563
B24: Growth % | J24: =J23/I23-1 -> 0.25 | K24: =K23/J23-1 -> 0.2 | L24: =L23/K23-1 -> 0.15 | M24: =M23/L23-1 -> 0.1 | N24: =N23/M23-1 -> 0.09 | O24: =O23/N23-1 -> 0.08 | P24: =P23/O23-1 -> 0.07 | Q24: =Q23/P23-1 -> 0.06
B25: Lithium Battery (WHIL) | H25: =Assumptions!D19 -> 64 | I25: =H25*(1+Assumptions!E16) -> 80 | J25: =I25*(1+Assumptions!F16) -> 96 | K25: =J25*(1+Assumptions!G16) -> 110.4 | L25: =K25*(1+Assumptions!H16) -> 123.648 | M25: =L25*(1+Assumptions!I16) -> 136.0128 | N25: =M25*(1+Assumptions!J16) -> 149.61408 | O25: =N25*(1+Assumptions!K16) -> 161.58321 | P25: =O25*(1+Assumptions!L16) -> 174.50986 | Q25: =P25*(1+Assumptions!M16) -> 188.47065
B26: Growth % | I26: =I25/H25-1 -> 0.25 | J26: =J25/I25-1 -> 0.2 | K26: =K25/J25-1 -> 0.15 | L26: =L25/K25-1 -> 0.12 | M26: =M25/L25-1 -> 0.1 | N26: =N25/M25-1 -> 0.1 | O26: =O25/N25-1 -> 0.08 | P26: =P25/O25-1 -> 0.08 | Q26: =Q25/P25-1 -> 0.08
B27: Total Revenue (before VAT) | C27: =C5+C7+C9+C11+C13+C15+C17+C19+C21+C23+C25 -> 7196.4938 | D27: =D5+D7+D9+D11+D13+D15+D17+D19+D21+D23+D25 -> 8433.6768 | E27: =E5+E7+E9+E11+E13+E15+E17+E19+E21+E23+E25 -> 7076.782 | F27: =F5+F7+F9+F11+F13+F15+F17+F19+F21+F23+F25 -> 7996.4483 | G27: =G5+G7+G9+G11+G13+G15+G17+G19+G21+G23+G25 -> 7691.7376 | H27: =H5+H7+H9+H11+H13+H15+H17+H19+H21+H23+H25 -> 8162.8778 | I27: =I5+I7+I9+I11+I13+I15+I17+I19+I21+I23+I25 -> 9894.6996 | J27: =J5+J7+J9+J11+J13+J15+J17+J19+J21+J23+J25 -> 10625.585 | ... Q27: =Q5+Q7+Q9+Q11+Q13+Q15+Q17+Q19+Q21+Q23+Q25 -> 14843.718
B28: VAT | C28: =IFERROR(Data!E187/10000000,0) -> -201.50126 | D28: =IFERROR(Data!F187/10000000,0) -> -265.50864 | E28: =IFERROR(Data!G187/10000000,0) -> -439.35489 | F28: =IFERROR(Data!H187/10000000,0) -> -484.33286 | G28: =IFERROR(Data!I187/10000000,0) -> -609.48999 | H28: =-H27*Assumptions!D17 -> -653.03022 | I28: =-I27*Assumptions!E17 -> -791.57597 | J28: =-J27*Assumptions!F17 -> -850.04682 | K28: =-K27*Assumptions!G17 -> -907.99452 | L28: =-L27*Assumptions!H17 -> -962.6649 | M28: =-M27*Assumptions!I17 -> -1009.2343 | N28: =-N27*Assumptions!J17 -> -1055.5926 | O28: =-O27*Assumptions!K17 -> -1101.9756 | ... Q28: =-Q27*Assumptions!M17 -> -1187.4974
B29: Net Revenue | C29: =SUM(C27:C28) -> 6994.9926 | D29: =SUM(D27:D28) -> 8168.1681 | E29: =SUM(E27:E28) -> 6637.4271 | F29: =SUM(F27:F28) -> 7512.1155 | G29: =SUM(G27:G28) -> 7082.2476 | H29: =SUM(H27:H28) -> 7509.8475 | I29: =SUM(I27:I28) -> 9103.1236 | J29: =SUM(J27:J28) -> 9775.5384 | ... Q29: =SUM(Q27:Q28) -> 13656.22
B30: YoY growth % | C30: 0.7028 | D30: =D29/C29-1 -> 0.16771648 | E30: =E29/D29-1 -> -0.18740322 | F30: =F29/E29-1 -> 0.13178123 | G30: =G29/F29-1 -> -0.057223281 | H30: =H29/G29-1 -> 0.06037631 | I30: =I29/H29-1 -> 0.21215824 | J30: =J29/I29-1 -> 0.073866377 | K30: =K29/J29-1 -> 0.068170012 | ... Q30: =Q29/P29-1 -> 0.037058138

Sheet Income Statement
B2: Income Statement - Walton Hi-Tech Industries PLC
B3: Years | C3: 2021 | D3: 2022 | E3: 2023 | F3: 2024 | G3: 2025 | H3: 2026 | I3: 2027 | J3: 2028 | K3: 2029 | L3: 2030 | M3: 2031 | N3: 2032 | O3: 2033 | P3: 2034 | Q3: 2035
Q4: BDT in Crore
B5: Income Statement
B6: Sales Revenue | C6: ='Revenue Forecast'!C29 -> 6994.9926 | D6: ='Revenue Forecast'!D29 -> 8168.1681 | E6: ='Revenue Forecast'!E29 -> 6637.4271 | F6: ='Revenue Forecast'!F29 -> 7512.1155 | G6: ='Revenue Forecast'!G29 -> 7082.2476 | H6: ='Revenue Forecast'!H29 -> 7509.8475 | I6: ='Revenue Forecast'!I29 -> 9103.1236 | J6: ='Revenue Forecast'!J29 -> 9775.5384 | ... Q6: ='Revenue Forecast'!Q29 -> 13656.22
B7: Revenue Growth % | C7: ='Revenue Forecast'!C30 -> 0.7028 | D7: ='Revenue Forecast'!D30 -> 0.16771648 | E7: ='Revenue Forecast'!E30 -> -0.18740322 | F7: ='Revenue Forecast'!F30 -> 0.13178123 | G7: ='Revenue Forecast'!G30 -> -0.057223281 | H7: ='Revenue Forecast'!H30 -> 0.06037631 | I7: ='Revenue Forecast'!I30 -> 0.21215824 | J7: ='Revenue Forecast'!J30 -> 0.073866377 | ... Q7: ='Revenue Forecast'!Q30 -> 0.037058138
B8: COGS | C8: ='Historical FS'!C7 -> 4351.549 | D8: ='Historical FS'!D7 -> 5514.6823 | E8: ='Historical FS'!E7 -> 4302.2876 | F8: ='Historical FS'!F7 -> 4647.3228 | G8: ='Historical FS'!G7 -> 4529.1678 | H8: =H6*Assumptions!D22 -> 4806.3024 | I8: =I6*Assumptions!E22 -> 5825.9991 | J8: =J6*Assumptions!F22 -> 6158.5892 | K8: =K6*Assumptions!G22 -> 6578.4203 | L8: =L6*Assumptions!H22 -> 6974.5072 | M8: =M6*Assumptions!I22 -> 7195.8404 | N8: =N6*Assumptions!J22 -> 7526.3752 | O8: =O6*Assumptions!K22 -> 7603.632 | ... Q8: =Q6*Assumptions!M22 -> 8193.7322
B9: COGS % of Sales | C9: =C8/C6 -> 0.62209486 | D9: =D8/D6 -> 0.6751431 | E9: =E8/E6 -> 0.64818603 | F9: =F8/F6 -> 0.61864369 | G9: =G8/G6 -> 0.63950996 | H9: =H8/H6 -> 0.64 | I9: =I8/I6 -> 0.64 | J9: =J8/J6 -> 0.63 | ... Q9: =Q8/Q6 -> 0.6
B10: Gross Profit | C10: =C6-C8 -> 2643.4436 | D10: =D6-D8 -> 2653.4858 | E10: =E6-E8 -> 2335.1396 | F10: =F6-F8 -> 2864.7926 | G10: =G6-G8 -> 2553.0797 | H10: =H6-H8 -> 2703.5451 | I10: =I6-I8 -> 3277.1245 | J10: =J6-J8 -> 3616.9492 | ... Q10: =Q6-Q8 -> 5462.4881
B11: Gross Margin % | C11: =C10/C6 -> 0.37790514 | D11: =D10/D6 -> 0.3248569 | E11: =E10/E6 -> 0.35181397 | F11: =F10/F6 -> 0.38135631 | G11: =G10/G6 -> 0.36049004 | H11: =H10/H6 -> 0.36 | I11: =I10/I6 -> 0.36 | J11: =J10/J6 -> 0.37 | ... Q11: =Q10/Q6 -> 0.4
B13: SG&A | C13: ='Historical FS'!C10+'Historical FS'!C11 -> 708.91123 | D13: ='Historical FS'!D10+'Historical FS'!D11 -> 918.45217 | E13: ='Historical FS'!E10+'Historical FS'!E11 -> 778.2902 | F13: ='Historical FS'!F10+'Historical FS'!F11 -> 985.09004 | G13: ='Historical FS'!G10+'Historical FS'!G11 -> 1070.9514 | H13: =H6*Assumptions!D23 -> 901.18171 | I13: =I6*Assumptions!E23 -> 1065.0655 | J13: =J6*Assumptions!F23 -> 1114.4114 | K13: =K6*Assumptions!G23 -> 1169.4969 | L13: =L6*Assumptions!H23 -> 1217.7711 | M13: =M6*Assumptions!I23 -> 1160.6194 | N13: =N6*Assumptions!J23 -> 1213.9315 | O13: =O6*Assumptions!K23 -> 1267.272 | ... Q13: =Q6*Assumptions!M23 -> 1365.622
B14: SG&A % of Sales | C14: =C13/C6 -> 0.10134553 | D14: =D13/D6 -> 0.11244286 | E14: =E13/E6 -> 0.11725781 | F14: =F13/F6 -> 0.13113351 | G14: =G13/G6 -> 0.15121631 | H14: =H13/H6 -> 0.12 | I14: =I13/I6 -> 0.117 | J14: =J13/J6 -> 0.114 | ... Q14: =Q13/Q6 -> 0.1
B15: Merger Integration Costs | C15: 0 | D15: 0 | E15: 0 | F15: 0 | G15: 0 | H15: 0 | I15: =Assumptions!E24 -> 50 | J15: 0 | K15: 0 | L15: 0 | M15: 0 | N15: 0 | O15: 0 | P15: 0 | Q15: 0
B16: Merger Integration Costs (% sales) | C16: =C15/C6 -> 0 | D16: =D15/D6 -> 0 | E16: =E15/E6 -> 0 | F16: =F15/F6 -> 0 | G16: =G15/G6 -> 0 | H16: =H15/H6 -> 0 | I16: =I15/I6 -> 0.0054926201 | J16: =J15/J6 -> 0 | ... Q16: =Q15/Q6 -> 0
B17: Total Operating Expenses | C17: =C13+C15 -> 708.91123 | D17: =D13+D15 -> 918.45217 | E17: =E13+E15 -> 778.2902 | F17: =F13+F15 -> 985.09004 | G17: =G13+G15 -> 1070.9514 | H17: =H13+H15 -> 901.18171 | I17: =I13+I15 -> 1115.0655 | J17: =J13+J15 -> 1114.4114 | ... Q17: =Q13+Q15 -> 1365.622
B18: OpEx % of Revenue | C18: =C17/C6 -> 0.10134553 | D18: =D17/D6 -> 0.11244286 | E18: =E17/E6 -> 0.11725781 | F18: =F17/F6 -> 0.13113351 | G18: =G17/G6 -> 0.15121631 | H18: =H17/H6 -> 0.12 | I18: =I17/I6 -> 0.12249262 | J18: =J17/J6 -> 0.114 | ... Q18: =Q17/Q6 -> 0.1
B19: EBITDA | C19: =C10-C17+C22 -> 2103.294 | D19: =D10-D17+D22 -> 1927.8944 | E19: =E10-E17+E22 -> 1771.5468 | F19: =F10-F17+F22 -> 2131.2985 | G19: =G10-G17+G22 -> 1778.2095 | H19: =H10-H17+H22 -> 2051.9638 | I19: =I10-I17+I22 -> 2426.306 | J19: =J10-J17+J22 -> 2781.3328 | ... Q19: =Q10-Q17+Q22 -> 4505.8397
B20: EBITDA Margin % | C20: =C19/C6 -> 0.30068566 | D20: =D19/D6 -> 0.23602531 | E20: =E19/E6 -> 0.26690264 | F20: =F19/F6 -> 0.28371482 | G20: =G19/G6 -> 0.25107983 | H20: =H19/H6 -> 0.27323641 | I20: =I19/I6 -> 0.26653554 | J20: =J19/J6 -> 0.28451965 | ... Q20: =Q19/Q6 -> 0.32994779
B22: Depreciation & Amortization | C22: ='Historical FS'!C13 -> 168.76159 | D22: ='Historical FS'!D13 -> 192.86081 | E22: ='Historical FS'!E13 -> 214.69746 | F22: ='Historical FS'!F13 -> 251.59587 | G22: ='Historical FS'!G13 -> 296.08111 | H22: ='Depreciation Schedule'!D10 -> 249.60035 | I22: ='Depreciation Schedule'!E10 -> 264.24696 | J22: ='Depreciation Schedule'!F10 -> 278.79498 | K22: ='Depreciation Schedule'!G10 -> 294.57782 | L22: ='Depreciation Schedule'!H10 -> 311.54046 | M22: ='Depreciation Schedule'!I10 -> 329.54936 | N22: ='Depreciation Schedule'!J10 -> 348.33475 | O22: ='Depreciation Schedule'!K10 -> 367.86546 | ... Q22: ='Depreciation Schedule'!M10 -> 408.97362
B23: EBIT | C23: =C19-C22 -> 1934.5324 | D23: =D19-D22 -> 1735.0336 | E23: =E19-E22 -> 1556.8494 | F23: =F19-F22 -> 1879.7026 | G23: =G19-G22 -> 1482.1284 | H23: =H19-H22 -> 1802.3634 | I23: =I19-I22 -> 2162.059 | J23: =J19-J22 -> 2502.5378 | ... Q23: =Q19-Q22 -> 4096.8661
B24: EBIT Margin % | C24: =C23/C6 -> 0.27655961 | D24: =D23/D6 -> 0.21241404 | E24: =E23/E6 -> 0.23455615 | F24: =F23/F6 -> 0.2502228 | G24: =G23/G6 -> 0.20927373 | H24: =H23/H6 -> 0.24 | I24: =I23/I6 -> 0.23750738 | J24: =J23/J6 -> 0.256 | ... Q24: =Q23/Q6 -> 0.3
B26: Other Income/(Expense) | C26: ='Historical FS'!C15+'Historical FS'!C16 -> 59.578721 | D26: ='Historical FS'!D15+'Historical FS'!D16 -> 35.03371 | E26: ='Historical FS'!E15+'Historical FS'!E16 -> 20.193012 | F26: ='Historical FS'!F15+'Historical FS'!F16 -> -9.4598252 | G26: ='Historical FS'!G15+'Historical FS'!G16 -> 26.661495 | H26: 0 | I26: 0 | J26: 0 | K26: 0 | L26: 0 | M26: 0 | N26: 0 | O26: 0 | P26: 0 | Q26: 0
B27: Finance Income | C27: ='Historical FS'!C17 -> 0 | D27: ='Historical FS'!D17 -> 0 | E27: ='Historical FS'!E17 -> 3.2175044 | F27: ='Historical FS'!F17 -> 17.122188 | G27: ='Historical FS'!G17 -> 29.033468 | H27: ='Debt Schedule'!D40 -> 30.920322 | I27: ='Debt Schedule'!E40 -> 27.609976 | J27: ='Debt Schedule'!F40 -> 17.525029 | K27: ='Debt Schedule'!G40 -> 24.225731 | L27: ='Debt Schedule'!H40 -> 31.676198 | M27: ='Debt Schedule'!I40 -> 46.562214 | N27: ='Debt Schedule'!J40 -> 62.44851 | O27: ='Debt Schedule'!K40 -> 79.235032 | ... Q27: ='Debt Schedule'!M40 -> 123.05536
B28: Finance Costs | C28: =-'Historical FS'!C18 -> -124.56798 | D28: =-'Historical FS'!D18 -> -473.83251 | E28: =-'Historical FS'!E18 -> -753.5856 | F28: =-'Historical FS'!F18 -> -459.12358 | G28: =-'Historical FS'!G18 -> -448.40387 | H28: =-'Debt Schedule'!D38 -> -437.98458 | I28: =-'Debt Schedule'!E38 -> -470.80363 | J28: =-'Debt Schedule'!F38 -> -484.65435 | K28: =-'Debt Schedule'!G38 -> -498.38115 | L28: =-'Debt Schedule'!H38 -> -511.3316 | M28: =-'Debt Schedule'!I38 -> -522.36307 | N28: =-'Debt Schedule'!J38 -> -533.34454 | O28: =-'Debt Schedule'!K38 -> -544.33187 | ... Q28: =-'Debt Schedule'!M38 -> -564.59048
B29: Profit Before WPPF & Tax | C29: =C23+SUM(C26:C28) -> 1869.5431 | D29: =D23+SUM(D26:D28) -> 1296.2348 | E29: =E23+SUM(E26:E28) -> 826.67429 | F29: =F23+SUM(F26:F28) -> 1428.2414 | G29: =G23+SUM(G26:G28) -> 1089.4195 | H29: =H23+SUM(H26:H28) -> 1395.2992 | I29: =I23+SUM(I26:I28) -> 1718.8654 | J29: =J23+SUM(J26:J28) -> 2035.4085 | ... Q29: =Q23+SUM(Q26:Q28) -> 3655.331
B31: Contribution to WPPF | C31: ='Historical FS'!C20 -> 89.025878 | D31: ='Historical FS'!D20 -> 61.725467 | E31: ='Historical FS'!E20 -> 39.365446 | F31: ='Historical FS'!F20 -> 68.011532 | G31: ='Historical FS'!G20 -> 51.877117 | H31: =H29*0.05 -> 69.764958 | I31: =I29*0.05 -> 85.943269 | J31: =J29*0.05 -> 101.77043 | K31: =K29*0.05 -> 110.99322 | L31: =L29*0.05 -> 119.93563 | M31: =M29*0.05 -> 138.69668 | N31: =N29*0.05 -> 146.40561 | O31: =O29*0.05 -> 166.83596 | ... Q31: =Q29*0.05 -> 182.76655
B32: Profit Before Taxation | C32: =C29-C31 -> 1780.5173 | D32: =D29-D31 -> 1234.5093 | E32: =E29-E31 -> 787.30885 | F32: =F29-F31 -> 1360.2298 | G32: =G29-G31 -> 1037.5423 | H32: =H29-H31 -> 1325.5342 | I32: =I29-I31 -> 1632.9221 | J32: =J29-J31 -> 1933.6381 | ... Q32: =Q29-Q31 -> 3472.5644
B34: Income Tax Expense | C34: ='Historical FS'!C22 -> 141.31369 | D34: ='Historical FS'!D22 -> 17.894292 | E34: ='Historical FS'!E22 -> 4.6309266 | F34: ='Historical FS'!F22 -> 3.7046974 | G34: ='Historical FS'!G22 -> 0.9263129 | H34: =H32*Assumptions!D26 -> 0 | I34: =I32*Assumptions!E26 -> 0 | J34: =J32*Assumptions!F26 -> 0 | K34: =K32*Assumptions!G26 -> 142.3488 | L34: =L32*Assumptions!H26 -> 153.81745 | M34: =M32*Assumptions!I26 -> 177.87849 | N34: =N32*Assumptions!J26 -> 625.88397 | O34: =O32*Assumptions!K26 -> 713.22372 | ... Q34: =Q32*Assumptions!M26 -> 781.327
B35: Net Profit | C35: =C32-C34 -> 1639.2036 | D35: =D32-D34 -> 1216.6151 | E35: =E32-E34 -> 782.67792 | F35: =F32-F34 -> 1356.5251 | G35: =G32-G34 -> 1036.616 | H35: =H32-H34 -> 1325.5342 | I35: =I32-I34 -> 1632.9221 | J35: =J32-J34 -> 1933.6381 | ... Q35: =Q32-Q34 -> 2691.2374
B36: Net Margin | C36: =C35/C6 -> 0.23433957 | D36: =D35/D6 -> 0.14894589 | E36: =E35/E6 -> 0.11791887 | F36: =F35/F6 -> 0.18057831 | G36: =G35/G6 -> 0.14636823 | H36: =H35/H6 -> 0.17650614 | I36: =I35/I6 -> 0.17938042 | J36: =J35/J6 -> 0.19780374 | ... Q36: =Q35/Q6 -> 0.19707045
B38: Number of Shares Outstanding | C38: ='Historical FS'!C24 -> 30.292834 | D38: ='Historical FS'!D24 -> 30.292834 | E38: ='Historical FS'!E24 -> 30.292834 | F38: ='Historical FS'!F24 -> 30.292834 | G38: ='Historical FS'!G24 -> 30.292834 | H38: =G38 -> 30.292834 | I38: =H38 -> 30.292834 | J38: =I38 -> 30.292834 | K38: =J38 -> 30.292834 | L38: =K38 -> 30.292834 | M38: =L38 -> 30.292834 | N38: =M38 -> 30.292834 | O38: =N38 -> 30.292834 | ... Q38: =P38 -> 30.292834
B39: Earnings Per Share (EPS) | C39: =C35/C38 -> 54.111925 | D39: =D35/D38 -> 40.16181 | E39: =E35/E38 -> 25.837065 | F39: =F35/F38 -> 44.780397 | G39: =G35/G38 -> 34.219843 | H39: =H35/H38 -> 43.757351 | I39: =I35/I38 -> 53.904567 | J39: =J35/J38 -> 63.831534 | ... Q39: =Q35/Q38 -> 88.840727
B40: EPS Growth % | D40: =(D39-C39)/C39 -> -0.25780112 | E40: =(E39-D39)/D39 -> -0.35667579 | F40: =(F39-E39)/E39 -> 0.73318436 | G40: =(G39-F39)/F39 -> -0.23582983 | H40: =(H39-G39)/G39 -> 0.2787128 | I40: =(I39-H39)/H39 -> 0.23189739 | J40: =(J39-I39)/I39 -> 0.18415818 | K40: =(K39-J39)/J39 -> 0.017006401 | ... Q40: =(Q39-P39)/P39 -> 0.045330186

Sheet Balance Sheet
B2: Balance Sheet - Walton Hi-Tech Industries PLC
B3: Years | C3: 2021 | D3: 2022 | E3: 2023 | F3: 2024 | G3: 2025 | H3: 2026 | I3: 2027 | J3: 2028 | K3: 2029 | L3: 2030 | M3: 2031 | N3: 2032 | O3: 2033 | P3: 2034 | Q3: 2035
Q4: BDT in Crore
B5: Balance Sheet
B6: Current Assets
B7: Cash & Cash Equivalents | C7: ='Historical FS'!C33 -> 370.38257 | D7: ='Historical FS'!D33 -> 232.13656 | E7: ='Historical FS'!E33 -> 241.72322 | F7: ='Historical FS'!F33 -> 654.73263 | G7: ='Historical FS'!G33 -> 506.5457 | H7: =G7+'Cash Flow Statement'!H35 -> 1039.4704 | I7: =H7+'Cash Flow Statement'!I35 -> 341.02842 | J7: =I7+'Cash Flow Statement'!J35 -> 535.22305 | K7: =J7+'Cash Flow Statement'!K35 -> 676.06352 | L7: =K7+'Cash Flow Statement'!L35 -> 907.74635 | M7: =L7+'Cash Flow Statement'!M35 -> 1420.3644 | N7: =M7+'Cash Flow Statement'!N35 -> 1702.0611 | O7: =N7+'Cash Flow Statement'!O35 -> 2259.6905 | ... Q7: =P7+'Cash Flow Statement'!Q35 -> 3368.0057
B8: Short-term Investments | C8: ='Historical FS'!C34 -> 136.55492 | D8: ='Historical FS'!D34 -> 27.821501 | E8: ='Historical FS'!E34 -> 31.351301 | F8: ='Historical FS'!F34 -> 30.585054 | G8: ='Historical FS'!G34 -> 29.732066 | H8: =G8 -> 29.732066 | I8: =H8 -> 29.732066 | J8: =I8 -> 29.732066 | K8: =J8 -> 29.732066 | L8: =K8 -> 29.732066 | M8: =L8 -> 29.732066 | N8: =M8 -> 29.732066 | O8: =N8 -> 29.732066 | ... Q8: =P8 -> 29.732066
B9: Trade and Other Receivables | C9: ='Historical FS'!C35 -> 3288.1935 | D9: ='Historical FS'!D35 -> 4189.4179 | E9: ='Historical FS'!E35 -> 3467.4948 | F9: ='Historical FS'!F35 -> 3724.663 | G9: ='Historical FS'!G35 -> 3606.624 | H9: =G9-'Cash Flow Statement'!H10 -> 3703.4865 | I9: =H9-'Cash Flow Statement'!I10 -> 4489.2116 | J9: =I9-'Cash Flow Statement'!J10 -> 4820.8134 | K9: =J9-'Cash Flow Statement'!K10 -> 5149.4484 | L9: =K9-'Cash Flow Statement'!L10 -> 5459.4968 | M9: =L9-'Cash Flow Statement'!M10 -> 5723.6026 | N9: =M9-'Cash Flow Statement'!N10 -> 5986.5114 | O9: =N9-'Cash Flow Statement'!O10 -> 6249.5605 | ... Q9: =P9-'Cash Flow Statement'!Q10 -> 6734.5744
B10: Inventory | C10: ='Historical FS'!C36 -> 2413.0562 | D10: ='Historical FS'!D36 -> 3619.7619 | E10: ='Historical FS'!E36 -> 2557.3533 | F10: ='Historical FS'!F36 -> 2618.2664 | G10: ='Historical FS'!G36 -> 2964.874 | H10: =G10-'Cash Flow Statement'!H11 -> 2633.5904 | I10: =H10-'Cash Flow Statement'!I11 -> 3192.3283 | J10: =I10-'Cash Flow Statement'!J11 -> 3374.5694 | K10: =J10-'Cash Flow Statement'!K11 -> 3604.6138 | L10: =K10-'Cash Flow Statement'!L11 -> 3821.6478 | M10: =L10-'Cash Flow Statement'!M11 -> 3942.9262 | N10: =M10-'Cash Flow Statement'!N11 -> 4124.0412 | O10: =N10-'Cash Flow Statement'!O11 -> 4166.3737 | ... Q10: =P10-'Cash Flow Statement'!Q11 -> 4489.7163
B11: Advances, Deposits & Prepayments | C11: ='Historical FS'!C37 -> 500.89681 | D11: ='Historical FS'!D37 -> 553.65029 | E11: ='Historical FS'!E37 -> 551.76371 | F11: ='Historical FS'!F37 -> 767.17047 | G11: ='Historical FS'!G37 -> 148.61545 | H11: =G11-'Cash Flow Statement'!H12 -> 370.34865 | I11: =H11-'Cash Flow Statement'!I12 -> 437.69814 | J11: =I11-'Cash Flow Statement'!J12 -> 457.97728 | K11: =J11-'Cash Flow Statement'!K12 -> 480.61518 | L11: =K11-'Cash Flow Statement'!L12 -> 500.45387 | M11: =L11-'Cash Flow Statement'!M12 -> 476.96688 | N11: =M11-'Cash Flow Statement'!N12 -> 498.87595 | O11: =N11-'Cash Flow Statement'!O12 -> 520.79671 | ... Q11: =P11-'Cash Flow Statement'!Q12 -> 561.21453
B12: Investment in Securities | C12: ='Historical FS'!C38 -> 110.60229 | D12: ='Historical FS'!D38 -> 118.6988 | E12: ='Historical FS'!E38 -> 103.37419 | F12: ='Historical FS'!F38 -> 77.828393 | G12: ='Historical FS'!G38 -> 36.58002 | H12: =G12 -> 36.58002 | I12: =H12 -> 36.58002 | J12: =I12 -> 36.58002 | K12: =J12 -> 36.58002 | L12: =K12 -> 36.58002 | M12: =L12 -> 36.58002 | N12: =M12 -> 36.58002 | O12: =N12 -> 36.58002 | ... Q12: =P12 -> 36.58002
B13: Total Current Assets | C13: =SUM(C7:C12) -> 6819.6863 | D13: =SUM(D7:D12) -> 8741.487 | E13: =SUM(E7:E12) -> 6953.0606 | F13: =SUM(F7:F12) -> 7873.2459 | G13: =SUM(G7:G12) -> 7292.9712 | H13: =SUM(H7:H12) -> 7813.208 | I13: =SUM(I7:I12) -> 8526.5786 | J13: =SUM(J7:J12) -> 9254.8953 | ... Q13: =SUM(Q7:Q12) -> 15219.823
B15: Non-Current Assets
B16: Property, Plant & Equipment | C16: ='Historical FS'!C41 -> 6229.528 | D16: ='Historical FS'!D41 -> 6547.5137 | E16: ='Historical FS'!E41 -> 6882.4875 | F16: ='Historical FS'!F41 -> 7086.3874 | G16: ='Historical FS'!G41 -> 7718.042
B17: Right-of-Use Assets | C17: ='Historical FS'!C42 -> 0 | D17: ='Historical FS'!D42 -> 20.768599 | E17: ='Historical FS'!E42 -> 21.313627 | F17: ='Historical FS'!F42 -> 20.186695 | G17: ='Historical FS'!G42 -> 21.172201
B18: Intangible Assets | C18: ='Historical FS'!C43 -> 1.3362588 | D18: ='Historical FS'!D43 -> 1.305385 | E18: ='Historical FS'!E43 -> 1.9217454 | F18: ='Historical FS'!F43 -> 1.6019226 | G18: ='Historical FS'!G43 -> 4.6082639
B19: Operating Assets, Net | C19: =SUM(C16:C18) -> 6230.8643 | D19: =SUM(D16:D18) -> 6569.5877 | E19: =SUM(E16:E18) -> 6905.7228 | F19: =SUM(F16:F18) -> 7108.176 | G19: =SUM(G16:G18) -> 7743.8225 | H19: ='Depreciation Schedule'!D11 -> 8198.232 | I19: ='Depreciation Schedule'!E11 -> 8649.5824 | J19: ='Depreciation Schedule'!F11 -> 9139.2435 | K19: ='Depreciation Schedule'!G11 -> 9665.5073 | L19: ='Depreciation Schedule'!H11 -> 10224.231 | M19: ='Depreciation Schedule'!I11 -> 10807.046 | N19: ='Depreciation Schedule'!J11 -> 11412.984 | O19: ='Depreciation Schedule'!K11 -> 12041.322 | ... Q19: ='Depreciation Schedule'!M11 -> 13352.903
B20: Other Non-current Assets | C20: ='Historical FS'!C44 -> 394.38023 | D20: ='Historical FS'!D44 -> 644.61877 | E20: ='Historical FS'!E44 -> 735.17363 | F20: ='Historical FS'!F44 -> 743.79646 | G20: ='Historical FS'!G44 -> 724.75993 | H20: =G20-'Cash Flow Statement'!H23-'Cash Flow Statement'!H15 -> 724.75993 | I20: =H20-'Cash Flow Statement'!I23-'Cash Flow Statement'!I15 -> 724.75993 | J20: =I20-'Cash Flow Statement'!J23-'Cash Flow Statement'!J15 -> 724.75993 | K20: =J20-'Cash Flow Statement'!K23-'Cash Flow Statement'!K15 -> 724.75993 | L20: =K20-'Cash Flow Statement'!L23-'Cash Flow Statement'!L15 -> 724.75993 | M20: =L20-'Cash Flow Statement'!M23-'Cash Flow Statement'!M15 -> 724.75993 | N20: =M20-'Cash Flow Statement'!N23-'Cash Flow Statement'!N15 -> 724.75993 | O20: =N20-'Cash Flow Statement'!O23-'Cash Flow Statement'!O15 -> 724.75993 | ... Q20: =P20-'Cash Flow Statement'!Q23-'Cash Flow Statement'!Q15 -> 724.75993
B21: Total Non-current Assets | C21: =SUM(C19:C20) -> 6625.2445 | D21: =SUM(D19:D20) -> 7214.2064 | E21: =SUM(E19:E20) -> 7640.8965 | F21: =SUM(F19:F20) -> 7851.9725 | G21: =SUM(G19:G20) -> 8468.5824 | H21: =SUM(H19:H20) -> 8922.9919 | I21: =SUM(I19:I20) -> 9374.3424 | J21: =SUM(J19:J20) -> 9864.0034 | ... Q21: =SUM(Q19:Q20) -> 14077.663
B23: Total Assets | C23: =C13+C21 -> 13444.931 | D23: =D13+D21 -> 15955.693 | E23: =E13+E21 -> 14593.957 | F23: =F13+F21 -> 15725.218 | G23: =G13+G21 -> 15761.554 | H23: =H13+H21 -> 16736.2 | I23: =I13+I21 -> 17900.921 | J23: =J13+J21 -> 19118.899 | ... Q23: =Q13+Q21 -> 29297.486
B25: Current Liabilities
B26: Accounts Payable | C26: ='Historical FS'!C48 -> 292.33228 | D26: ='Historical FS'!D48 -> 458.14572 | E26: ='Historical FS'!E48 -> 305.80097 | F26: ='Historical FS'!F48 -> 363.01136 | G26: ='Historical FS'!G48 -> 240.30518 | H26: =G26+'Cash Flow Statement'!H13 -> 395.03856 | I26: =H26+'Cash Flow Statement'!I13 -> 478.84924 | J26: =I26+'Cash Flow Statement'!J13 -> 506.18541 | K26: =J26+'Cash Flow Statement'!K13 -> 540.69208 | L26: =K26+'Cash Flow Statement'!L13 -> 573.24717 | M26: =L26+'Cash Flow Statement'!M13 -> 591.43893 | N26: =M26+'Cash Flow Statement'!N13 -> 618.60618 | O26: =N26+'Cash Flow Statement'!O13 -> 624.95605 | ... Q26: =P26+'Cash Flow Statement'!Q13 -> 673.45744
B27: Accrued Expenses | C27: ='Historical FS'!C49 -> 704.55801 | D27: ='Historical FS'!D49 -> 626.12201 | E27: ='Historical FS'!E49 -> 652.17449 | F27: ='Historical FS'!F49 -> 790.42642 | G27: ='Historical FS'!G49 -> 531.66138 | H27: =G27+'Cash Flow Statement'!H14 -> 556.25371 | I27: =H27+'Cash Flow Statement'!I14 -> 657.41084 | J27: =I27+'Cash Flow Statement'!J14 -> 687.86956 | K27: =J27+'Cash Flow Statement'!K14 -> 721.87108 | L27: =K27+'Cash Flow Statement'!L14 -> 751.66827 | M27: =L27+'Cash Flow Statement'!M14 -> 716.39144 | N27: =M27+'Cash Flow Statement'!N14 -> 749.29828 | O27: =N27+'Cash Flow Statement'!O14 -> 782.22266 | ... Q27: =P27+'Cash Flow Statement'!Q14 -> 842.92915
B28: Short-term Debt | C28: ='Historical FS'!C50 -> 2387.9415 | D28: ='Historical FS'!D50 -> 4265.9074 | E28: ='Historical FS'!E50 -> 2409.6052 | F28: ='Historical FS'!F50 -> 2124.3602 | G28: ='Historical FS'!G50 -> 1788.3977 | H28: ='Debt Schedule'!D15 -> 1788.3977 | I28: ='Debt Schedule'!E15 -> 1788.3977 | J28: ='Debt Schedule'!F15 -> 1788.3977 | K28: ='Debt Schedule'!G15 -> 1788.3977 | L28: ='Debt Schedule'!H15 -> 1788.3977 | M28: ='Debt Schedule'!I15 -> 1788.3977 | N28: ='Debt Schedule'!J15 -> 1788.3977 | O28: ='Debt Schedule'!K15 -> 1788.3977 | ... Q28: ='Debt Schedule'!M15 -> 1788.3977
B29: Current Portion of LT Debt | C29: ='Historical FS'!C51 -> 235.25441 | D29: ='Historical FS'!D51 -> 133.12941 | E29: ='Historical FS'!E51 -> 169.59514 | F29: ='Historical FS'!F51 -> 251.32621 | G29: ='Historical FS'!G51 -> 294.82176 | H29: =G29 -> 294.82176 | I29: =H29 -> 294.82176 | J29: =I29 -> 294.82176 | K29: =J29 -> 294.82176 | L29: =K29 -> 294.82176 | M29: =L29 -> 294.82176 | N29: =M29 -> 294.82176 | O29: =N29 -> 294.82176 | ... Q29: =P29 -> 294.82176
B30: Current Portion of Leases | C30: ='Historical FS'!C52 -> 0 | D30: ='Historical FS'!D52 -> 2.839484 | E30: ='Historical FS'!E52 -> 3.5666642 | F30: ='Historical FS'!F52 -> 4.1207819 | G30: ='Historical FS'!G52 -> 3.9624404 | H30: =G30 -> 3.9624404 | I30: =H30 -> 3.9624404 | J30: =I30 -> 3.9624404 | K30: =J30 -> 3.9624404 | L30: =K30 -> 3.9624404 | M30: =L30 -> 3.9624404 | N30: =M30 -> 3.9624404 | O30: =N30 -> 3.9624404 | ... Q30: =P30 -> 3.9624404
B31: Unclaimed Dividend | C31: ='Historical FS'!C53 -> 0.1547499 | D31: ='Historical FS'!D53 -> 0.2840777 | E31: ='Historical FS'!E53 -> 0.3778478 | F31: ='Historical FS'!F53 -> 0.5752783 | G31: ='Historical FS'!G53 -> 0.7481253 | H31: =G31 -> 0.7481253 | I31: =H31 -> 0.7481253 | J31: =I31 -> 0.7481253 | K31: =J31 -> 0.7481253 | L31: =K31 -> 0.7481253 | M31: =L31 -> 0.7481253 | N31: =M31 -> 0.7481253 | O31: =N31 -> 0.7481253 | ... Q31: =P31 -> 0.7481253
B32: Total Current Liabilities | C32: =SUM(C26:C31) -> 3620.2409 | D32: =SUM(D26:D31) -> 5486.4281 | E32: =SUM(E26:E31) -> 3541.1203 | F32: =SUM(F26:F31) -> 3533.8202 | G32: =SUM(G26:G31) -> 2859.8966 | H32: =SUM(H26:H31) -> 3039.2223 | I32: =SUM(I26:I31) -> 3224.1901 | J32: =SUM(J26:J31) -> 3281.985 | ... Q32: =SUM(Q26:Q31) -> 3604.3166
B34: Non-Current Liabilities
B35: Long-term Debt | C35: ='Historical FS'!C56 -> 341.39273 | D35: ='Historical FS'!D56 -> 258.40659 | E35: ='Historical FS'!E56 -> 514.43276 | F35: ='Historical FS'!F56 -> 578.46689 | G35: ='Historical FS'!G56 -> 562.55482 | H35: ='Debt Schedule'!D23-'Balance Sheet'!H29 -> 562.55482 | I35: ='Debt Schedule'!E23-'Balance Sheet'!I29 -> 562.55482 | J35: ='Debt Schedule'!F23-'Balance Sheet'!J29 -> 562.55482 | K35: ='Debt Schedule'!G23-'Balance Sheet'!K29 -> 562.55482 | L35: ='Debt Schedule'!H23-'Balance Sheet'!L29 -> 562.55482 | M35: ='Debt Schedule'!I23-'Balance Sheet'!M29 -> 562.55482 | N35: ='Debt Schedule'!J23-'Balance Sheet'!N29 -> 562.55482 | O35: ='Debt Schedule'!K23-'Balance Sheet'!O29 -> 562.55482 | ... Q35: ='Debt Schedule'!M23-'Balance Sheet'!Q29 -> 562.55482
B36: Lease Liabilities | C36: ='Historical FS'!C57 -> 0 | D36: ='Historical FS'!D57 -> 18.948746 | E36: ='Historical FS'!E57 -> 19.612008 | F36: ='Historical FS'!F57 -> 18.695771 | G36: ='Historical FS'!G57 -> 19.946937 | H36: ='Debt Schedule'!D28-'Balance Sheet'!H30 -> 19.946937 | I36: ='Debt Schedule'!E28-'Balance Sheet'!I30 -> 19.946937 | J36: ='Debt Schedule'!F28-'Balance Sheet'!J30 -> 19.946937 | K36: ='Debt Schedule'!G28-'Balance Sheet'!K30 -> 19.946937 | L36: ='Debt Schedule'!H28-'Balance Sheet'!L30 -> 19.946937 | M36: ='Debt Schedule'!I28-'Balance Sheet'!M30 -> 19.946937 | N36: ='Debt Schedule'!J28-'Balance Sheet'!N30 -> 19.946937 | O36: ='Debt Schedule'!K28-'Balance Sheet'!O30 -> 19.946937 | ... Q36: ='Debt Schedule'!M28-'Balance Sheet'!Q30 -> 19.946937
B37: Deferred Tax Liabilities | C37: ='Historical FS'!C58 -> 36.546214 | D37: ='Historical FS'!D58 -> 47.768313 | E37: ='Historical FS'!E58 -> 98.945058 | F37: ='Historical FS'!F58 -> 96.71463 | G37: ='Historical FS'!G58 -> 201.94047 | H37: =G37 -> 201.94047 | I37: =H37 -> 201.94047 | J37: =I37 -> 201.94047 | K37: =J37 -> 201.94047 | L37: =K37 -> 201.94047 | M37: =L37 -> 201.94047 | N37: =M37 -> 201.94047 | O37: =N37 -> 201.94047 | ... Q37: =P37 -> 201.94047
B38: UNDP Fund | C38: ='Historical FS'!C59 -> 7.7603084 | D38: ='Historical FS'!D59 -> 5.7116262 | E38: ='Historical FS'!E59 -> 7.4329381 | F38: ='Historical FS'!F59 -> 7.4068576 | G38: ='Historical FS'!G59 -> 7.8824932 | H38: =G38 -> 7.8824932 | I38: =H38 -> 7.8824932 | J38: =I38 -> 7.8824932 | K38: =J38 -> 7.8824932 | L38: =K38 -> 7.8824932 | M38: =L38 -> 7.8824932 | N38: =M38 -> 7.8824932 | O38: =N38 -> 7.8824932 | ... Q38: =P38 -> 7.8824932
B39: Total Non-current Liabilities | C39: =SUM(C35:C38) -> 385.69925 | D39: =SUM(D35:D38) -> 330.83527 | E39: =SUM(E35:E38) -> 640.42276 | F39: =SUM(F35:F38) -> 701.28414 | G39: =SUM(G35:G38) -> 792.32473 | H39: =SUM(H35:H38) -> 792.32473 | I39: =SUM(I35:I38) -> 792.32473 | J39: =SUM(J35:J38) -> 792.32473 | ... Q39: =SUM(Q35:Q38) -> 792.32473
B41: Total Liabilities | C41: =C32+C39 -> 4005.9402 | D41: =D32+D39 -> 5817.2633 | E41: =E32+E39 -> 4181.543 | F41: =F32+F39 -> 4235.1044 | G41: =G32+G39 -> 3652.2213 | H41: =H32+H39 -> 3831.547 | I41: =I32+I39 -> 4016.5148 | J41: =J32+J39 -> 4074.3097 | ... Q41: =Q32+Q39 -> 4396.6413
B43: Shareholders' Equity
B44: Common Stock | C44: ='Historical FS'!C63 -> 302.92834 | D44: ='Historical FS'!D63 -> 302.92834 | E44: ='Historical FS'!E63 -> 302.92834 | F44: ='Historical FS'!F63 -> 302.92834 | G44: ='Historical FS'!G63 -> 302.92834 | H44: =G44 -> 302.92834 | I44: =H44 -> 302.92834 | J44: =I44 -> 302.92834 | K44: =J44 -> 302.92834 | L44: =K44 -> 302.92834 | M44: =L44 -> 302.92834 | N44: =M44 -> 302.92834 | O44: =N44 -> 302.92834 | ... Q44: =P44 -> 302.92834
B45: Additional Paid-in Capital | C45: ='Historical FS'!C64 -> 93.168372 | D45: ='Historical FS'!D64 -> 93.168372 | E45: ='Historical FS'!E64 -> 93.168372 | F45: ='Historical FS'!F64 -> 93.168372 | G45: ='Historical FS'!G64 -> 93.168372 | H45: =G45 -> 93.168372 | I45: =H45 -> 93.168372 | J45: =I45 -> 93.168372 | K45: =J45 -> 93.168372 | L45: =K45 -> 93.168372 | M45: =L45 -> 93.168372 | N45: =M45 -> 93.168372 | O45: =N45 -> 93.168372 | ... Q45: =P45 -> 93.168372
B46: Revaluation Reserve | C46: ='Historical FS'!C65 -> 3133.2448 | D46: ='Historical FS'!D65 -> 3130.3391 | E46: ='Historical FS'!E65 -> 3075.967 | F46: ='Historical FS'!F65 -> 3073.0612 | G46: ='Historical FS'!G65 -> 3376.1917 | H46: =G46 -> 3376.1917 | I46: =H46 -> 3376.1917 | J46: =I46 -> 3376.1917 | K46: =J46 -> 3376.1917 | L46: =K46 -> 3376.1917 | M46: =L46 -> 3376.1917 | N46: =M46 -> 3376.1917 | O46: =N46 -> 3376.1917 | ... Q46: =P46 -> 3376.1917
B47: Retained Earnings | C47: ='Historical FS'!C66 -> 5909.649 | D47: ='Historical FS'!D66 -> 6611.9943 | E47: ='Historical FS'!E66 -> 6940.3504 | F47: ='Historical FS'!F66 -> 8020.956 | G47: ='Historical FS'!G66 -> 8337.044 | H47: =G47+'Income Statement'!H35+'Cash Flow Statement'!H31 -> 9132.3645 | I47: =H47+'Income Statement'!I35+'Cash Flow Statement'!I31 -> 10112.118 | J47: =I47+'Income Statement'!J35+'Cash Flow Statement'!J31 -> 11272.301 | K47: =J47+'Income Statement'!K35+'Cash Flow Statement'!K31 -> 12452.214 | L47: =K47+'Income Statement'!L35+'Cash Flow Statement'!L31 -> 13727.19 | M47: =L47+'Income Statement'!M35+'Cash Flow Statement'!M31 -> 15201.605 | N47: =M47+'Income Statement'!N35+'Cash Flow Statement'!N31 -> 16495.098 | O47: =N47+'Income Statement'!O35+'Cash Flow Statement'!O31 -> 17969.094 | ... Q47: =P47+'Income Statement'!Q35+'Cash Flow Statement'!Q31 -> 21128.556
B48: Total Equity | C48: =SUM(C44:C47) -> 9438.9906 | D48: =SUM(D44:D47) -> 10138.43 | E48: =SUM(E44:E47) -> 10412.414 | F48: =SUM(F44:F47) -> 11490.114 | G48: =SUM(G44:G47) -> 12109.332 | H48: =SUM(H44:H47) -> 12904.653 | I48: =SUM(I44:I47) -> 13884.406 | J48: =SUM(J44:J47) -> 15044.589 | ... Q48: =SUM(Q44:Q47) -> 24900.845
B50: Total Liabilities and Equity | C50: =C41+C48 -> 13444.931 | D50: =D41+D48 -> 15955.693 | E50: =E41+E48 -> 14593.957 | F50: =F41+F48 -> 15725.218 | G50: =G41+G48 -> 15761.554 | H50: =H41+H48 -> 16736.2 | I50: =I41+I48 -> 17900.921 | J50: =J41+J48 -> 19118.899 | ... Q50: =Q41+Q48 -> 29297.486
B52: Balance? | C52: =IF(C23=C50, "Y", "N") -> Y | D52: =IF(D23=D50, "Y", "N") -> Y | E52: =IF(E23=E50, "Y", "N") -> Y | F52: =IF(F23=F50, "Y", "N") -> Y | G52: =IF(G23=G50, "Y", "N") -> Y | H52: =IF(H23=H50, "Y", "N") -> Y | I52: =IF(I23=I50, "Y", "N") -> Y | J52: =IF(J23=J50, "Y", "N") -> Y | ... Q52: =IF(Q23=Q50, "Y", "N") -> Y

Sheet Cash Flow Statement
B2: Cash Flow Statement - Walton Hi-Tech Industries PLC
B3: Years | C3: 2021 | D3: 2022 | E3: 2023 | F3: 2024 | G3: 2025 | H3: 2026 | I3: 2027 | J3: 2028 | K3: 2029 | L3: 2030 | M3: 2031 | N3: 2032 | O3: 2033 | P3: 2034 | Q3: 2035
Q4: BDT in Crore
B5: Cash Flow Statement
B6: Cash Flow from Operations
B7: Net Profit | C7: ='Income Statement'!C35 -> 1639.2036 | D7: ='Income Statement'!D35 -> 1216.6151 | E7: ='Income Statement'!E35 -> 782.67792 | F7: ='Income Statement'!F35 -> 1356.5251 | G7: ='Income Statement'!G35 -> 1036.616 | H7: ='Income Statement'!H35 -> 1325.5342 | I7: ='Income Statement'!I35 -> 1632.9221 | J7: ='Income Statement'!J35 -> 1933.6381 | ... Q7: ='Income Statement'!Q35 -> 2691.2374
B8: Depreciation & Amortization | C8: ='Income Statement'!C22 -> 168.76159 | D8: ='Income Statement'!D22 -> 192.86081 | E8: ='Income Statement'!E22 -> 214.69746 | F8: ='Income Statement'!F22 -> 251.59587 | G8: ='Income Statement'!G22 -> 296.08111 | H8: ='Income Statement'!H22 -> 249.60035 | I8: ='Income Statement'!I22 -> 264.24696 | J8: ='Income Statement'!J22 -> 278.79498 | ... Q8: ='Income Statement'!Q22 -> 408.97362
B9: Other Non-Cash Adjustments | C9: =SUM('Historical FS'!C74:C77) -> 21.040611 | D9: =SUM('Historical FS'!D74:D77) -> 424.84853 | E9: =SUM('Historical FS'!E74:E77) -> 730.56167 | F9: =SUM('Historical FS'!F74:F77) -> 477.78923 | G9: =SUM('Historical FS'!G74:G77) -> 412.18048 | H9: 0 | I9: 0 | J9: 0 | K9: 0 | L9: 0 | M9: 0 | N9: 0 | O9: 0 | P9: 0 | Q9: 0
B10: Change in Accounts Receivable | C10: ='Historical FS'!C78 -> -939.523 | D10: ='Historical FS'!D78 -> -901.81409 | E10: ='Historical FS'!E78 -> 723.76026 | F10: ='Historical FS'!F78 -> -254.44947 | G10: ='Historical FS'!G78 -> 159.01845 | H10: =-('Working Capital Schedule'!H7-'Working Capital Schedule'!G7) -> -96.862461 | I10: =-('Working Capital Schedule'!I7-'Working Capital Schedule'!H7) -> -785.72519 | J10: =-('Working Capital Schedule'!J7-'Working Capital Schedule'!I7) -> -331.6018 | K10: =-('Working Capital Schedule'!K7-'Working Capital Schedule'!J7) -> -328.63491 | L10: =-('Working Capital Schedule'!L7-'Working Capital Schedule'!K7) -> -310.04845 | M10: =-('Working Capital Schedule'!M7-'Working Capital Schedule'!L7) -> -264.10579 | N10: =-('Working Capital Schedule'!N7-'Working Capital Schedule'!M7) -> -262.90885 | O10: =-('Working Capital Schedule'!O7-'Working Capital Schedule'!N7) -> -263.04907 | ... Q10: =-('Working Capital Schedule'!Q7-'Working Capital Schedule'!P7) -> -240.65265
B11: Change in Inventory | C11: ='Historical FS'!C79 -> -219.73056 | D11: ='Historical FS'!D79 -> -1206.7057 | E11: ='Historical FS'!E79 -> 1062.4086 | F11: ='Historical FS'!F79 -> -60.913018 | G11: ='Historical FS'!G79 -> -346.60762 | H11: =-('Working Capital Schedule'!H5-'Working Capital Schedule'!G5) -> 331.2836 | I11: =-('Working Capital Schedule'!I5-'Working Capital Schedule'!H5) -> -558.73791 | J11: =-('Working Capital Schedule'!J5-'Working Capital Schedule'!I5) -> -182.24113 | K11: =-('Working Capital Schedule'!K5-'Working Capital Schedule'!J5) -> -230.04444 | L11: =-('Working Capital Schedule'!L5-'Working Capital Schedule'!K5) -> -217.03392 | M11: =-('Working Capital Schedule'!M5-'Working Capital Schedule'!L5) -> -121.27847 | N11: =-('Working Capital Schedule'!N5-'Working Capital Schedule'!M5) -> -181.11499 | O11: =-('Working Capital Schedule'!O5-'Working Capital Schedule'!N5) -> -42.33246 | ... Q11: =-('Working Capital Schedule'!Q5-'Working Capital Schedule'!P5) -> -160.4351
B12: Change in Prepaid Expenses | H12: =-('Working Capital Schedule'!H9-'Working Capital Schedule'!G9) -> -221.7332 | I12: =-('Working Capital Schedule'!I9-'Working Capital Schedule'!H9) -> -67.349489 | J12: =-('Working Capital Schedule'!J9-'Working Capital Schedule'!I9) -> -20.279142 | K12: =-('Working Capital Schedule'!K9-'Working Capital Schedule'!J9) -> -22.637902 | L12: =-('Working Capital Schedule'!L9-'Working Capital Schedule'!K9) -> -19.838694 | M12: =-('Working Capital Schedule'!M9-'Working Capital Schedule'!L9) -> 23.486991 | N12: =-('Working Capital Schedule'!N9-'Working Capital Schedule'!M9) -> -21.909071 | O12: =-('Working Capital Schedule'!O9-'Working Capital Schedule'!N9) -> -21.920756 | ... Q12: =-('Working Capital Schedule'!Q9-'Working Capital Schedule'!P9) -> -20.054387
B13: Change in Accounts Payable | C13: ='Historical FS'!C80 -> 105.18648 | D13: ='Historical FS'!D80 -> 165.67774 | E13: ='Historical FS'!E80 -> -152.34475 | F13: ='Historical FS'!F80 -> 57.210386 | G13: ='Historical FS'!G80 -> -122.70617 | H13: ='Working Capital Schedule'!H14-'Working Capital Schedule'!G14 -> 154.73338 | I13: ='Working Capital Schedule'!I14-'Working Capital Schedule'!H14 -> 83.810686 | J13: ='Working Capital Schedule'!J14-'Working Capital Schedule'!I14 -> 27.33617 | K13: ='Working Capital Schedule'!K14-'Working Capital Schedule'!J14 -> 34.506665 | L13: ='Working Capital Schedule'!L14-'Working Capital Schedule'!K14 -> 32.555088 | M13: ='Working Capital Schedule'!M14-'Working Capital Schedule'!L14 -> 18.19177 | N13: ='Working Capital Schedule'!N14-'Working Capital Schedule'!M14 -> 27.167248 | O13: ='Working Capital Schedule'!O14-'Working Capital Schedule'!N14 -> 6.349869 | ... Q13: ='Working Capital Schedule'!Q14-'Working Capital Schedule'!P14 -> 24.065265
B14: Change in Accrued Expenses | H14: ='Working Capital Schedule'!H16-'Working Capital Schedule'!G16 -> 24.592337 | I14: ='Working Capital Schedule'!I16-'Working Capital Schedule'!H16 -> 101.15712 | J14: ='Working Capital Schedule'!J16-'Working Capital Schedule'!I16 -> 30.458726 | K14: ='Working Capital Schedule'!K16-'Working Capital Schedule'!J16 -> 34.001521 | L14: ='Working Capital Schedule'!L16-'Working Capital Schedule'!K16 -> 29.797186 | M14: ='Working Capital Schedule'!M16-'Working Capital Schedule'!L16 -> -35.27683 | N14: ='Working Capital Schedule'!N16-'Working Capital Schedule'!M16 -> 32.906836 | O14: ='Working Capital Schedule'!O16-'Working Capital Schedule'!N16 -> 32.924386 | ... Q14: ='Working Capital Schedule'!Q16-'Working Capital Schedule'!P16 -> 30.121151
B15: Change in Other WC | C15: =SUM('Historical FS'!C81:C82) -> 191.58948 | D15: =SUM('Historical FS'!D81:D82) -> -131.05378 | E15: =SUM('Historical FS'!E81:E82) -> 26.253443 | F15: =SUM('Historical FS'!F81:F82) -> -102.15409 | G15: =SUM('Historical FS'!G81:G82) -> 328.4676 | H15: 0 | I15: 0 | J15: 0 | K15: 0 | L15: 0 | M15: 0 | N15: 0 | O15: 0 | P15: 0 | Q15: 0
B16: Net Cash from Operations | C16: =SUM(C7:C15) -> 966.52816 | D16: =SUM(D7:D15) -> -239.57147 | E16: =SUM(E7:E15) -> 3388.0146 | F16: =SUM(F7:F15) -> 1725.604 | G16: =SUM(G7:G15) -> 1763.0499 | H16: =SUM(H7:H15) -> 1767.1482 | I16: =SUM(I7:I15) -> 670.3243 | J16: =SUM(J7:J15) -> 1736.1059 | ... Q16: =SUM(Q7:Q15) -> 2733.2553
D17: =(D15-D12-D14) -> -131.05378 | E17: =(E15-E12-E14) -> 26.253443
B18: Cash Flow from Investing
B19: Capital Expenditures | C19: ='Historical FS'!C84 -> -459.55299 | D19: ='Historical FS'!D84 -> -761.87803 | E19: ='Historical FS'!E84 -> -642.47735 | F19: ='Historical FS'!F84 -> -480.08757 | G19: ='Historical FS'!G84 -> -519.65592 | H19: =-('Income Statement'!H6*Assumptions!D29+Assumptions!D31) -> -704.00984 | I19: =-('Income Statement'!I6*Assumptions!E29+Assumptions!E31) -> -715.59742 | J19: =-('Income Statement'!J6*Assumptions!F29+Assumptions!F31) -> -768.45601 | K19: =-('Income Statement'!K6*Assumptions!G29+Assumptions!G31) -> -820.84167 | L19: =-('Income Statement'!L6*Assumptions!H29+Assumptions!H31) -> -870.26457 | M19: =-('Income Statement'!M6*Assumptions!I29+Assumptions!I31) -> -912.36404 | N19: =-('Income Statement'!N6*Assumptions!J29+Assumptions!J31) -> -954.27271 | O19: =-('Income Statement'!O6*Assumptions!K29+Assumptions!K31) -> -996.20373 | ... Q19: =-('Income Statement'!Q6*Assumptions!M29+Assumptions!M31) -> -1073.5168
B20: Sale of Property, Plant & Equipment | C20: ='Historical FS'!C85 -> 11.754631 | D20: ='Historical FS'!D85 -> 0.7850469 | E20: ='Historical FS'!E85 -> 1.8922211 | F20: ='Historical FS'!F85 -> 0.4946368 | G20: ='Historical FS'!G85 -> 0.0586024 | H20: 0 | I20: 0 | J20: 0 | K20: 0 | L20: 0 | M20: 0 | N20: 0 | O20: 0 | P20: 0 | Q20: 0
B21: Sale (Purchase) of Intangibles | C21: ='Historical FS'!C86 -> -0.1831593 | D21: ='Historical FS'!D86 -> -0.3637488 | E21: ='Historical FS'!E86 -> -1.148884 | F21: ='Historical FS'!F86 -> -0.3824614 | G21: ='Historical FS'!G86 -> -3.792673 | H21: 0 | I21: 0 | J21: 0 | K21: 0 | L21: 0 | M21: 0 | N21: 0 | O21: 0 | P21: 0 | Q21: 0
B22: Investment in Securities | C22: ='Historical FS'!C87 -> -102.00127 | D22: ='Historical FS'!D87 -> 93.590996 | E22: ='Historical FS'!E87 -> 10.01047 | F22: ='Historical FS'!F87 -> 2.6587882 | G22: ='Historical FS'!G87 -> 44.161243 | H22: 0 | I22: 0 | J22: 0 | K22: 0 | L22: 0 | M22: 0 | N22: 0 | O22: 0 | P22: 0 | Q22: 0
B23: Other Investing Activities | C23: ='Historical FS'!C88 -> 20.202402 | D23: ='Historical FS'!D88 -> 20.722549 | E23: ='Historical FS'!E88 -> 8.1418239 | F23: ='Historical FS'!F88 -> 18.958533 | G23: ='Historical FS'!G88 -> 36.124163 | H23: 0 | I23: 0 | J23: 0 | K23: 0 | L23: 0 | M23: 0 | N23: 0 | O23: 0 | P23: 0 | Q23: 0
B24: Net Cash from Investing | C24: =SUM(C19:C23) -> -529.78039 | D24: =SUM(D19:D23) -> -647.14319 | E24: =SUM(E19:E23) -> -623.58172 | F24: =SUM(F19:F23) -> -458.35807 | G24: =SUM(G19:G23) -> -443.10458 | H24: =SUM(H19:H22) -> -704.00984 | I24: =SUM(I19:I22) -> -715.59742 | J24: =SUM(J19:J22) -> -768.45601 | K24: =SUM(K19:K22) -> -820.84167 | L24: =SUM(L19:L22) -> -870.26457 | M24: =SUM(M19:M22) -> -912.36404 | N24: =SUM(N19:N22) -> -954.27271 | O24: =SUM(O19:O22) -> -996.20373 | ... Q24: =SUM(Q19:Q22) -> -1073.5168
B26: Cash Flow from Financing
B27: Short Term Loan-Received/(Repaid), Net | C27: ='Historical FS'!C90 -> 139.27831 | D27: ='Historical FS'!D90 -> 1877.9659 | E27: ='Historical FS'!E90 -> -1856.4035 | F27: ='Historical FS'!F90 -> -285.24495 | G27: ='Historical FS'!G90 -> -335.9625 | H27: ='Debt Schedule'!D13+'Debt Schedule'!D14 -> 0 | I27: ='Debt Schedule'!E13+'Debt Schedule'!E14 -> 0 | J27: ='Debt Schedule'!F13+'Debt Schedule'!F14 -> 0 | K27: ='Debt Schedule'!G13+'Debt Schedule'!G14 -> 0 | L27: ='Debt Schedule'!H13+'Debt Schedule'!H14 -> 0 | M27: ='Debt Schedule'!I13+'Debt Schedule'!I14 -> 0 | N27: ='Debt Schedule'!J13+'Debt Schedule'!J14 -> 0 | O27: ='Debt Schedule'!K13+'Debt Schedule'!K14 -> 0 | ... Q27: ='Debt Schedule'!M13+'Debt Schedule'!M14 -> 0
B28: Long Term Loan-Received/(Repaid), Net | C28: ='Historical FS'!C91 -> -9.1645422 | D28: ='Historical FS'!D91 -> -185.11114 | E28: ='Historical FS'!E91 -> 292.4919 | F28: ='Historical FS'!F91 -> 145.76521 | G28: ='Historical FS'!G91 -> 27.58348 | H28: ='Debt Schedule'!D21+'Debt Schedule'!D22 -> 0 | I28: ='Debt Schedule'!E21+'Debt Schedule'!E22 -> 0 | J28: ='Debt Schedule'!F21+'Debt Schedule'!F22 -> 0 | K28: ='Debt Schedule'!G21+'Debt Schedule'!G22 -> 0 | L28: ='Debt Schedule'!H21+'Debt Schedule'!H22 -> 0 | M28: ='Debt Schedule'!I21+'Debt Schedule'!I22 -> 0 | N28: ='Debt Schedule'!J21+'Debt Schedule'!J22 -> 0 | O28: ='Debt Schedule'!K21+'Debt Schedule'!K22 -> 0 | ... Q28: ='Debt Schedule'!M21+'Debt Schedule'!M22 -> 0
B29: Lease Payment | C29: ='Historical FS'!C92 -> 0 | D29: ='Historical FS'!D92 -> -3.5346059 | E29: ='Historical FS'!E92 -> -3.0258351 | F29: ='Historical FS'!F92 -> -3.7516806 | G29: ='Historical FS'!G92 -> -4.1340652 | H29: ='Debt Schedule'!D29+'Debt Schedule'!D30 -> 0 | I29: ='Debt Schedule'!E29+'Debt Schedule'!E30 -> 0 | J29: ='Debt Schedule'!F29+'Debt Schedule'!F30 -> 0 | K29: ='Debt Schedule'!G29+'Debt Schedule'!G30 -> 0 | L29: ='Debt Schedule'!H29+'Debt Schedule'!H30 -> 0 | M29: ='Debt Schedule'!I29+'Debt Schedule'!I30 -> 0 | N29: ='Debt Schedule'!J29+'Debt Schedule'!J30 -> 0 | O29: ='Debt Schedule'!K29+'Debt Schedule'!K30 -> 0 | ... Q29: ='Debt Schedule'!M29+'Debt Schedule'!M30 -> 0
B30: Issuance of Common Stock | C30: ='Historical FS'!C93 -> 35.130934 | D30: ='Historical FS'!D93 -> 0 | E30: ='Historical FS'!E93 -> 0 | F30: ='Historical FS'!F93 -> 0 | G30: ='Historical FS'!G93 -> 0 | H30: 0 | I30: 0 | J30: 0 | K30: 0 | L30: 0 | M30: 0 | N30: 0 | O30: 0 | P30: 0 | Q30: 0
B31: Common Dividends Paid | C31: ='Historical FS'!C94 -> -230.70194 | D31: ='Historical FS'!D94 -> -517.32086 | E31: ='Historical FS'!E94 -> -457.27919 | F31: ='Historical FS'!F94 -> -279.05848 | G31: ='Historical FS'!G94 -> -723.66632 | H31: =-'Income Statement'!H35*Assumptions!D33 -> -530.21368 | I31: =-'Income Statement'!I35*Assumptions!E33 -> -653.16884 | J31: =-'Income Statement'!J35*Assumptions!F33 -> -773.45523 | K31: =-'Income Statement'!K35*Assumptions!G33 -> -786.60892 | L31: =-'Income Statement'!L35*Assumptions!H33 -> -849.98382 | M31: =-'Income Statement'!M35*Assumptions!I33 -> -982.94334 | N31: =-'Income Statement'!N35*Assumptions!J33 -> -862.32902 | O31: =-'Income Statement'!O35*Assumptions!K33 -> -982.66379 | ... Q31: =-'Income Statement'!Q35*Assumptions!M33 -> -1076.495
B32: Other Financing Activities | C32: ='Historical FS'!C95 -> -147.6116 | D32: ='Historical FS'!D95 -> -423.53061 | E32: ='Historical FS'!E95 -> -730.62961 | F32: ='Historical FS'!F95 -> -431.94744 | G32: ='Historical FS'!G95 -> -431.95283 | H32: 0 | I32: 0 | J32: 0 | K32: 0 | L32: 0 | M32: 0 | N32: 0 | O32: 0 | P32: 0 | Q32: 0
B33: Net Cash from Financing | C33: =SUM(C27:C32) -> -213.06884 | D33: =SUM(D27:D32) -> 748.46866 | E33: =SUM(E27:E32) -> -2754.8463 | F33: =SUM(F27:F32) -> -854.23735 | G33: =SUM(G27:G32) -> -1468.1322 | H33: =SUM(H27:H32) -> -530.21368 | I33: =SUM(I27:I32) -> -653.16884 | J33: =SUM(J27:J32) -> -773.45523 | ... Q33: =SUM(Q27:Q32) -> -1076.495
B35: Net Change in Cash | C35: =C16+C24+C33 -> 223.67894 | D35: =D16+D24+D33 -> -138.246 | E35: =E16+E24+E33 -> 9.5865735 | F35: =F16+F24+F33 -> 413.00862 | G35: =G16+G24+G33 -> -148.18694 | H35: =H16+H24+H33 -> 532.92469 | I35: =I16+I24+I33 -> -698.44197 | J35: =J16+J24+J33 -> 194.19463 | ... Q35: =Q16+Q24+Q33 -> 583.24356
B36: Beginning Cash | C36: ='Historical FS'!C98 -> 146.69793 | D36: ='Historical FS'!D98 -> 370.38257 | E36: ='Historical FS'!E98 -> 232.13656 | F36: ='Historical FS'!F98 -> 241.72322 | G36: ='Historical FS'!G98 -> 654.73263 | H36: =G37 -> 506.5457 | I36: =H37 -> 1039.4704 | J36: =I37 -> 341.02842 | K36: =J37 -> 535.22305 | L36: =K37 -> 676.06352 | M36: =L37 -> 907.74635 | N36: =M37 -> 1420.3644 | O36: =N37 -> 1702.0611 | ... Q36: =P37 -> 2784.7621
B37: Ending Cash | C37: =SUM(C35:C36) -> 370.37687 | D37: =SUM(D35:D36) -> 232.13656 | E37: =SUM(E35:E36) -> 241.72314 | F37: =SUM(F35:F36) -> 654.73183 | G37: =SUM(G35:G36) -> 506.5457 | H37: =SUM(H35:H36) -> 1039.4704 | I37: =SUM(I35:I36) -> 341.02842 | J37: =SUM(J35:J36) -> 535.22305 | ... Q37: =SUM(Q35:Q36) -> 3368.0057
B39: Supplemental Data:
B40: Cash flow before debt paydown | H40: =H16+H24+H30+H31+H32 -> 532.92469 | I40: =I16+I24+I30+I31+I32 -> -698.44197 | J40: =J16+J24+J30+J31+J32 -> 194.19463 | K40: =K16+K24+K30+K31+K32 -> 140.84048 | L40: =L16+L24+L30+L31+L32 -> 231.68283 | M40: =M16+M24+M30+M31+M32 -> 512.61801 | N40: =N16+N24+N30+N31+N32 -> 281.69675 | O40: =O16+O24+O30+O31+O32 -> 557.62937 | ... Q40: =Q16+Q24+Q30+Q31+Q32 -> 583.24356

Sheet Ratio Analysis
B2: Ratio Analysis - Walton Hi-Tech Industries PLC
B3: Years | C3: 2021 | D3: 2022 | E3: 2023 | F3: 2024 | G3: 2025 | H3: 5Y Trend | I3: Mean | J3: Median
B5: Growth Ratios
B6: Sales Growth | D6: =IFERROR('Revenue Forecast'!D30,0) -> 0.16771648 | E6: =IFERROR('Revenue Forecast'!E30,0) -> -0.18740322 | F6: =IFERROR('Revenue Forecast'!F30,0) -> 0.13178123 | G6: =IFERROR('Revenue Forecast'!G30,0) -> -0.057223281 | I6: =AVERAGE(C6:G6) -> 0.013717804 | J6: =MEDIAN(C6:G6) -> 0.037278975
B7: EBITDA Growth | D7: =IFERROR('Historical FS'!D12/'Historical FS'!C12-1,0) -> -0.08339279 | E7: =IFERROR('Historical FS'!E12/'Historical FS'!D12-1,0) -> -0.081097591 | F7: =IFERROR('Historical FS'!F12/'Historical FS'!E12-1,0) -> 0.20307204 | G7: =IFERROR('Historical FS'!G12/'Historical FS'!F12-1,0) -> -0.16566848 | I7: =AVERAGE(C7:G7) -> -0.031771706 | J7: =MEDIAN(C7:G7) -> -0.082245191
B8: EBIT Growth | D8: =IFERROR('Historical FS'!D14/'Historical FS'!C14-1,0) -> -0.10312507 | E8: =IFERROR('Historical FS'!E14/'Historical FS'!D14-1,0) -> -0.10269786 | F8: =IFERROR('Historical FS'!F14/'Historical FS'!E14-1,0) -> 0.20737601 | G8: =IFERROR('Historical FS'!G14/'Historical FS'!F14-1,0) -> -0.2115091 | I8: =AVERAGE(C8:G8) -> -0.052489005 | J8: =MEDIAN(C8:G8) -> -0.10291146
B9: Net Profit Growth | D9: =IFERROR('Historical FS'!D23/'Historical FS'!C23-1,0) -> -0.25780126 | E9: =IFERROR('Historical FS'!E23/'Historical FS'!D23-1,0) -> -0.35667572 | F9: =IFERROR('Historical FS'!F23/'Historical FS'!E23-1,0) -> 0.73318521 | G9: =IFERROR('Historical FS'!G23/'Historical FS'!F23-1,0) -> -0.23583028 | I9: =AVERAGE(C9:G9) -> -0.029280514 | J9: =MEDIAN(C9:G9) -> -0.24681577
B10: Dividend Growth | D10: =IFERROR('Historical FS'!D27/'Historical FS'!C27-1,0) -> 0 | E10: =IFERROR('Historical FS'!E27/'Historical FS'!D27-1,0) -> 0.2 | F10: =IFERROR('Historical FS'!F27/'Historical FS'!E27-1,0) -> 0.16666667 | G10: =IFERROR('Historical FS'!G27/'Historical FS'!F27-1,0) -> -0.5 | I10: =AVERAGE(C10:G10) -> -0.033333333 | J10: =MEDIAN(C10:G10) -> 0.083333333
B12: Profitability Ratios
B13: Gross Margin | C13: ='Income Statement'!C11 -> 0.37790514 | D13: ='Income Statement'!D11 -> 0.3248569 | E13: ='Income Statement'!E11 -> 0.35181397 | F13: ='Income Statement'!F11 -> 0.38135631 | G13: ='Income Statement'!G11 -> 0.36049004 | I13: =AVERAGE(C13:G13) -> 0.35928447 | J13: =MEDIAN(C13:G13) -> 0.36049004
B14: EBITDA Margin | C14: ='Income Statement'!C20 -> 0.30068566 | D14: ='Income Statement'!D20 -> 0.23602531 | E14: ='Income Statement'!E20 -> 0.26690264 | F14: ='Income Statement'!F20 -> 0.28371482 | G14: ='Income Statement'!G20 -> 0.25107983 | I14: =AVERAGE(C14:G14) -> 0.26768165 | J14: =MEDIAN(C14:G14) -> 0.26690264
B15: EBIT Margin | C15: ='Income Statement'!C24 -> 0.27655961 | D15: ='Income Statement'!D24 -> 0.21241404 | E15: ='Income Statement'!E24 -> 0.23455615 | F15: ='Income Statement'!F24 -> 0.2502228 | G15: ='Income Statement'!G24 -> 0.20927373 | I15: =AVERAGE(C15:G15) -> 0.23660527 | J15: =MEDIAN(C15:G15) -> 0.23455615
B16: Net Profit Margin | C16: ='Income Statement'!C36 -> 0.23433957 | D16: ='Income Statement'!D36 -> 0.14894589 | E16: ='Income Statement'!E36 -> 0.11791887 | F16: ='Income Statement'!F36 -> 0.18057831 | G16: ='Income Statement'!G36 -> 0.14636823 | I16: =AVERAGE(C16:G16) -> 0.16563017 | J16: =MEDIAN(C16:G16) -> 0.14894589
B17: Return on Equity (ROE) | C17: ='Income Statement'!C35/'Balance Sheet'!C48 -> 0.17366302 | D17: ='Income Statement'!D35/'Balance Sheet'!D48 -> 0.12000034 | E17: ='Income Statement'!E35/'Balance Sheet'!E48 -> 0.075167768 | F17: ='Income Statement'!F35/'Balance Sheet'!F48 -> 0.1180602 | G17: ='Income Statement'!G35/'Balance Sheet'!G48 -> 0.085604723 | I17: =AVERAGE(C17:G17) -> 0.11449921 | J17: =MEDIAN(C17:G17) -> 0.1180602
B18: Return on Assets (ROA) | C18: ='Income Statement'!C35/'Balance Sheet'!C23 -> 0.12191982 | D18: ='Income Statement'!D35/'Balance Sheet'!D23 -> 0.076249588 | E18: ='Income Statement'!E35/'Balance Sheet'!E23 -> 0.053630274 | F18: ='Income Statement'!F35/'Balance Sheet'!F23 -> 0.086264311 | G18: ='Income Statement'!G35/'Balance Sheet'!G23 -> 0.065768646 | I18: =AVERAGE(C18:G18) -> 0.080766528 | J18: =MEDIAN(C18:G18) -> 0.076249588
B20: Efficiency Ratios
B21: Asset Turnover | C21: ='Income Statement'!C6/AVERAGE('Balance Sheet'!C23) -> 0.52026988 | D21: ='Income Statement'!D6/AVERAGE('Balance Sheet'!C23:D23) -> 0.5556459 | E21: ='Income Statement'!E6/AVERAGE('Balance Sheet'!D23:E23) -> 0.43453375 | F21: ='Income Statement'!F6/AVERAGE('Balance Sheet'!E23:F23) -> 0.49553561 | G21: ='Income Statement'!G6/AVERAGE('Balance Sheet'!F23:G23) -> 0.44985542 | I21: =AVERAGE(C21:G21) -> 0.49116811 | J21: =MEDIAN(C21:G21) -> 0.49553561
B22: Fixed Asset Turnover | C22: ='Income Statement'!C6/AVERAGE('Balance Sheet'!C21) -> 1.055809 | D22: ='Income Statement'!D6/AVERAGE('Balance Sheet'!C21:D21) -> 1.1804179 | E22: ='Income Statement'!E6/AVERAGE('Balance Sheet'!D21:E21) -> 0.89362251 | F22: ='Income Statement'!F6/AVERAGE('Balance Sheet'!E21:F21) -> 0.96975137 | G22: ='Income Statement'!G6/AVERAGE('Balance Sheet'!F21:G21) -> 0.86789299 | I22: =AVERAGE(C22:G22) -> 0.99349876 | J22: =MEDIAN(C22:G22) -> 0.96975137
B23: Debtor Turnover | C23: ='Income Statement'!C6/AVERAGE('Balance Sheet'!C9) -> 2.1273056 | D23: ='Income Statement'!D6/AVERAGE('Balance Sheet'!C9:D9) -> 2.1846998 | E23: ='Income Statement'!E6/AVERAGE('Balance Sheet'!D9:E9) -> 1.7337084 | F23: ='Income Statement'!F6/AVERAGE('Balance Sheet'!E9:F9) -> 2.088974 | G23: ='Income Statement'!G6/AVERAGE('Balance Sheet'!F9:G9) -> 1.9320612 | I23: =AVERAGE(C23:G23) -> 2.0133498 | J23: =MEDIAN(C23:G23) -> 2.088974
B24: Creditor Turnover | C24: =IFERROR((Data!E15/10000000)/(AVERAGE('Balance Sheet'!C26)),0) -> 11.723199 | D24: =IFERROR((Data!F15/10000000)/(AVERAGE('Balance Sheet'!D26:E26)),0) -> 14.366485 | E24: =IFERROR((Data!G15/10000000)/(AVERAGE('Balance Sheet'!E26:F26)),0) -> 8.2139317 | F24: =IFERROR((Data!H15/10000000)/(AVERAGE('Balance Sheet'!F26:G26)),0) -> 11.68501 | G24: =IFERROR((Data!I15/10000000)/(AVERAGE('Balance Sheet'!G26:H26)),0) -> 12.905183 | I24: =AVERAGE(C24:G24) -> 11.778762 | J24: =MEDIAN(C24:G24) -> 11.723199
B25: Inventory Turnover | C25: ='Income Statement'!C8/AVERAGE('Balance Sheet'!C10) -> 1.8033351 | D25: ='Income Statement'!D8/AVERAGE('Balance Sheet'!C10:D10) -> 1.8282276 | E25: ='Income Statement'!E8/AVERAGE('Balance Sheet'!D10:E10) -> 1.3929763 | F25: ='Income Statement'!F8/AVERAGE('Balance Sheet'!E10:F10) -> 1.7958517 | G25: ='Income Statement'!G8/AVERAGE('Balance Sheet'!F10:G10) -> 1.6224446 | I25: =AVERAGE(C25:G25) -> 1.6885671 | J25: =MEDIAN(C25:G25) -> 1.7958517
B26: Capital Turnover | C26: ='Income Statement'!C6/'Balance Sheet'!C48 -> 0.74107422 | D26: ='Income Statement'!D6/'Balance Sheet'!D48 -> 0.805664 | E26: ='Income Statement'!E6/'Balance Sheet'!E48 -> 0.63745325 | F26: ='Income Statement'!F6/'Balance Sheet'!F48 -> 0.65378947 | G26: ='Income Statement'!G6/'Balance Sheet'!G48 -> 0.58485863 | I26: =AVERAGE(C26:G26) -> 0.68456791 | J26: =MEDIAN(C26:G26) -> 0.65378947
B27: Inventory Days (DIO) | C27: ='Working Capital Schedule'!C6 -> 0 | D27: ='Working Capital Schedule'!D6 -> 199.64691 | E27: ='Working Capital Schedule'!E6 -> 262.02887 | F27: ='Working Capital Schedule'!F6 -> 203.24618 | G27: ='Working Capital Schedule'!G6 -> 224.96917 | I27: =AVERAGE(C27:G27) -> 177.97822 | J27: =MEDIAN(C27:G27) -> 203.24618
B28: Receivable Days (DSO) | C28: ='Working Capital Schedule'!C8 -> 0 | D28: ='Working Capital Schedule'!D8 -> 167.07101 | E28: ='Working Capital Schedule'!E8 -> 210.53136 | F28: ='Working Capital Schedule'!F8 -> 174.72692 | G28: ='Working Capital Schedule'!G8 -> 188.91741 | I28: =AVERAGE(C28:G28) -> 148.24934 | J28: =MEDIAN(C28:G28) -> 174.72692
B29: Payable Days (DPO) | C29: ='Working Capital Schedule'!C15 -> 0 | D29: ='Working Capital Schedule'!D15 -> 24.835925 | E29: ='Working Capital Schedule'!E15 -> 32.406079 | F29: ='Working Capital Schedule'!F15 -> 26.264207 | G29: ='Working Capital Schedule'!G15 -> 24.310264 | I29: =AVERAGE(C29:G29) -> 21.563295 | J29: =MEDIAN(C29:G29) -> 24.835925
B30: Cash Conversion Cycle (Days) | C30: =C27+C28-C29 -> 0 | D30: =D27+D28-D29 -> 341.882 | E30: =E27+E28-E29 -> 440.15415 | F30: =F27+F28-F29 -> 351.70889 | G30: =G27+G28-G29 -> 389.57631 | I30: =AVERAGE(C30:G30) -> 304.66427 | J30: =MEDIAN(C30:G30) -> 351.70889
B32: Leverage & Solvency Ratios
B33: Debt-to-Equity (D/E) | C33: ='Historical FS'!C69/'Balance Sheet'!C48 -> 0.31407899 | D33: ='Historical FS'!D69/'Balance Sheet'!D48 -> 0.46153414 | E33: ='Historical FS'!E69/'Balance Sheet'!E48 -> 0.29933613 | F33: ='Historical FS'!F69/'Balance Sheet'!F48 -> 0.25908967 | G33: ='Historical FS'!G69/'Balance Sheet'!G48 -> 0.22046498 | I33: =AVERAGE(C33:G33) -> 0.31090078 | J33: =MEDIAN(C33:G33) -> 0.29933613
B34: Debt-to-Assets | C34: ='Historical FS'!C69/'Balance Sheet'!C23 -> 0.22049861 | D34: ='Historical FS'!D69/'Balance Sheet'!D23 -> 0.29326407 | E34: ='Historical FS'!E69/'Balance Sheet'!E23 -> 0.21356865 | F34: ='Historical FS'!F69/'Balance Sheet'!F23 -> 0.18931183 | G34: ='Historical FS'!G69/'Balance Sheet'!G23 -> 0.16937947 | I34: =AVERAGE(C34:G34) -> 0.21720453 | J34: =MEDIAN(C34:G34) -> 0.21356865
B35: Interest Coverage | C35: ='Income Statement'!C23/(-'Income Statement'!C28) -> 15.529934 | D35: ='Income Statement'!D23/(-'Income Statement'!D28) -> 3.6617023 | E35: ='Income Statement'!E23/(-'Income Statement'!E28) -> 2.0659224 | F35: ='Income Statement'!F23/(-'Income Statement'!F28) -> 4.0941103 | G35: ='Income Statement'!G23/(-'Income Statement'!G28) -> 3.3053425 | I35: =AVERAGE(C35:G35) -> 5.7314022 | J35: =MEDIAN(C35:G35) -> 3.6617023
B36: Equity Multiplier | C36: ='Balance Sheet'!C23/'Balance Sheet'!C48 -> 1.4244035 | D36: =IFERROR('Historical FS'!#REF!/'Historical FS'!#REF!,0) -> 0 | E36: =IFERROR('Historical FS'!#REF!/'Historical FS'!#REF!,0) -> 0 | F36: =IFERROR('Historical FS'!#REF!/'Historical FS'!#REF!,0) -> 0 | G36: =IFERROR('Historical FS'!#REF!/'Historical FS'!#REF!,0) -> 0 | I36: =AVERAGE(C36:G36) -> 0.28488069 | J36: =MEDIAN(C36:G36) -> 0
B38: Liquidity
B39: Current Ratio | C39: ='Balance Sheet'!C13/'Balance Sheet'!C32 -> 1.8837659 | D39: ='Balance Sheet'!D13/'Balance Sheet'!D32 -> 1.5932929 | E39: ='Balance Sheet'!E13/'Balance Sheet'!E32 -> 1.96352 | F39: ='Balance Sheet'!F13/'Balance Sheet'!F32 -> 2.2279701 | G39: ='Balance Sheet'!G13/'Balance Sheet'!G32 -> 2.5500822 | I39: =AVERAGE(C39:G39) -> 2.0437262 | J39: =MEDIAN(C39:G39) -> 1.96352
B40: Quick Ratio | C40: =('Balance Sheet'!C13-'Balance Sheet'!C10-'Balance Sheet'!C11)/'Balance Sheet'!C32 -> 1.07886 | D40: =('Balance Sheet'!D13-'Balance Sheet'!D10-'Balance Sheet'!D11)/'Balance Sheet'!D32 -> 0.83261363 | E40: =('Balance Sheet'!E13-'Balance Sheet'!E10-'Balance Sheet'!E11)/'Balance Sheet'!E32 -> 1.0855162 | F40: =('Balance Sheet'!F13-'Balance Sheet'!F10-'Balance Sheet'!F11)/'Balance Sheet'!F32 -> 1.2699596 | G40: =('Balance Sheet'!G13-'Balance Sheet'!G10-'Balance Sheet'!G11)/'Balance Sheet'!G32 -> 1.4614101 | I40: =AVERAGE(C40:G40) -> 1.1456719 | J40: =MEDIAN(C40:G40) -> 1.0855162
B41: Cash Ratio | C41: ='Balance Sheet'!C7/'Balance Sheet'!C32 -> 0.10230882 | D41: ='Balance Sheet'!D7/'Balance Sheet'!D32 -> 0.042311056 | E41: ='Balance Sheet'!E7/'Balance Sheet'!E32 -> 0.068261793 | F41: ='Balance Sheet'!F7/'Balance Sheet'!F32 -> 0.18527616 | G41: ='Balance Sheet'!G7/'Balance Sheet'!G32 -> 0.17712029 | I41: =AVERAGE(C41:G41) -> 0.11505562 | J41: =MEDIAN(C41:G41) -> 0.10230882
B43: Other Ratios
B44: Depreciation & Amortization (% of Opening OA) | C44: ='Historical FS'!C13/SUM('Historical FS'!C41:C43) -> 0.02708478 | D44: ='Historical FS'!D13/SUM('Historical FS'!D41:D43) -> 0.029356608 | E44: ='Historical FS'!E13/SUM('Historical FS'!E41:E43) -> 0.031089788 | F44: ='Historical FS'!F13/SUM('Historical FS'!F41:F43) -> 0.035395279 | G44: ='Historical FS'!G13/SUM('Historical FS'!G41:G43) -> 0.03823449 | I44: =AVERAGE(C44:G44) -> 0.032232189 | J44: =MEDIAN(C44:G44) -> 0.031089788
B45: CapEx (% of Sales) | C45: =IFERROR(-('Historical FS'!C84/'Historical FS'!C6),0) -> 0.065697423 | D45: =IFERROR(-('Historical FS'!D84/'Historical FS'!D6),0) -> 0.093274039 | E45: =IFERROR(-('Historical FS'!E84/'Historical FS'!E6),0) -> 0.096796144 | F45: =IFERROR(-('Historical FS'!F84/'Historical FS'!F6),0) -> 0.063908439 | G45: =IFERROR(-('Historical FS'!G84/'Historical FS'!G6),0) -> 0.073374435 | I45: =AVERAGE(C45:G45) -> 0.078610096 | J45: =MEDIAN(C45:G45) -> 0.073374435
B46: SG&A % of Sales | C46: ='Income Statement'!C14 -> 0.10134553 | D46: ='Income Statement'!D14 -> 0.11244286 | E46: ='Income Statement'!E14 -> 0.11725781 | F46: ='Income Statement'!F14 -> 0.13113351 | G46: ='Income Statement'!G14 -> 0.15121631 | I46: =AVERAGE(C46:G46) -> 0.1226792 | J46: =MEDIAN(C46:G46) -> 0.11725781
B47: Retained Earnings% | C47: =IFERROR('Historical FS'!C29,0) -> 0.53799471 | D47: =IFERROR('Historical FS'!D29,0) -> 0.3775181 | E47: =IFERROR('Historical FS'!E29,0) -> 0 | F47: =IFERROR('Historical FS'!F29,0) -> 0.21840845 | G47: =IFERROR('Historical FS'!G29,0) -> 0.48860081 | I47: =AVERAGE(C47:G47) -> 0.32450441 | J47: =MEDIAN(C47:G47) -> 0.3775181
B48: Self Sustained Growth Rate | C48: =IFERROR(C17*C47,0) -> 0.093429784 | D48: =IFERROR(D17*D47,0) -> 0.0453023 | E48: =IFERROR(E17*E47,0) -> 0 | F48: =IFERROR(F17*F47,0) -> 0.025785345 | G48: =IFERROR(G17*G47,0) -> 0.041826537 | I48: =AVERAGE(C48:G48) -> 0.041268793 | J48: =MEDIAN(C48:G48) -> 0.041826537
B50: CFO/Sales | C50: ='Cash Flow Statement'!C16/'Income Statement'!C6 -> 0.13817429 | D50: ='Cash Flow Statement'!D16/'Income Statement'!D6 -> -0.02932989 | E50: ='Cash Flow Statement'!E16/'Income Statement'!E6 -> 0.51044094 | F50: ='Cash Flow Statement'!F16/'Income Statement'!F6 -> 0.22970947 | G50: ='Cash Flow Statement'!G16/'Income Statement'!G6 -> 0.24893932 | I50: =AVERAGE(C50:G50) -> 0.21958683 | J50: =MEDIAN(C50:G50) -> 0.22970947
B51: CFO/Total Assets | C51: ='Cash Flow Statement'!C16/'Balance Sheet'!C23 -> 0.071887924 | D51: ='Cash Flow Statement'!D16/'Balance Sheet'!D23 -> -0.015014795 | E51: ='Cash Flow Statement'!E16/'Balance Sheet'!E23 -> 0.23215188 | F51: ='Cash Flow Statement'!F16/'Balance Sheet'!F23 -> 0.10973482 | G51: ='Cash Flow Statement'!G16/'Balance Sheet'!G23 -> 0.11185762 | I51: =AVERAGE(C51:G51) -> 0.10212349 | J51: =MEDIAN(C51:G51) -> 0.10973482
B52: CFO/Total Debt | C52: ='Cash Flow Statement'!C16/'Historical FS'!C69 -> 0.32602438 | D52: ='Cash Flow Statement'!D16/'Historical FS'!D69 -> -0.051198892 | E52: ='Cash Flow Statement'!E16/'Historical FS'!E69 -> 1.0870129 | F52: ='Cash Flow Statement'!F16/'Historical FS'!F69 -> 0.57965117 | G52: ='Cash Flow Statement'!G16/'Historical FS'!G69 -> 0.66039655 | I52: =AVERAGE(C52:G52) -> 0.52037722 | J52: =MEDIAN(C52:G52) -> 0.57965117

Sheet DCF Valuation
B2: DCF Valuation - WALTONHIL
B3: Years | C3: 2025 | D3: 2026 | E3: 2027 | F3: 2028 | G3: 2029 | H3: 2030 | I3: 2031 | J3: 2032 | K3: 2033 | L3: 2034 | M3: 2035
B4: FCFF Calculation
B5: EBIT | D5: ='Income Statement'!H23 -> 1802.3634 | E5: ='Income Statement'!I23 -> 2162.059 | F5: ='Income Statement'!J23 -> 2502.5378 | G5: ='Income Statement'!K23 -> 2694.0197 | H5: ='Income Statement'!L23 -> 2878.368 | I5: ='Income Statement'!M23 -> 3249.7344 | J5: ='Income Statement'!N23 -> 3399.0082 | K5: ='Income Statement'!O23 -> 3801.816 | ... M5: ='Income Statement'!Q23 -> 4096.8661 | P5: Sensitivity Anaysis - Enterprise Value
B6: Depreciation & Amortization | D6: ='Income Statement'!H22 -> 249.60035 | E6: ='Income Statement'!I22 -> 264.24696 | F6: ='Income Statement'!J22 -> 278.79498 | G6: ='Income Statement'!K22 -> 294.57782 | H6: ='Income Statement'!L22 -> 311.54046 | I6: ='Income Statement'!M22 -> 329.54936 | J6: ='Income Statement'!N22 -> 348.33475 | K6: ='Income Statement'!O22 -> 367.86546 | ... M6: ='Income Statement'!Q22 -> 408.97362 | P6: Growth Rate (g) | R6: WACC
B7: Changes in Working Capital | D7: =SUM('Cash Flow Statement'!H10:H15) -> 192.01366 | E7: =SUM('Cash Flow Statement'!I10:I15) -> -1226.8448 | F7: =SUM('Cash Flow Statement'!J10:J15) -> -476.32718 | G7: =SUM('Cash Flow Statement'!K10:K15) -> -512.80906 | H7: =SUM('Cash Flow Statement'!L10:L15) -> -484.56879 | I7: =SUM('Cash Flow Statement'!M10:M15) -> -378.98232 | J7: =SUM('Cash Flow Statement'!N10:N15) -> -405.85883 | K7: =SUM('Cash Flow Statement'!O10:O15) -> -288.02803 | ... M7: =SUM('Cash Flow Statement'!Q10:Q15) -> -366.95572 | Q7: =C21 -> 10858.866 | R7: 0.14 | S7: 0.15 | T7: 0.16708233 | U7: 0.17 | V7: 0.18
B8: Capital Expenditures | D8: ='Cash Flow Statement'!H19 -> -704.00984 | E8: ='Cash Flow Statement'!I19 -> -715.59742 | F8: ='Cash Flow Statement'!J19 -> -768.45601 | G8: ='Cash Flow Statement'!K19 -> -820.84167 | H8: ='Cash Flow Statement'!L19 -> -870.26457 | I8: ='Cash Flow Statement'!M19 -> -912.36404 | J8: ='Cash Flow Statement'!N19 -> -954.27271 | K8: ='Cash Flow Statement'!O19 -> -996.20373 | ... M8: ='Cash Flow Statement'!Q19 -> -1073.5168 | Q8: 0.02 | R8: 12908.078 | S8: 11808.813 | T8: 10287.902 | U8: 10064.056 | V8: 9361.3042
B9: Taxes | D9: =-D5*Assumptions!D26 -> 0 | E9: =-E5*Assumptions!E26 -> 0 | F9: =-F5*Assumptions!F26 -> 0 | G9: =-G5*Assumptions!G26 -> -181.84633 | H9: =-H5*Assumptions!H26 -> -194.28984 | I9: =-I5*Assumptions!I26 -> -219.35707 | J9: =-J5*Assumptions!J26 -> -764.77684 | K9: =-K5*Assumptions!K26 -> -855.4086 | ... M9: =-M5*Assumptions!M26 -> -921.79487 | Q9: 0.03 | R9: 13407.446 | S9: 12199.414 | T9: 10552.558 | U9: 10312.51 | V9: 9562.6715
B10: FCFF | D10: =SUM(D5:D9) -> 1539.9676 | E10: =SUM(E5:E9) -> 483.8638 | F10: =SUM(F5:F9) -> 1536.5496 | G10: =SUM(G5:G9) -> 1473.1005 | H10: =SUM(H5:H9) -> 1640.7853 | I10: =SUM(I5:I9) -> 2068.5803 | J10: =SUM(J5:J9) -> 1622.4345 | K10: =SUM(K5:K9) -> 2030.0411 | ... M10: =SUM(M5:M9) -> 2143.5723 | Q10: 0.04 | R10: 14006.687 | S10: 12661.033 | T10: 10858.866 | U10: 10599.188 | V10: 9792.8055
B11: Terminal Value | M11: =M10*(1+C16)/(C15-C16) -> 17542.291 | Q11: 0.05 | R11: 14739.094 | S11: 13214.975 | T11: 11217.497 | U11: 10933.646 | V11: 10058.345
B12: Total FCFF | D12: =SUM(D10:D11) -> 1539.9676 | E12: =SUM(E10:E11) -> 483.8638 | F12: =SUM(F10:F11) -> 1536.5496 | G12: =SUM(G10:G11) -> 1473.1005 | H12: =SUM(H10:H11) -> 1640.7853 | I12: =SUM(I10:I11) -> 2068.5803 | J12: =SUM(J10:J11) -> 1622.4345 | K12: =SUM(K10:K11) -> 2030.0411 | ... M12: =SUM(M10:M11) -> 19685.863
B14: Period | D14: 1 | E14: 2 | F14: 3 | G14: 4 | H14: 5 | I14: 6 | J14: 7 | K14: 8 | L14: 9 | M14: 10 | P14: Sensitivity Anaysis - Per Share Value
B15: WACC | C15: ='WACC Calculation'!J19 -> 0.16708233 | P15: Growth Rate (g) | R15: WACC
B16: Growth Rate (g) | C16: =Assumptions!D38 -> 0.04 | Q16: =C26 -> 287.05561 | R16: 0.14 | S16: 0.15 | T16: 0.16708233 | U16: 0.17 | V16: 0.18
Q17: 0.02 | R17: 354.70237 | S17: 318.41441 | T17: 268.20744 | U17: 260.81807 | V17: 237.61944
B18: PV of FCFF | D18: =D12/(1+$C$15)^D14 -> 1319.5021 | E18: =E12/(1+$C$15)^E14 -> 355.2386 | F18: =F12/(1+$C$15)^F14 -> 966.58956 | G18: =G12/(1+$C$15)^G14 -> 794.01077 | H18: =H12/(1+$C$15)^H14 -> 757.78199 | I18: =I12/(1+$C$15)^I14 -> 818.5843 | J18: =J12/(1+$C$15)^J14 -> 550.11909 | K18: =K12/(1+$C$15)^K14 -> 589.78383 | ... M18: =M12/(1+$C$15)^M14 -> 4198.9384 | Q18: 0.03 | R18: 371.18706 | S18: 331.30857 | T18: 276.94405 | U18: 269.01981 | V18: 244.26679
Q19: 0.04 | R19: 390.96868 | S19: 346.54712 | T19: 287.05561 | U19: 278.48336 | V19: 251.86377
Q20: 0.05 | R20: 415.14622 | S20: 364.83339 | T20: 298.89442 | U20: 289.52417 | V20: 260.62952
B21: Enterprise Value | C21: =SUM(D18:M18) -> 10858.866
B22: Add: Cash | C22: ='Balance Sheet'!G7 -> 506.5457
B23: Less: Debt | C23: ='Historical FS'!G69 -> 2669.6837
B24: Equity Value | C24: =C21-C23+C22 -> 8695.728
B25: Shares Outstanding (Crores) | C25: ='Income Statement'!G38 -> 30.292834
B26: Estimated Per Share Value | C26: =C24/C25 -> 287.05561

Sheet WACC Calculation
B2: Weighted Average Cost of Capital
B3: Cost of Debt | G3: Cost of Equity
B5: Pre-tax Cost of Debt | E5: =Assumptions!D54 -> 0.1192 | G5: Risk Free Rate | J5: =Assumptions!D35-Assumptions!D36 -> 0.022829513
B6: Tax Rate | E6: =Assumptions!D48 -> 0.225 | G6: Equity Risk Premium | J6: =Assumptions!D37 -> 0.1235
B7: After Tax Cost of Debt | E7: =E5*(1-E6) -> 0.09238 | G7: Beta (β) | J7: =J34 -> 1.2961417
G8: Cost of Equity | J8: =J5+(J6*J7) -> 0.18290301
B11: Capital Structure | G11: Weighted Average Cost of Capital
D13: 2025A | E13: Current | G13: Cost of Equity | J13: =J8 -> 0.18290301
B14: Total Debt | D14: ='Historical FS'!G69 -> 2669.6837 | E14: =D14/$D$16 -> 0.17476966 | G14: Equity Weight | J14: =E15 -> 0.82523034
B15: Market Capitalization | D15: =Data!C9/10 -> 12605.757 | E15: =D15/$D$16 -> 0.82523034
B16: Total Capitalization | D16: =SUM(D14:D15) -> 15275.441 | E16: =D16/$D$16 -> 1 | G16: Cost of Debt | J16: =E7 -> 0.09238
G17: Debt Weight | J17: =E14 -> 0.17476966
B18: Debt / Equity | E18: =E14/E15 -> 0.21178289
G19: WACC | J19: =(J13*J14)+(J16*J17) -> 0.16708233
B24: Beta Calculation [Regression - 5 Years Monthly]:
B26: WALTONHIL Monthly Return | F26: DSEX Monthly Return | I26: Beta Drifting
B28: Date | C28: Price | D28: Return | F28: Price | G28: Return | I28: Levered Raw Beta | J28: =J56 -> 1.4442125
B29: 44136 | C29: 699.8 | F29: 4866.84 | I29: Raw Beta Weight | J29: =2/3 -> 0.66666667
B30: 44166 | C30: 1113.8 | D30: =C30/C29-1 -> 0.5915976 | F30: 5402.06 | G30: =F30/F29-1 -> 0.1099728
B31: 44197 | C31: 1047.4 | D31: =C31/C30-1 -> -0.05961573 | F31: 5649.86 | G31: =F31/F30-1 -> 0.04587139 | I31: Market Beta | J31: 1
B32: 44228 | C32: 1220.5 | D32: =C32/C31-1 -> 0.16526637 | F32: 5404.79 | G32: =F32/F31-1 -> -0.043376296 | I32: Market Beta Weight | J32: =1/3 -> 0.33333333
B33: 44256 | C33: 1192.9 | D33: =C33/C32-1 -> -0.022613683 | F33: 5278.16 | G33: =F33/F32-1 -> -0.023429217
B34: 44287 | C34: 1190.1 | D34: =C34/C33-1 -> -0.0023472211 | F34: 5479.61 | G34: =F34/F33-1 -> 0.03816671 | I34: Bloomberg Adjusted Beta | J34: =(J28*J29)+(J31*J32) -> 1.2961417
B35: 44317 | C35: 1274 | D35: =C35/C34-1 -> 0.070498277 | F35: 5990.98 | G35: =F35/F34-1 -> 0.093322335
B36: 44348 | C36: 1340 | D36: =C36/C35-1 -> 0.051805338 | F36: 6150.48 | G36: =F36/F35-1 -> 0.026623357
B37: 44378 | C37: 1397.3 | D37: =C37/C36-1 -> 0.042761194 | F37: 6425.25 | G37: =F37/F36-1 -> 0.044674562
B38: 44409 | C38: 1394.5 | D38: =C38/C37-1 -> -0.0020038646 | F38: 6869.24 | G38: =F38/F37-1 -> 0.069100813
B39: 44440 | C39: 1276.1 | D39: =C39/C38-1 -> -0.084904984 | F39: 7329.03 | G39: =F39/F38-1 -> 0.066934624 | I39: SUMMARY OUTPUT
B40: 44470 | C40: 1165.7 | D40: =C40/C39-1 -> -0.086513596 | F40: 7000.94 | G40: =F40/F39-1 -> -0.044765815
B41: 44501 | C41: 1102.7 | D41: =C41/C40-1 -> -0.05404478 | F41: 6703.25 | G41: =F41/F40-1 -> -0.042521433 | I41: Regression Statistics
B42: 44531 | C42: 1148.8 | D42: =C42/C41-1 -> 0.041806475 | F42: 6756.65 | G42: =F42/F41-1 -> 0.007966285 | I42: Multiple R | J42: 0.54319181
B43: 44562 | C43: 1061.5 | D43: =C43/C42-1 -> -0.07599234 | F43: 6926.29 | G43: =F43/F42-1 -> 0.025107117 | I43: R Square | J43: 0.29505734
B44: 44593 | C44: 1107.2 | D44: =C44/C43-1 -> 0.043052285 | F44: 6739.44 | G44: =F44/F43-1 -> -0.026976924 | I44: Adjusted R Square | J44: 0.28246908
B45: 44621 | C45: 1076.1 | D45: =C45/C44-1 -> -0.028088873 | F45: 6757.83 | G45: =F45/F44-1 -> 0.0027287134 | I45: Standard Error | J45: 0.096931743
B46: 44652 | C46: 1162.4 | D46: =C46/C45-1 -> 0.080197008 | F46: 6655.66 | G46: =F46/F45-1 -> -0.015118759 | I46: Observations | J46: 58
B47: 44682 | C47: 1075.5 | D47: =C47/C46-1 -> -0.074759119 | F47: 6392.85 | G47: =F47/F46-1 -> -0.039486693
B48: 44713 | C48: 1093.9 | D48: =C48/C47-1 -> 0.017108322 | F48: 6376.94 | G48: =F48/F47-1 -> -0.0024887179 | I48: ANOVA
B49: 44743 | C49: 1050.1 | D49: =C49/C48-1 -> -0.040040223 | F49: 6133.96 | G49: =F49/F48-1 -> -0.038102915 | J49: df | K49: SS | L49: MS | M49: F | N49: Significance F
B50: 44774 | C50: 1047.9 | D50: =C50/C49-1 -> -0.0020950386 | F50: 6457.22 | G50: =F50/F49-1 -> 0.05270005 | I50: Regression | J50: 1 | K50: 0.22022809 | L50: 0.22022809 | M50: 23.439086 | N50: 1.0540775e-05
B51: 44805 | C51: 1047.7 | D51: =C51/C50-1 -> -0.00019085791 | F51: 6515.11 | G51: =F51/F50-1 -> 0.0089651584 | I51: Residual | J51: 56 | K51: 0.52616272 | L51: 0.0093957628
B52: 44835 | C52: 1047.7 | D52: =C52/C51-1 -> 0 | F52: 6307.34 | G52: =F52/F51-1 -> -0.031890482 | I52: Total | J52: 57 | K52: 0.7463908
B53: 44866 | C53: 1047.7 | D53: =C53/C52-1 -> 0 | F53: 6235.95 | G53: =F53/F52-1 -> -0.011318559
B54: 44896 | C54: 1047.7 | D54: =C54/C53-1 -> 0 | F54: 6206.81 | G54: =F54/F53-1 -> -0.0046729047 | J54: Coefficients | K54: Standard Error | L54: t Stat | M54: P-value | N54: Lower 95% | O54: Upper 95% | P54: Lower 95.0% | Q54: Upper 95.0%
B55: 44927 | C55: 1047.7 | D55: =C55/C54-1 -> 0 | F55: 6267.05 | G55: =F55/F54-1 -> 0.0097054687 | I55: Intercept | J55: -0.0070213654 | K55: 0.012753877 | L55: -0.5505279 | M55: 0.58414688 | N55: -0.032570452 | O55: 0.018527721 | P55: -0.032570452 | Q55: 0.018527721
B56: 44958 | C56: 1047.7 | D56: =C56/C55-1 -> 0 | F56: 6216.95 | G56: =F56/F55-1 -> -0.0079941918 | I56: WALTONHIL Return | J56: 1.4442125 | K56: 0.29830516 | L56: 4.8413929 | M56: 1.0540775e-05 | N56: 0.84663547 | O56: 2.0417896 | P56: 0.84663547 | Q56: 2.0417896
B57: 44986 | C57: 1047.7 | D57: =C57/C56-1 -> 0 | F57: 6206.8 | G57: =F57/F56-1 -> -0.0016326334
B58: 45017 | C58: 1047.7 | D58: =C58/C57-1 -> 0 | F58: 6262.69 | G58: =F58/F57-1 -> 0.0090046401
B59: 45047 | C59: 1047.7 | D59: =C59/C58-1 -> 0 | F59: 6339.74 | G59: =F59/F58-1 -> 0.01230302
B60: 45078 | C60: 1047.7 | D60: =C60/C59-1 -> 0 | F60: 6344.09 | G60: =F60/F59-1 -> 0.00068614801
B61: 45108 | C61: 1047.7 | D61: =C61/C60-1 -> 0 | F61: 6324.81 | G61: =F61/F60-1 -> -0.0030390489
B62: 45139 | C62: 1047.7 | D62: =C62/C61-1 -> 0 | F62: 6299.5 | G62: =F62/F61-1 -> -0.0040017012
B63: 45170 | C63: 1047.7 | D63: =C63/C62-1 -> 0 | F63: 6284.63 | G63: =F63/F62-1 -> -0.0023605048
B64: 45200 | C64: 1047.7 | D64: =C64/C63-1 -> 0 | F64: 6278.66 | G64: =F64/F63-1 -> -0.00094993659
B65: 45231 | C65: 1047.7 | D65: =C65/C64-1 -> 0 | F65: 6223.03 | G65: =F65/F64-1 -> -0.0088601708
B66: 45261 | C66: 1047.7 | D66: =C66/C65-1 -> 0 | F66: 6246.5 | G66: =F66/F65-1 -> 0.0037714747
B67: 45292 | C67: 752.8 | D67: =C67/C66-1 -> -0.2814737 | F67: 6153.34 | G67: =F67/F66-1 -> -0.014913952
B68: 45323 | C68: 745.5 | D68: =C68/C67-1 -> -0.0096971307 | F68: 6254.54 | G68: =F68/F67-1 -> 0.016446353
... B87: 45901 | C87: 419.9 | D87: =C87/C86-1 -> -0.058330156 | F87: 5415.79 | G87: =F87/F86-1 -> -0.031924839

Sheet Depreciation Schedule
B2: Depreciation and Amortization Schedule
B3: Year | C3: 2025 | D3: 2026 | E3: 2027 | F3: 2028 | G3: 2029 | H3: 2030 | I3: 2031 | J3: 2032 | K3: 2033 | L3: 2034 | M3: 2035
B4: Operating Assets
B5: Property, Plant & Equipment | C5: ='Balance Sheet'!G16 -> 7718.042
B6: Right-of-Use Assets | C6: ='Balance Sheet'!G17 -> 21.172201
B7: Intangible Assets | C7: ='Balance Sheet'!G18 -> 4.6082639
B8: Opening Operating Assets | C8: =SUM(C5:C7) -> 7743.8225 | D8: =C11 -> 7743.8225 | E8: =D11 -> 8198.232 | F8: =E11 -> 8649.5824 | G8: =F11 -> 9139.2435 | H8: =G11 -> 9665.5073 | I8: =H11 -> 10224.231 | J8: =I11 -> 10807.046 | K8: =J11 -> 11412.984 | ... M8: =L11 -> 12688.36
B9: Add: CapEx | D9: =-'Cash Flow Statement'!H19 -> 704.00984 | E9: =-'Cash Flow Statement'!I19 -> 715.59742 | F9: =-'Cash Flow Statement'!J19 -> 768.45601 | G9: =-'Cash Flow Statement'!K19 -> 820.84167 | H9: =-'Cash Flow Statement'!L19 -> 870.26457 | I9: =-'Cash Flow Statement'!M19 -> 912.36404 | J9: =-'Cash Flow Statement'!N19 -> 954.27271 | K9: =-'Cash Flow Statement'!O19 -> 996.20373 | ... M9: =-'Cash Flow Statement'!Q19 -> 1073.5168
B10: Less: D&A (% of Opening Assets) | D10: =D8*Assumptions!D25 -> 249.60035 | E10: =E8*Assumptions!E25 -> 264.24696 | F10: =F8*Assumptions!F25 -> 278.79498 | G10: =G8*Assumptions!G25 -> 294.57782 | H10: =H8*Assumptions!H25 -> 311.54046 | I10: =I8*Assumptions!I25 -> 329.54936 | J10: =J8*Assumptions!J25 -> 348.33475 | K10: =K8*Assumptions!K25 -> 367.86546 | ... M10: =M8*Assumptions!M25 -> 408.97362
B11: Closing Operating Assets | C11: =C8+C9-C10 -> 7743.8225 | D11: =D8+D9-D10 -> 8198.232 | E11: =E8+E9-E10 -> 8649.5824 | F11: =F8+F9-F10 -> 9139.2435 | G11: =G8+G9-G10 -> 9665.5073 | H11: =H8+H9-H10 -> 10224.231 | I11: =I8+I9-I10 -> 10807.046 | J11: =J8+J9-J10 -> 11412.984 | ... M11: =M8+M9-M10 -> 13352.903

Sheet Working Capital Schedule
B2: Working Capital Schedule
C3: 2021 | D3: 2022 | E3: 2023 | F3: 2024 | G3: 2025 | H3: 2026 | I3: 2027 | J3: 2028 | K3: 2029 | L3: 2030 | M3: 2031 | N3: 2032 | O3: 2033 | P3: 2034 | Q3: 2035
B4: Current assets: | S4: Note: Historical DIO/DSO/DPO based on average balances
B5: Inventories | C5: ='Balance Sheet'!C10 -> 2413.0562 | D5: ='Balance Sheet'!D10 -> 3619.7619 | E5: ='Balance Sheet'!E10 -> 2557.3533 | F5: ='Balance Sheet'!F10 -> 2618.2664 | G5: ='Balance Sheet'!G10 -> 2964.874 | H5: =(H6/365)*'Income Statement'!H8 -> 2633.5904 | I5: =(I6/365)*'Income Statement'!I8 -> 3192.3283 | J5: =(J6/365)*'Income Statement'!J8 -> 3374.5694 | K5: =(K6/365)*'Income Statement'!K8 -> 3604.6138 | L5: =(L6/365)*'Income Statement'!L8 -> 3821.6478 | M5: =(M6/365)*'Income Statement'!M8 -> 3942.9262 | N5: =(N6/365)*'Income Statement'!N8 -> 4124.0412 | O5: =(O6/365)*'Income Statement'!O8 -> 4166.3737 | ... Q5: =(Q6/365)*'Income Statement'!Q8 -> 4489.7163
B6: Days Inventory Outstanding (DIO) | D6: =(AVERAGE(C5:D5)/'Income Statement'!D8)*365 -> 199.64691 | E6: =(AVERAGE(D5:E5)/'Income Statement'!E8)*365 -> 262.02887 | F6: =(AVERAGE(E5:F5)/'Income Statement'!F8)*365 -> 203.24618 | G6: =(AVERAGE(F5:G5)/'Income Statement'!G8)*365 -> 224.96917 | H6: 200 | I6: 200 | J6: 200 | K6: 200 | L6: 200 | M6: 200 | N6: 200 | O6: 200 | P6: 200 | Q6: 200
B7: Accounts Receivable | C7: ='Balance Sheet'!C9 -> 3288.1935 | D7: ='Balance Sheet'!D9 -> 4189.4179 | E7: ='Balance Sheet'!E9 -> 3467.4948 | F7: ='Balance Sheet'!F9 -> 3724.663 | G7: ='Balance Sheet'!G9 -> 3606.624 | H7: =(H8/365)*'Income Statement'!H6 -> 3703.4865 | I7: =(I8/365)*'Income Statement'!I6 -> 4489.2116 | J7: =(J8/365)*'Income Statement'!J6 -> 4820.8134 | K7: =(K8/365)*'Income Statement'!K6 -> 5149.4484 | L7: =(L8/365)*'Income Statement'!L6 -> 5459.4968 | M7: =(M8/365)*'Income Statement'!M6 -> 5723.6026 | N7: =(N8/365)*'Income Statement'!N6 -> 5986.5114 | O7: =(O8/365)*'Income Statement'!O6 -> 6249.5605 | ... Q7: =(Q8/365)*'Income Statement'!Q6 -> 6734.5744
B8: Days Sales Outstanding (DSO) | D8: =(AVERAGE(C7:D7)/'Income Statement'!D6)*365 -> 167.07101 | E8: =(AVERAGE(D7:E7)/'Income Statement'!E6)*365 -> 210.53136 | F8: =(AVERAGE(E7:F7)/'Income Statement'!F6)*365 -> 174.72692 | G8: =(AVERAGE(F7:G7)/'Income Statement'!G6)*365 -> 188.91741 | H8: 180 | I8: 180 | J8: 180 | K8: 180 | L8: 180 | M8: 180 | N8: 180 | O8: 180 | P8: 180 | Q8: 180
B9: Prepaid Expenses | C9: ='Balance Sheet'!C11 -> 500.89681 | D9: ='Balance Sheet'!D11 -> 553.65029 | E9: ='Balance Sheet'!E11 -> 551.76371 | F9: ='Balance Sheet'!F11 -> 767.17047 | G9: ='Balance Sheet'!G11 -> 148.61545 | H9: =(H10/365)*'Income Statement'!H13 -> 370.34865 | I9: =(I10/365)*'Income Statement'!I13 -> 437.69814 | J9: =(J10/365)*'Income Statement'!J13 -> 457.97728 | K9: =(K10/365)*'Income Statement'!K13 -> 480.61518 | L9: =(L10/365)*'Income Statement'!L13 -> 500.45387 | M9: =(M10/365)*'Income Statement'!M13 -> 476.96688 | N9: =(N10/365)*'Income Statement'!N13 -> 498.87595 | O9: =(O10/365)*'Income Statement'!O13 -> 520.79671 | ... Q9: =(Q10/365)*'Income Statement'!Q13 -> 561.21453
B10: Days prepaid | D10: =(AVERAGE(C9:D9)/'Income Statement'!D13)*365 -> 209.54259 | E10: =(AVERAGE(D9:E9)/'Income Statement'!E13)*365 -> 259.20673 | F10: =(AVERAGE(E9:F9)/'Income Statement'!F13)*365 -> 244.34872 | G10: =(AVERAGE(F9:G9)/'Income Statement'!G13)*365 -> 156.05838 | H10: 150 | I10: 150 | J10: 150 | K10: 150 | L10: 150 | M10: 150 | N10: 150 | O10: 150 | P10: 150 | Q10: 150
B11: Total Current Assets | C11: =C5+C7+C9 -> 6202.1465 | D11: =D5+D7+D9 -> 8362.8301 | E11: =E5+E7+E9 -> 6576.6119 | F11: =F5+F7+F9 -> 7110.0998 | G11: =G5+G7+G9 -> 6720.1134 | H11: =H5+H7+H9 -> 6707.4255 | I11: =I5+I7+I9 -> 8119.2381 | J11: =J5+J7+J9 -> 8653.3601 | ... Q11: =Q5+Q7+Q9 -> 11785.505
B13: Current liabilities
B14: Accounts Payable | C14: ='Balance Sheet'!C26 -> 292.33228 | D14: ='Balance Sheet'!D26 -> 458.14572 | E14: ='Balance Sheet'!E26 -> 305.80097 | F14: ='Balance Sheet'!F26 -> 363.01136 | G14: ='Balance Sheet'!G26 -> 240.30518 | H14: =(H15/365)*'Income Statement'!H8 -> 395.03856 | I14: =(I15/365)*'Income Statement'!I8 -> 478.84924 | J14: =(J15/365)*'Income Statement'!J8 -> 506.18541 | K14: =(K15/365)*'Income Statement'!K8 -> 540.69208 | L14: =(L15/365)*'Income Statement'!L8 -> 573.24717 | M14: =(M15/365)*'Income Statement'!M8 -> 591.43893 | N14: =(N15/365)*'Income Statement'!N8 -> 618.60618 | O14: =(O15/365)*'Income Statement'!O8 -> 624.95605 | ... Q14: =(Q15/365)*'Income Statement'!Q8 -> 673.45744
B15: Days Payable Outstanding (DPO) | D15: =(AVERAGE(C14:D14)/'Income Statement'!D8*365) -> 24.835925 | E15: =(AVERAGE(D14:E14)/'Income Statement'!E8*365) -> 32.406079 | F15: =(AVERAGE(E14:F14)/'Income Statement'!F8*365) -> 26.264207 | G15: =(AVERAGE(F14:G14)/'Income Statement'!G8*365) -> 24.310264 | H15: 30 | I15: =$H$15 -> 30 | J15: =$H$15 -> 30 | K15: =$H$15 -> 30 | L15: =$H$15 -> 30 | M15: =$H$15 -> 30 | N15: =$H$15 -> 30 | O15: =$H$15 -> 30 | P15: =$H$15 -> 30 | Q15: =$H$15 -> 30
B16: Accrued Expenses | C16: ='Balance Sheet'!C27 -> 704.55801 | D16: ='Balance Sheet'!D27 -> 626.12201 | E16: ='Balance Sheet'!E27 -> 652.17449 | F16: ='Balance Sheet'!F27 -> 790.42642 | G16: ='Balance Sheet'!G27 -> 531.66138 | H16: =(H17/365)*'Income Statement'!H13 -> 556.25371 | I16: =(I17/365)*'Income Statement'!I13 -> 657.41084 | J16: =(J17/365)*'Income Statement'!J13 -> 687.86956 | K16: =(K17/365)*'Income Statement'!K13 -> 721.87108 | L16: =(L17/365)*'Income Statement'!L13 -> 751.66827 | M16: =(M17/365)*'Income Statement'!M13 -> 716.39144 | N16: =(N17/365)*'Income Statement'!N13 -> 749.29828 | O16: =(O17/365)*'Income Statement'!O13 -> 782.22266 | ... Q16: =(Q17/365)*'Income Statement'!Q13 -> 842.92915
B17: Days acrrued expenses payable | D17: =(AVERAGE(C16:D16)/'Income Statement'!D13)*365 -> 264.41127 | E17: =(AVERAGE(D16:E16)/'Income Statement'!E13)*365 -> 299.74566 | F17: =(AVERAGE(E16:F16)/'Income Statement'!F13)*365 -> 267.25949 | G17: =(AVERAGE(F16:G16)/'Income Statement'!G13)*365 -> 225.29597 | H17: =G17 -> 225.29597 | I17: =$H$17 -> 225.29597 | J17: =$H$17 -> 225.29597 | K17: =$H$17 -> 225.29597 | L17: =$H$17 -> 225.29597 | M17: =$H$17 -> 225.29597 | N17: =$H$17 -> 225.29597 | O17: =$H$17 -> 225.29597 | P17: =$H$17 -> 225.29597 | Q17: =$H$17 -> 225.29597
B18: Total Current Liabilities | C18: =C14+C16 -> 996.8903 | D18: =D14+D16 -> 1084.2677 | E18: =E14+E16 -> 957.97546 | F18: =F14+F16 -> 1153.4378 | G18: =G14+G16 -> 771.96656 | H18: =H14+H16 -> 951.29227 | I18: =I14+I16 -> 1136.2601 | J18: =J14+J16 -> 1194.055 | ... Q18: =Q14+Q16 -> 1516.3866
B20: Total Operating Working Capital | C20: =C11-C18 -> 5205.2562 | D20: =D11-D18 -> 7278.5624 | E20: =E11-E18 -> 5618.6364 | F20: =F11-F18 -> 5956.662 | G20: =G11-G18 -> 5948.1469 | H20: =H11-H18 -> 5756.1332 | I20: =I11-I18 -> 6982.978 | J20: =J11-J18 -> 7459.3052 | ... Q20: =Q11-Q18 -> 10269.119

Sheet Debt Schedule
B2: Debt Schedule
B3: Year | C3: 2025 | D3: 2026 | E3: 2027 | F3: 2028 | G3: 2029 | H3: 2030 | I3: 2031 | J3: 2032 | K3: 2033 | L3: 2034 | M3: 2035 | R3: Finance Costs | S3: 2021 to 2022 (Taka) | T3: 2020 to 2021 (Taka)
B4: Cash available to pay down debt | R4: Interest on Short Term Loan | S4: 56.621139 | T4: 12.131552
B5: Cash at beginning of year | C5: ='Balance Sheet'!F7 -> 654.73263 | D5: ='Balance Sheet'!G7 -> 506.5457 | E5: ='Balance Sheet'!H7 -> 1039.4704 | F5: ='Balance Sheet'!I7 -> 341.02842 | G5: ='Balance Sheet'!J7 -> 535.22305 | H5: ='Balance Sheet'!K7 -> 676.06352 | I5: ='Balance Sheet'!L7 -> 907.74635 | J5: ='Balance Sheet'!M7 -> 1420.3644 | ... M5: ='Balance Sheet'!P7 -> 2784.7621 | P5: On | R5: Interest on Term Loan | S5: 16.827933 | T5: 29.043754
B6: Cash flow before debt paydown | D6: ='Cash Flow Statement'!H40 -> 532.92469 | E6: ='Cash Flow Statement'!I40 -> -698.44197 | F6: ='Cash Flow Statement'!J40 -> 194.19463 | G6: ='Cash Flow Statement'!K40 -> 140.84048 | H6: ='Cash Flow Statement'!L40 -> 231.68283 | I6: ='Cash Flow Statement'!M40 -> 512.61801 | J6: ='Cash Flow Statement'!N40 -> 281.69675 | K6: ='Cash Flow Statement'!O40 -> 557.62937 | ... M6: ='Cash Flow Statement'!Q40 -> 583.24356 | P6: Off | R6: Interest on Acceptance | S6: 70.825844 | T6: 49.543492
B7: Minimum cash cushion | D7: -50 | E7: -50 | F7: -50 | G7: -50 | H7: -50 | I7: -50 | J7: -50 | K7: -50 | L7: -50 | M7: -50 | R7: Interest Expense - Lease | S7: 1.6353047 | T7: 0
B8: Total cash available to pay down debt | D8: =SUM(D5:D7) -> 989.47039 | E8: =SUM(E5:E7) -> 291.02842 | F8: =SUM(F5:F7) -> 485.22305 | G8: =SUM(G5:G7) -> 626.06352 | H8: =SUM(H5:H7) -> 857.74635 | I8: =SUM(I5:I7) -> 1370.3644 | J8: =SUM(J5:J7) -> 1652.0611 | K8: =SUM(K5:K7) -> 2209.6905 | ... M8: =SUM(M5:M7) -> 3318.0057 | R8: Excise Duty, Bank Charges & Others | S8: 23.775444 | T8: 15.303684
R9: Exchange Loss or (Gain) on Foreign Currency (Note: 33.01) | S9: 304.13265 | T9: 18.545194
D10: Switch | E10: Off | R10: Total | S10: 473.83251 | T10: 124.56768
B11: Short-term Debt/ Revolver | E11: =IF(E10="On", 1, 0) -> 0
B12: Short-term Debt (beginning of year) | C12: ='Balance Sheet'!F28 -> 2124.3602 | D12: =C15 -> 1788.3977 | E12: =D15 -> 1788.3977 | F12: =E15 -> 1788.3977 | G12: =F15 -> 1788.3977 | H12: =G15 -> 1788.3977 | I12: =H15 -> 1788.3977 | J12: =I15 -> 1788.3977 | K12: =J15 -> 1788.3977 | ... M12: =L15 -> 1788.3977 | R12: Finance Costs | S12: 2022 to 2023 (Taka) | T12: 2021 to 2022 (Taka)
B13: Mandatory issuances / (retirements) | D13: 0 | E13: 0 | F13: 0 | G13: 0 | H13: 0 | I13: 0 | J13: 0 | K13: 0 | L13: 0 | M13: 0 | R13: Interest on Short Term Loan | S13: 140.02899 | T13: 56.621139
B14: Non-mandatory issuances / (retirements) | D14: =MIN(-(MIN(D8,D12)*$E$11), 8950) -> 0 | E14: =MIN(-(MIN(E8,E12)*$E$11), 8950) -> 0 | F14: =MIN(-(MIN(F8,F12)*$E$11), 8950) -> 0 | G14: =MIN(-(MIN(G8,G12)*$E$11), 8950) -> 0 | H14: =MIN(-(MIN(H8,H12)*$E$11), 8950) -> 0 | I14: =MIN(-(MIN(I8,I12)*$E$11), 8950) -> 0 | J14: =MIN(-(MIN(J8,J12)*$E$11), 8950) -> 0 | K14: =MIN(-(MIN(K8,K12)*$E$11), 8950) -> 0 | ... M14: =MIN(-(MIN(M8,M12)*$E$11), 8950) -> 0 | R14: Interest on Term Loan | S14: 32.124339 | T14: 16.827933
B15: Short-term Debt (end of year) | C15: ='Balance Sheet'!G28 -> 1788.3977 | D15: =SUM(D12:D14) -> 1788.3977 | E15: =SUM(E12:E14) -> 1788.3977 | F15: =SUM(F12:F14) -> 1788.3977 | G15: =SUM(G12:G14) -> 1788.3977 | H15: =SUM(H12:H14) -> 1788.3977 | I15: =SUM(I12:I14) -> 1788.3977 | J15: =SUM(J12:J14) -> 1788.3977 | K15: =SUM(K12:K14) -> 1788.3977 | ... M15: =SUM(M12:M14) -> 1788.3977 | R15: Interest on Acceptance | S15: 93.92814 | T15: 70.825844
B16: Interest on Short Term Debt | C16: =(S22+S24) -> 236.63736 | D16: =AVERAGE(D12,D15)*D17 -> 216.31888 | E16: =AVERAGE(E12,E15)*E17 -> 216.31888 | F16: =AVERAGE(F12,F15)*F17 -> 216.31888 | G16: =AVERAGE(G12,G15)*G17 -> 216.31888 | H16: =AVERAGE(H12,H15)*H17 -> 216.31888 | I16: =AVERAGE(I12,I15)*I17 -> 216.31888 | J16: =AVERAGE(J12,J15)*J17 -> 216.31888 | K16: =AVERAGE(K12,K15)*K17 -> 216.31888 | ... M16: =AVERAGE(M12,M15)*M17 -> 216.31888 | R16: Interest Expense - Lease | S16: 1.8755619 | T16: 1.4553047
B17: Short-term interest rate | C17: =C16/AVERAGE(C12,C15) -> 0.12095681 | D17: =C17 -> 0.12095681 | E17: =D17 -> 0.12095681 | F17: =E17 -> 0.12095681 | G17: =F17 -> 0.12095681 | H17: =G17 -> 0.12095681 | I17: =H17 -> 0.12095681 | J17: =I17 -> 0.12095681 | K17: =J17 -> 0.12095681 | ... M17: =L17 -> 0.12095681 | R17: Excise Duty, Bank Charges & Others | S17: 16.352193 | T17: 23.775444
R18: Exchange Loss or (Gain) on Foreign Currency (Note: 33.01) | S18: 469.27632 | T18: 304.32685
B19: Long-term Debt | R19: Total | S19: 753.5856 | T19: 473.83251
B20: Long-term Debt (beginning of year) | C20: ='Balance Sheet'!F35+'Balance Sheet'!F29 -> 829.7931 | D20: =C23 -> 857.37658 | E20: =D23 -> 857.37658 | F20: =E23 -> 857.37658 | G20: =F23 -> 857.37658 | H20: =G23 -> 857.37658 | I20: =H23 -> 857.37658 | J20: =I23 -> 857.37658 | K20: =J23 -> 857.37658 | ... M20: =L23 -> 857.37658
B21: Mandatory issuances / (retirements) | D21: 0 | E21: 0 | F21: 0 | G21: 0 | H21: 0 | I21: 0 | J21: 0 | K21: 0 | L21: 0 | M21: 0 | R21: Finance Costs | S21: 2024 to 2025 (Taka) | T21: 2023 to 2024 (Taka)
B22: Non-mandatory issuances / (retirements) | D22: 0 | E22: 0 | F22: 0 | G22: 0 | H22: 0 | I22: 0 | J22: 0 | K22: 0 | L22: 0 | M22: 0 | R22: Interest on Short Term Loan | S22: 114.43229 | T22: 130.02882
B23: Long-term Debt (end of year) | C23: ='Balance Sheet'!G35+'Balance Sheet'!G29 -> 857.37658 | D23: =SUM(D20:D22) -> 857.37658 | E23: =SUM(E20:E22) -> 857.37658 | F23: =SUM(F20:F22) -> 857.37658 | G23: =SUM(G20:G22) -> 857.37658 | H23: =SUM(H20:H22) -> 857.37658 | I23: =SUM(I20:I22) -> 857.37658 | J23: =SUM(J20:J22) -> 857.37658 | K23: =SUM(K20:K22) -> 857.37658 | ... M23: =SUM(M20:M22) -> 857.37658 | R23: Interest on Term Loan | S23: 63.872179 | T23: 57.137753
B24: Interest on Long-term Debt | C24: =S23 -> 63.872179 | D24: =AVERAGE(D20,D23)*D25 -> 64.916424 | E24: =AVERAGE(E20,E23)*E25 -> 64.916424 | F24: =AVERAGE(F20,F23)*F25 -> 64.916424 | G24: =AVERAGE(G20,G23)*G25 -> 64.916424 | H24: =AVERAGE(H20,H23)*H25 -> 64.916424 | I24: =AVERAGE(I20,I23)*I25 -> 64.916424 | J24: =AVERAGE(J20,J23)*J25 -> 64.916424 | K24: =AVERAGE(K20,K23)*K25 -> 64.916424 | ... M24: =AVERAGE(M20,M23)*M25 -> 64.916424 | R24: Interest on Acceptance | S24: 122.20507 | T24: 93.311605
B25: Long-term interest rate | C25: =C24/AVERAGE(C20,C23) -> 0.075715182 | D25: =C25 -> 0.075715182 | E25: =D25 -> 0.075715182 | F25: =E25 -> 0.075715182 | G25: =F25 -> 0.075715182 | H25: =G25 -> 0.075715182 | I25: =H25 -> 0.075715182 | J25: =I25 -> 0.075715182 | K25: =J25 -> 0.075715182 | ... M25: =L25 -> 0.075715182 | R25: Interest Expense - Lease | S25: 2.0108376 | T25: 1.9974144
R26: Excise Duty, Bank Charges & Others | S26: 22.277175 | T26: 19.194007
B27: Lease Liabilities | R27: Exchange Loss or (Gain) on Foreign Currency | S27: 123.60632 | T27: 157.45398
B28: Lease Liabilities (beginning of year) | C28: ='Balance Sheet'!F36+'Balance Sheet'!F30 -> 22.816553 | D28: =C31 -> 23.909378 | E28: =D31 -> 23.909378 | F28: =E31 -> 23.909378 | G28: =F31 -> 23.909378 | H28: =G31 -> 23.909378 | I28: =H31 -> 23.909378 | J28: =I31 -> 23.909378 | K28: =J31 -> 23.909378 | ... M28: =L31 -> 23.909378 | R28: Total | S28: 448.40387 | T28: 459.12358
B29: Mandatory issuances / (retirements) | D29: 0 | E29: 0 | F29: 0 | G29: 0 | H29: 0 | I29: 0 | J29: 0 | K29: 0 | L29: 0 | M29: 0
B30: Non-mandatory issuances / (retirements) | D30: 0 | E30: 0 | F30: 0 | G30: 0 | H30: 0 | I30: 0 | J30: 0 | K30: 0 | L30: 0 | M30: 0
B31: Lease Liabilities (end of year) | C31: ='Balance Sheet'!G36+'Balance Sheet'!G30 -> 23.909378 | D31: =SUM(D28:D30) -> 23.909378 | E31: =SUM(E28:E30) -> 23.909378 | F31: =SUM(F28:F30) -> 23.909378 | G31: =SUM(G28:G30) -> 23.909378 | H31: =SUM(H28:H30) -> 23.909378 | I31: =SUM(I28:I30) -> 23.909378 | J31: =SUM(J28:J30) -> 23.909378 | K31: =SUM(K28:K30) -> 23.909378 | ... M31: =SUM(M28:M30) -> 23.909378
B32: Interest on Lease Liabilities | C32: =S25 -> 2.0108376 | D32: =AVERAGE(D28,D31)*D33 -> 2.057867 | E32: =AVERAGE(E28,E31)*E33 -> 2.057867 | F32: =AVERAGE(F28,F31)*F33 -> 2.057867 | G32: =AVERAGE(G28,G31)*G33 -> 2.057867 | H32: =AVERAGE(H28,H31)*H33 -> 2.057867 | I32: =AVERAGE(I28,I31)*I33 -> 2.057867 | J32: =AVERAGE(J28,J31)*J33 -> 2.057867 | K32: =AVERAGE(K28,K31)*K33 -> 2.057867 | ... M32: =AVERAGE(M28,M31)*M33 -> 2.057867
B33: Lease Liabilities interest rate | C33: =C32/AVERAGE(C28,C31) -> 0.086069451 | D33: =C33 -> 0.086069451 | E33: =D33 -> 0.086069451 | F33: =E33 -> 0.086069451 | G33: =F33 -> 0.086069451 | H33: =G33 -> 0.086069451 | I33: =H33 -> 0.086069451 | J33: =I33 -> 0.086069451 | K33: =J33 -> 0.086069451 | ... M33: =L33 -> 0.086069451
B35: Total issuances / (retirements) | D35: =D13+D14+D21+D22+D29+D30 -> 0 | E35: =E13+E14+E21+E22+E29+E30 -> 0 | F35: =F13+F14+F21+F22+F29+F30 -> 0 | G35: =G13+G14+G21+G22+G29+G30 -> 0 | H35: =H13+H14+H21+H22+H29+H30 -> 0 | I35: =I13+I14+I21+I22+I29+I30 -> 0 | J35: =J13+J14+J21+J22+J29+J30 -> 0 | K35: =K13+K14+K21+K22+K29+K30 -> 0 | ... M35: =M13+M14+M21+M22+M29+M30 -> 0
B36: Other Finance Costs | C36: =S26+S27 -> 145.8835 | D36: ='Income Statement'!H6*'Debt Schedule'!D37 -> 154.6914 | E36: ='Income Statement'!I6*'Debt Schedule'!E37 -> 187.51046 | F36: ='Income Statement'!J6*'Debt Schedule'!F37 -> 201.36118 | G36: ='Income Statement'!K6*'Debt Schedule'!G37 -> 215.08797 | H36: ='Income Statement'!L6*'Debt Schedule'!H37 -> 228.03843 | I36: ='Income Statement'!M6*'Debt Schedule'!I37 -> 239.0699 | J36: ='Income Statement'!N6*'Debt Schedule'!J37 -> 250.05137 | K36: ='Income Statement'!O6*'Debt Schedule'!K37 -> 261.0387 | ... M36: ='Income Statement'!Q6*'Debt Schedule'!M37 -> 281.29731
B37: % of sales | C37: =C36/'Income Statement'!G6 -> 0.020598475 | D37: =C37 -> 0.020598475 | E37: =D37 -> 0.020598475 | F37: =E37 -> 0.020598475 | G37: =F37 -> 0.020598475 | H37: =G37 -> 0.020598475 | I37: =H37 -> 0.020598475 | J37: =I37 -> 0.020598475 | K37: =J37 -> 0.020598475 | ... M37: =L37 -> 0.020598475
B38: Total interest expense | D38: =D16+D24+D32+D36 -> 437.98458 | E38: =E16+E24+E32+E36 -> 470.80363 | F38: =F16+F24+F32+F36 -> 484.65435 | G38: =G16+G24+G32+G36 -> 498.38115 | H38: =H16+H24+H32+H36 -> 511.3316 | I38: =I16+I24+I32+I36 -> 522.36307 | J38: =J16+J24+J32+J36 -> 533.34454 | K38: =K16+K24+K32+K36 -> 544.33187 | ... M38: =M16+M24+M32+M36 -> 564.59048
B39: Cash at the end of the year | C39: 506.5457 | D39: =D5+D6+D35 -> 1039.4704 | E39: =E5+E6+E35 -> 341.02842 | F39: =F5+F6+F35 -> 535.22305 | G39: =G5+G6+G35 -> 676.06352 | H39: =H5+H6+H35 -> 907.74635 | I39: =I5+I6+I35 -> 1420.3644 | J39: =J5+J6+J35 -> 1702.0611 | K39: =K5+K6+K35 -> 2259.6905 | ... M39: =M5+M6+M35 -> 3368.0057
B40: Interest income | C40: ='Income Statement'!G27 -> 29.033468 | D40: =AVERAGE(D5+D39)*D41 -> 30.920322 | E40: =AVERAGE(E5+E39)*E41 -> 27.609976 | F40: =AVERAGE(F5+F39)*F41 -> 17.525029 | G40: =AVERAGE(G5+G39)*G41 -> 24.225731 | H40: =AVERAGE(H5+H39)*H41 -> 31.676198 | I40: =AVERAGE(I5+I39)*I41 -> 46.562214 | J40: =AVERAGE(J5+J39)*J41 -> 62.44851 | K40: =AVERAGE(K5+K39)*K41 -> 79.235032 | ... M40: =AVERAGE(M5+M39)*M41 -> 123.05536
B41: Interest rate | C41: =C40/AVERAGE(C5,C39) -> 0.0500026 | D41: 0.02 | E41: =D41 -> 0.02 | F41: =E41 -> 0.02 | G41: =F41 -> 0.02 | H41: =G41 -> 0.02 | I41: =H41 -> 0.02 | J41: =I41 -> 0.02 | K41: =J41 -> 0.02 | L41: =K41 -> 0.02 | M41: =L41 -> 0.02
B43: Match? (Y/N) | C43: =IF(EXACT(C39, 'Balance Sheet'!G7), "Y", "N") -> Y | D43: =IF(EXACT(D39, 'Balance Sheet'!H7), "Y", "N") -> Y | E43: =IF(EXACT(E39, 'Balance Sheet'!I7), "Y", "N") -> Y | F43: =IF(EXACT(F39, 'Balance Sheet'!J7), "Y", "N") -> Y | G43: =IF(EXACT(G39, 'Balance Sheet'!K7), "Y", "N") -> Y | H43: =IF(EXACT(H39, 'Balance Sheet'!L7), "Y", "N") -> Y | I43: =IF(EXACT(I39, 'Balance Sheet'!M7), "Y", "N") -> Y | J43: =IF(EXACT(J39, 'Balance Sheet'!N7), "Y", "N") -> Y | ... M43: =IF(EXACT(M39, 'Balance Sheet'!Q7), "Y", "N") -> Y

Sheet Charts
